Workbook
Name ReportFrom: Settings!$B$5
Name ReportTo: Settings!$B$6

Sheet Cover
B2: BEYOND DESIGN
B3: Interior Design & Finishing
B4: ERP workbook — books, statements and import template
B5: Generated 2026-10-01 09:25 · all amounts in EGP · EMPTY TEMPLATE
B7: How to use | C7: Enter data only in the data sheets (blue text). Statements recalculate automatically. Import the whole file back into the app from Import & Export (same sheet and column names).
B8: Report period | C8: Change report_from / report_to on the Settings sheet (rows 5–6).
B9: Blue text | C9: Input cells — safe to edit.
B10: Black text | C10: Formulas — do not overwrite.
B11: Grey columns | C11: Helper formulas (collapsed with [+]); copy them down if you add rows beyond the prepared ones.
B12: Row 3 (grey italic) | C12: An example of the expected format in every data sheet — not imported.
B13: Accounts | C13: Leave account columns blank to use the defaults (by system role), or pick a code.
B14: Model Audit | C14: Must show OK on every line before you rely on the statements.
B16: Sheets
B17: Settings | C17: Company settings & report period
B18: Chart of Accounts | C18: Chart of accounts — edit codes and names freely; Role is the system tag (do not duplicate)
B19: Tax Codes | C19: VAT and withholding-tax codes with their e-invoice (ETA) tax type / sub-type. Rates are editable
B20: Business Units | C20: Business units (cost centres / projects). Overhead % = manual share of shared indirect costs
B21: Parties | C21: Customers & suppliers master — tax registration numbers and addresses are needed for e-invoices
B22: Partners | C22: Partners and their default profit share
B23: Partner Shares | C23: Ownership per business unit (overrides the default share)
B24: Fixed Assets | C24: Fixed asset register (its purchase, depreciation and disposal are journal entries with reference FA:<code>)
B25: Warehouses | C25: Warehouses / stores and their inventory account
B26: Stock Items | C26: Item master
B27: Price List | C27: Unit-rate price list (historical cost × (1 + markup) = client price)
B28: BOQ Lines | C28: Bills of quantities — one row per line; rows with the same BOQ Title + Business Unit form one BOQ
... B48: Model Audit | C48: integrity checks (must all be OK)
B50: Audit status | C50: ='Model Audit'!E11

Sheet Settings
A1: BEYOND DESIGN | SETTINGS
A2: Company settings & report period
A3: e.g. company_name | B3: BEYOND DESIGN
A4: Key | B4: Value
A5: report_from | B5: 46023
A6: report_to | B6: 46387
A7: appearance | B7: {}
A8: backup_keep | B8: 14
A9: bank_account
A10: bank_holder
A11: bank_iban
A12: bank_name
A13: bank_swift
A14: branding | B14: {}
A15: coa_v2 | B15: 1
A16: company_address
A17: company_city
A18: company_cr_no
A19: company_email
A20: company_legal_name
A21: company_name | B21: BEYOND DESIGN
A22: company_phone
A23: company_tagline | B23: Interior Design & Finishing
A24: company_tax_id
A25: company_website
A26: currency | B26: EGP
A27: entry_types
A28: eta_activity_code
A29: eta_branch_id | B29: 0
A30: eta_building
A31: eta_client_id
A32: eta_default_item_code
A33: eta_default_unit | B33: EA
A34: eta_doc_version | B34: 1.0
A35: eta_env | B35: preprod
A36: eta_governate
A37: eta_item_prefix | B37: EG
A38: eta_postal_code
A39: eta_region
A40: eta_signer_url
A41: eta_street
A42: fiscal_year_start | B42: 01-01
A43: font_family | B43: system
A44: font_size | B44: 15
A45: hidden_modules | B45: []
A46: lock_date
A47: menu_labels | B47: {}
A48: new_menu | B48: []
A49: offer_digits | B49: 4
A50: offer_prefix | B50: OFR-
A51: offer_validity_days | B51: 15
A52: regional | B52: {}
A53: reserve_pct | B53: 0.40
A54: units | B54: ["Task", "pcs", "m2", "m.t", "ML", "kg", "ton", "L", "Lump Sum", "عدد", "م٢", "م.ط", "مقطوعية"]

Sheet Chart of Accounts
A1: BEYOND DESIGN | CHART OF ACCOUNTS
A2: Chart of accounts — edit codes and names freely; Role is the system tag (do not duplicate)
A3: e.g. 6095 | B3: Cleaning & Hospitality | C3: Expense | D3: general_admin | H3: Yes
A4: Code | B4: Account Name | C4: Type | D4: Statement Line | E4: Normal Balance | F4: System Role | G4: Arabic Name | H4: Active
A5: 1010 | B5: Cash on Hand | C5: Asset | D5: cash | E5: =IF(OR(C5="Asset",C5="COGS",C5="Expense"),IF(OR(D5="accumulated_depreciation",D5="accumulated_amortization",D5="allowance_doubtful"),"Credit","Debit"),IF(OR(D5="drawings",D5="sales_discount"),"Debit","Credit")) | F5: cash | G5: النقدية بالصندوق | H5: Yes
A6: 1020 | B6: Bank Account | C6: Asset | D6: cash | E6: =IF(OR(C6="Asset",C6="COGS",C6="Expense"),IF(OR(D6="accumulated_depreciation",D6="accumulated_amortization",D6="allowance_doubtful"),"Credit","Debit"),IF(OR(D6="drawings",D6="sales_discount"),"Debit","Credit")) | F6: bank | G6: الحساب البنكي | H6: Yes
A7: 1030 | B7: Petty Cash | C7: Asset | D7: cash | E7: =IF(OR(C7="Asset",C7="COGS",C7="Expense"),IF(OR(D7="accumulated_depreciation",D7="accumulated_amortization",D7="allowance_doubtful"),"Credit","Debit"),IF(OR(D7="drawings",D7="sales_discount"),"Debit","Credit")) | G7: العهد النقدية | H7: Yes
A8: 1035 | B8: Cash Custody with Employees | C8: Asset | D8: other_current_asset | E8: =IF(OR(C8="Asset",C8="COGS",C8="Expense"),IF(OR(D8="accumulated_depreciation",D8="accumulated_amortization",D8="allowance_doubtful"),"Credit","Debit"),IF(OR(D8="drawings",D8="sales_discount"),"Debit","Credit")) | F8: custody | G8: عهد نقدية لدى العاملين | H8: Yes
A9: 1100 | B9: Accounts Receivable — Clients | C9: Asset | D9: receivable | E9: =IF(OR(C9="Asset",C9="COGS",C9="Expense"),IF(OR(D9="accumulated_depreciation",D9="accumulated_amortization",D9="allowance_doubtful"),"Credit","Debit"),IF(OR(D9="drawings",D9="sales_discount"),"Debit","Credit")) | F9: ar | G9: العملاء (المدينون) | H9: Yes
A10: 1120 | B10: Notes Receivable (Cheques Under Collection) | C10: Asset | D10: receivable | E10: =IF(OR(C10="Asset",C10="COGS",C10="Expense"),IF(OR(D10="accumulated_depreciation",D10="accumulated_amortization",D10="allowance_doubtful"),"Credit","Debit"),IF(OR(D10="drawings",D10="sales_discount"),"Debit","Credit")) | F10: notes_receivable | G10: أوراق القبض (شيكات تحت التحصيل) | H10: Yes
A11: 1150 | B11: Retention Receivable | C11: Asset | D11: receivable | E11: =IF(OR(C11="Asset",C11="COGS",C11="Expense"),IF(OR(D11="accumulated_depreciation",D11="accumulated_amortization",D11="allowance_doubtful"),"Credit","Debit"),IF(OR(D11="drawings",D11="sales_discount"),"Debit","Credit")) | G11: محتجزات لدى العملاء (ضمان أعمال) | H11: Yes
A12: 1160 | B12: Employee Advances | C12: Asset | D12: other_current_asset | E12: =IF(OR(C12="Asset",C12="COGS",C12="Expense"),IF(OR(D12="accumulated_depreciation",D12="accumulated_amortization",D12="allowance_doubtful"),"Credit","Debit"),IF(OR(D12="drawings",D12="sales_discount"),"Debit","Credit")) | G12: سلف العاملين | H12: Yes
A13: 1170 | B13: Due from Partners | C13: Asset | D13: other_current_asset | E13: =IF(OR(C13="Asset",C13="COGS",C13="Expense"),IF(OR(D13="accumulated_depreciation",D13="accumulated_amortization",D13="allowance_doubtful"),"Credit","Debit"),IF(OR(D13="drawings",D13="sales_discount"),"Debit","Credit")) | F13: partner_receivable | G13: مستحق من الشركاء | H13: Yes
A14: 1175 | B14: Loans Receivable (Short-term) | C14: Asset | D14: other_current_asset | E14: =IF(OR(C14="Asset",C14="COGS",C14="Expense"),IF(OR(D14="accumulated_depreciation",D14="accumulated_amortization",D14="allowance_doubtful"),"Credit","Debit"),IF(OR(D14="drawings",D14="sales_discount"),"Debit","Credit")) | F14: loans_receivable | G14: قروض ممنوحة للغير (قصيرة الأجل) | H14: Yes
A15: 1180 | B15: Unbilled Revenue (Work Done, Not Yet Invoiced) | C15: Asset | D15: other_current_asset | E15: =IF(OR(C15="Asset",C15="COGS",C15="Expense"),IF(OR(D15="accumulated_depreciation",D15="accumulated_amortization",D15="allowance_doubtful"),"Credit","Debit"),IF(OR(D15="drawings",D15="sales_discount"),"Debit","Credit")) | G15: إيرادات مستحقة غير مفوترة (أعمال منفذة) | H15: Yes
A16: 1185 | B16: Accrued Interest Receivable | C16: Asset | D16: other_current_asset | E16: =IF(OR(C16="Asset",C16="COGS",C16="Expense"),IF(OR(D16="accumulated_depreciation",D16="accumulated_amortization",D16="allowance_doubtful"),"Credit","Debit"),IF(OR(D16="drawings",D16="sales_discount"),"Debit","Credit")) | F16: interest_receivable | G16: فوائد مستحقة التحصيل | H16: Yes
A17: 1190 | B17: Allowance for Doubtful Accounts | C17: Asset | D17: allowance_doubtful | E17: =IF(OR(C17="Asset",C17="COGS",C17="Expense"),IF(OR(D17="accumulated_depreciation",D17="accumulated_amortization",D17="allowance_doubtful"),"Credit","Debit"),IF(OR(D17="drawings",D17="sales_discount"),"Debit","Credit")) | F17: doubtful_allowance | G17: مخصص الديون المشكوك في تحصيلها | H17: Yes
A18: 1200 | B18: Materials Inventory | C18: Asset | D18: inventory | E18: =IF(OR(C18="Asset",C18="COGS",C18="Expense"),IF(OR(D18="accumulated_depreciation",D18="accumulated_amortization",D18="allowance_doubtful"),"Credit","Debit"),IF(OR(D18="drawings",D18="sales_discount"),"Debit","Credit")) | F18: inventory | G18: مخزون الخامات | H18: Yes
A19: 1300 | B19: Prepaid Expenses | C19: Asset | D19: prepaid | E19: =IF(OR(C19="Asset",C19="COGS",C19="Expense"),IF(OR(D19="accumulated_depreciation",D19="accumulated_amortization",D19="allowance_doubtful"),"Credit","Debit"),IF(OR(D19="drawings",D19="sales_discount"),"Debit","Credit")) | G19: مصروفات مدفوعة مقدماً | H19: Yes
A20: 1310 | B20: Supplier Advances | C20: Asset | D20: prepaid | E20: =IF(OR(C20="Asset",C20="COGS",C20="Expense"),IF(OR(D20="accumulated_depreciation",D20="accumulated_amortization",D20="allowance_doubtful"),"Credit","Debit"),IF(OR(D20="drawings",D20="sales_discount"),"Debit","Credit")) | G20: دفعات مقدمة للموردين | H20: Yes
A21: 1320 | B21: VAT Recoverable (Input) | C21: Asset | D21: other_current_asset | E21: =IF(OR(C21="Asset",C21="COGS",C21="Expense"),IF(OR(D21="accumulated_depreciation",D21="accumulated_amortization",D21="allowance_doubtful"),"Credit","Debit"),IF(OR(D21="drawings",D21="sales_discount"),"Debit","Credit")) | F21: vat_input | G21: ضريبة القيمة المضافة (مدخلات) | H21: Yes
A22: 1330 | B22: Withholding Tax Receivable (deducted by clients) | C22: Asset | D22: other_current_asset | E22: =IF(OR(C22="Asset",C22="COGS",C22="Expense"),IF(OR(D22="accumulated_depreciation",D22="accumulated_amortization",D22="allowance_doubtful"),"Credit","Debit"),IF(OR(D22="drawings",D22="sales_discount"),"Debit","Credit")) | F22: wht_receivable | G22: ضريبة خصم وتحصيل لدى العملاء | H22: Yes
A23: 1340 | B23: Letters of Guarantee — Cash Margin | C23: Asset | D23: other_current_asset | E23: =IF(OR(C23="Asset",C23="COGS",C23="Expense"),IF(OR(D23="accumulated_depreciation",D23="accumulated_amortization",D23="allowance_doubtful"),"Credit","Debit"),IF(OR(D23="drawings",D23="sales_discount"),"Debit","Credit")) | G23: غطاء خطابات الضمان | H23: Yes
A24: 1400 | B24: Furniture & Office Equipment | C24: Asset | D24: fixed_asset | E24: =IF(OR(C24="Asset",C24="COGS",C24="Expense"),IF(OR(D24="accumulated_depreciation",D24="accumulated_amortization",D24="allowance_doubtful"),"Credit","Debit"),IF(OR(D24="drawings",D24="sales_discount"),"Debit","Credit")) | F24: fixed_asset | G24: أثاث ومعدات مكتبية | H24: Yes
A25: 1410 | B25: Tools & Site Equipment | C25: Asset | D25: fixed_asset | E25: =IF(OR(C25="Asset",C25="COGS",C25="Expense"),IF(OR(D25="accumulated_depreciation",D25="accumulated_amortization",D25="allowance_doubtful"),"Credit","Debit"),IF(OR(D25="drawings",D25="sales_discount"),"Debit","Credit")) | G25: عدد ومعدات مواقع | H25: Yes
A26: 1415 | B26: Rental Equipment (Scaffolding, Elevators, Cradles) | C26: Asset | D26: fixed_asset | E26: =IF(OR(C26="Asset",C26="COGS",C26="Expense"),IF(OR(D26="accumulated_depreciation",D26="accumulated_amortization",D26="allowance_doubtful"),"Credit","Debit"),IF(OR(D26="drawings",D26="sales_discount"),"Debit","Credit")) | F26: rental_fleet | G26: معدات التأجير (سقالات، مصاعد، سقالات معلقة) | H26: Yes
A27: 1416 | B27: Accumulated Depreciation — Rental Equipment | C27: Asset | D27: accumulated_depreciation | E27: =IF(OR(C27="Asset",C27="COGS",C27="Expense"),IF(OR(D27="accumulated_depreciation",D27="accumulated_amortization",D27="allowance_doubtful"),"Credit","Debit"),IF(OR(D27="drawings",D27="sales_discount"),"Debit","Credit")) | F27: rental_accum | G27: مجمع إهلاك معدات التأجير | H27: Yes
A28: 1420 | B28: Vehicles | C28: Asset | D28: fixed_asset | E28: =IF(OR(C28="Asset",C28="COGS",C28="Expense"),IF(OR(D28="accumulated_depreciation",D28="accumulated_amortization",D28="allowance_doubtful"),"Credit","Debit"),IF(OR(D28="drawings",D28="sales_discount"),"Debit","Credit")) | G28: سيارات | H28: Yes
A29: 1430 | B29: Computers & IT Equipment | C29: Asset | D29: fixed_asset | E29: =IF(OR(C29="Asset",C29="COGS",C29="Expense"),IF(OR(D29="accumulated_depreciation",D29="accumulated_amortization",D29="allowance_doubtful"),"Credit","Debit"),IF(OR(D29="drawings",D29="sales_discount"),"Debit","Credit")) | G29: أجهزة حاسب ومعدات تقنية | H29: Yes
A30: 1440 | B30: Land | C30: Asset | D30: fixed_asset | E30: =IF(OR(C30="Asset",C30="COGS",C30="Expense"),IF(OR(D30="accumulated_depreciation",D30="accumulated_amortization",D30="allowance_doubtful"),"Credit","Debit"),IF(OR(D30="drawings",D30="sales_discount"),"Debit","Credit")) | G30: أراضي | H30: Yes
A31: 1450 | B31: Buildings & Leasehold Improvements | C31: Asset | D31: fixed_asset | E31: =IF(OR(C31="Asset",C31="COGS",C31="Expense"),IF(OR(D31="accumulated_depreciation",D31="accumulated_amortization",D31="allowance_doubtful"),"Credit","Debit"),IF(OR(D31="drawings",D31="sales_discount"),"Debit","Credit")) | G31: مباني وتحسينات أماكن مستأجرة | H31: Yes
A32: 1460 | B32: Assets Under Construction | C32: Asset | D32: fixed_asset | E32: =IF(OR(C32="Asset",C32="COGS",C32="Expense"),IF(OR(D32="accumulated_depreciation",D32="accumulated_amortization",D32="allowance_doubtful"),"Credit","Debit"),IF(OR(D32="drawings",D32="sales_discount"),"Debit","Credit")) | G32: مشروعات تحت التنفيذ | H32: Yes
A33: 1490 | B33: Accumulated Depreciation | C33: Asset | D33: accumulated_depreciation | E33: =IF(OR(C33="Asset",C33="COGS",C33="Expense"),IF(OR(D33="accumulated_depreciation",D33="accumulated_amortization",D33="allowance_doubtful"),"Credit","Debit"),IF(OR(D33="drawings",D33="sales_discount"),"Debit","Credit")) | F33: accum_depreciation | G33: مجمع الإهلاك | H33: Yes
A34: 1500 | B34: Software & Licences | C34: Asset | D34: intangible | E34: =IF(OR(C34="Asset",C34="COGS",C34="Expense"),IF(OR(D34="accumulated_depreciation",D34="accumulated_amortization",D34="allowance_doubtful"),"Credit","Debit"),IF(OR(D34="drawings",D34="sales_discount"),"Debit","Credit")) | F34: intangible | G34: برامج وتراخيص | H34: Yes
A35: 1510 | B35: Brand, Website & Design Library | C35: Asset | D35: intangible | E35: =IF(OR(C35="Asset",C35="COGS",C35="Expense"),IF(OR(D35="accumulated_depreciation",D35="accumulated_amortization",D35="allowance_doubtful"),"Credit","Debit"),IF(OR(D35="drawings",D35="sales_discount"),"Debit","Credit")) | G35: العلامة التجارية والموقع ومكتبة التصميمات | H35: Yes
A36: 1520 | B36: Goodwill | C36: Asset | D36: intangible | E36: =IF(OR(C36="Asset",C36="COGS",C36="Expense"),IF(OR(D36="accumulated_depreciation",D36="accumulated_amortization",D36="allowance_doubtful"),"Credit","Debit"),IF(OR(D36="drawings",D36="sales_discount"),"Debit","Credit")) | G36: الشهرة | H36: Yes
A37: 1590 | B37: Accumulated Amortization | C37: Asset | D37: accumulated_amortization | E37: =IF(OR(C37="Asset",C37="COGS",C37="Expense"),IF(OR(D37="accumulated_depreciation",D37="accumulated_amortization",D37="allowance_doubtful"),"Credit","Debit"),IF(OR(D37="drawings",D37="sales_discount"),"Debit","Credit")) | F37: accum_amortization | G37: مجمع الاستهلاك | H37: Yes
A38: 1600 | B38: Security Deposits | C38: Asset | D38: other_noncurrent_asset | E38: =IF(OR(C38="Asset",C38="COGS",C38="Expense"),IF(OR(D38="accumulated_depreciation",D38="accumulated_amortization",D38="allowance_doubtful"),"Credit","Debit"),IF(OR(D38="drawings",D38="sales_discount"),"Debit","Credit")) | G38: تأمينات لدى الغير | H38: Yes
A39: 1610 | B39: Loans Receivable (Long-term) | C39: Asset | D39: other_noncurrent_asset | E39: =IF(OR(C39="Asset",C39="COGS",C39="Expense"),IF(OR(D39="accumulated_depreciation",D39="accumulated_amortization",D39="allowance_doubtful"),"Credit","Debit"),IF(OR(D39="drawings",D39="sales_discount"),"Debit","Credit")) | F39: loans_receivable_lt | G39: قروض ممنوحة للغير (طويلة الأجل) | H39: Yes
A40: 1700 | B40: Long-term Investments | C40: Asset | D40: investment | E40: =IF(OR(C40="Asset",C40="COGS",C40="Expense"),IF(OR(D40="accumulated_depreciation",D40="accumulated_amortization",D40="allowance_doubtful"),"Credit","Debit"),IF(OR(D40="drawings",D40="sales_discount"),"Debit","Credit")) | F40: investments | G40: استثمارات طويلة الأجل | H40: Yes
A41: 2010 | B41: Accounts Payable — Suppliers | C41: Liability | D41: payable | E41: =IF(OR(C41="Asset",C41="COGS",C41="Expense"),IF(OR(D41="accumulated_depreciation",D41="accumulated_amortization",D41="allowance_doubtful"),"Credit","Debit"),IF(OR(D41="drawings",D41="sales_discount"),"Debit","Credit")) | F41: ap | G41: الموردون (الدائنون) | H41: Yes
A42: 2015 | B42: Subcontractors Payable | C42: Liability | D42: payable | E42: =IF(OR(C42="Asset",C42="COGS",C42="Expense"),IF(OR(D42="accumulated_depreciation",D42="accumulated_amortization",D42="allowance_doubtful"),"Credit","Debit"),IF(OR(D42="drawings",D42="sales_discount"),"Debit","Credit")) | G42: مقاولو الباطن | H42: Yes
A43: 2020 | B43: Accrued Payroll | C43: Liability | D43: accrued | E43: =IF(OR(C43="Asset",C43="COGS",C43="Expense"),IF(OR(D43="accumulated_depreciation",D43="accumulated_amortization",D43="allowance_doubtful"),"Credit","Debit"),IF(OR(D43="drawings",D43="sales_discount"),"Debit","Credit")) | F43: accrued_payroll | G43: أجور مستحقة | H43: Yes
A44: 2030 | B44: Accrued Expenses | C44: Liability | D44: accrued | E44: =IF(OR(C44="Asset",C44="COGS",C44="Expense"),IF(OR(D44="accumulated_depreciation",D44="accumulated_amortization",D44="allowance_doubtful"),"Credit","Debit"),IF(OR(D44="drawings",D44="sales_discount"),"Debit","Credit")) | G44: مصروفات مستحقة | H44: Yes
A45: 2040 | B45: Social Insurance Payable | C45: Liability | D45: accrued | E45: =IF(OR(C45="Asset",C45="COGS",C45="Expense"),IF(OR(D45="accumulated_depreciation",D45="accumulated_amortization",D45="allowance_doubtful"),"Credit","Debit"),IF(OR(D45="drawings",D45="sales_discount"),"Debit","Credit")) | G45: تأمينات اجتماعية مستحقة | H45: Yes
A46: 2050 | B46: Notes Payable (Cheques Issued) | C46: Liability | D46: payable | E46: =IF(OR(C46="Asset",C46="COGS",C46="Expense"),IF(OR(D46="accumulated_depreciation",D46="accumulated_amortization",D46="allowance_doubtful"),"Credit","Debit"),IF(OR(D46="drawings",D46="sales_discount"),"Debit","Credit")) | G46: أوراق الدفع (شيكات صادرة) | H46: Yes
A47: 2060 | B47: Accrued Interest Payable | C47: Liability | D47: accrued | E47: =IF(OR(C47="Asset",C47="COGS",C47="Expense"),IF(OR(D47="accumulated_depreciation",D47="accumulated_amortization",D47="allowance_doubtful"),"Credit","Debit"),IF(OR(D47="drawings",D47="sales_discount"),"Debit","Credit")) | F47: accrued_interest | G47: فوائد مستحقة | H47: Yes
A48: 2100 | B48: Client Advances (Unearned Revenue) | C48: Liability | D48: deferred_revenue | E48: =IF(OR(C48="Asset",C48="COGS",C48="Expense"),IF(OR(D48="accumulated_depreciation",D48="accumulated_amortization",D48="allowance_doubtful"),"Credit","Debit"),IF(OR(D48="drawings",D48="sales_discount"),"Debit","Credit")) | F48: client_advances | G48: دفعات مقدمة من العملاء (إيرادات مؤجلة) | H48: Yes
A49: 2105 | B49: Security Deposits from Clients | C49: Liability | D49: other_current_liability | E49: =IF(OR(C49="Asset",C49="COGS",C49="Expense"),IF(OR(D49="accumulated_depreciation",D49="accumulated_amortization",D49="allowance_doubtful"),"Credit","Debit"),IF(OR(D49="drawings",D49="sales_discount"),"Debit","Credit")) | F49: rental_deposits | G49: تأمينات العملاء (ودائع ضمان) | H49: Yes
A50: 2110 | B50: Retention Payable | C50: Liability | D50: other_current_liability | E50: =IF(OR(C50="Asset",C50="COGS",C50="Expense"),IF(OR(D50="accumulated_depreciation",D50="accumulated_amortization",D50="allowance_doubtful"),"Credit","Debit"),IF(OR(D50="drawings",D50="sales_discount"),"Debit","Credit")) | G50: محتجزات مقاولي الباطن | H50: Yes
A51: 2120 | B51: Profit Distributions Payable to Partners | C51: Liability | D51: dividends_payable | E51: =IF(OR(C51="Asset",C51="COGS",C51="Expense"),IF(OR(D51="accumulated_depreciation",D51="accumulated_amortization",D51="allowance_doubtful"),"Credit","Debit"),IF(OR(D51="drawings",D51="sales_discount"),"Debit","Credit")) | F51: dividends_payable | G51: توزيعات أرباح مستحقة للشركاء | H51: Yes
A52: 2130 | B52: Due to Departing Partners | C52: Liability | D52: other_current_liability | E52: =IF(OR(C52="Asset",C52="COGS",C52="Expense"),IF(OR(D52="accumulated_depreciation",D52="accumulated_amortization",D52="allowance_doubtful"),"Credit","Debit"),IF(OR(D52="drawings",D52="sales_discount"),"Debit","Credit")) | F52: partner_payable | G52: مستحق للشركاء المنسحبين | H52: Yes
A53: 2200 | B53: VAT Payable (Output) | C53: Liability | D53: tax_payable | E53: =IF(OR(C53="Asset",C53="COGS",C53="Expense"),IF(OR(D53="accumulated_depreciation",D53="accumulated_amortization",D53="allowance_doubtful"),"Credit","Debit"),IF(OR(D53="drawings",D53="sales_discount"),"Debit","Credit")) | F53: vat_output | G53: ضريبة القيمة المضافة (مخرجات) | H53: Yes
A54: 2210 | B54: Withholding Tax Payable (deducted from suppliers) | C54: Liability | D54: tax_payable | E54: =IF(OR(C54="Asset",C54="COGS",C54="Expense"),IF(OR(D54="accumulated_depreciation",D54="accumulated_amortization",D54="allowance_doubtful"),"Credit","Debit"),IF(OR(D54="drawings",D54="sales_discount"),"Debit","Credit")) | F54: wht_payable | G54: ضريبة الخصم والتحصيل المستحقة (من الموردين) | H54: Yes
A55: 2220 | B55: Income Tax Payable | C55: Liability | D55: tax_payable | E55: =IF(OR(C55="Asset",C55="COGS",C55="Expense"),IF(OR(D55="accumulated_depreciation",D55="accumulated_amortization",D55="allowance_doubtful"),"Credit","Debit"),IF(OR(D55="drawings",D55="sales_discount"),"Debit","Credit")) | F55: income_tax_payable | G55: ضريبة الدخل المستحقة | H55: Yes
A56: 2300 | B56: Short-term Loans | C56: Liability | D56: short_term_debt | E56: =IF(OR(C56="Asset",C56="COGS",C56="Expense"),IF(OR(D56="accumulated_depreciation",D56="accumulated_amortization",D56="allowance_doubtful"),"Credit","Debit"),IF(OR(D56="drawings",D56="sales_discount"),"Debit","Credit")) | F56: short_term_debt | G56: قروض قصيرة الأجل | H56: Yes
A57: 2310 | B57: Credit Card Payable | C57: Liability | D57: short_term_debt | E57: =IF(OR(C57="Asset",C57="COGS",C57="Expense"),IF(OR(D57="accumulated_depreciation",D57="accumulated_amortization",D57="allowance_doubtful"),"Credit","Debit"),IF(OR(D57="drawings",D57="sales_discount"),"Debit","Credit")) | G57: بطاقات ائتمان مستحقة | H57: Yes
A58: 2400 | B58: Long-term Loans | C58: Liability | D58: long_term_debt | E58: =IF(OR(C58="Asset",C58="COGS",C58="Expense"),IF(OR(D58="accumulated_depreciation",D58="accumulated_amortization",D58="allowance_doubtful"),"Credit","Debit"),IF(OR(D58="drawings",D58="sales_discount"),"Debit","Credit")) | F58: long_term_debt | G58: قروض طويلة الأجل | H58: Yes
A59: 2500 | B59: Partner Loans | C59: Liability | D59: long_term_debt | E59: =IF(OR(C59="Asset",C59="COGS",C59="Expense"),IF(OR(D59="accumulated_depreciation",D59="accumulated_amortization",D59="allowance_doubtful"),"Credit","Debit"),IF(OR(D59="drawings",D59="sales_discount"),"Debit","Credit")) | F59: partner_loans | G59: قروض الشركاء | H59: Yes
A60: 2510 | B60: End-of-Service Provision | C60: Liability | D60: other_noncurrent_liability | E60: =IF(OR(C60="Asset",C60="COGS",C60="Expense"),IF(OR(D60="accumulated_depreciation",D60="accumulated_amortization",D60="allowance_doubtful"),"Credit","Debit"),IF(OR(D60="drawings",D60="sales_discount"),"Debit","Credit")) | G60: مخصص مكافأة نهاية الخدمة | H60: Yes
A61: 3010 | B61: Partner Capital | C61: Equity | D61: capital | E61: =IF(OR(C61="Asset",C61="COGS",C61="Expense"),IF(OR(D61="accumulated_depreciation",D61="accumulated_amortization",D61="allowance_doubtful"),"Credit","Debit"),IF(OR(D61="drawings",D61="sales_discount"),"Debit","Credit")) | F61: capital | G61: رأس مال الشركاء | H61: Yes
A62: 3020 | B62: Partners' Current Accounts | C62: Equity | D62: partner_current | E62: =IF(OR(C62="Asset",C62="COGS",C62="Expense"),IF(OR(D62="accumulated_depreciation",D62="accumulated_amortization",D62="allowance_doubtful"),"Credit","Debit"),IF(OR(D62="drawings",D62="sales_discount"),"Debit","Credit")) | F62: partner_current | G62: جاري الشركاء | H62: Yes
A63: 3030 | B63: Share Premium | C63: Equity | D63: other_equity | E63: =IF(OR(C63="Asset",C63="COGS",C63="Expense"),IF(OR(D63="accumulated_depreciation",D63="accumulated_amortization",D63="allowance_doubtful"),"Credit","Debit"),IF(OR(D63="drawings",D63="sales_discount"),"Debit","Credit")) | F63: share_premium | G63: علاوة إصدار / علاوة حصص | H63: Yes
A64: 3100 | B64: Retained Earnings | C64: Equity | D64: retained_earnings | E64: =IF(OR(C64="Asset",C64="COGS",C64="Expense"),IF(OR(D64="accumulated_depreciation",D64="accumulated_amortization",D64="allowance_doubtful"),"Credit","Debit"),IF(OR(D64="drawings",D64="sales_discount"),"Debit","Credit")) | F64: retained | G64: الأرباح المحتجزة | H64: Yes
A65: 3110 | B65: Legal Reserve | C65: Equity | D65: reserves | E65: =IF(OR(C65="Asset",C65="COGS",C65="Expense"),IF(OR(D65="accumulated_depreciation",D65="accumulated_amortization",D65="allowance_doubtful"),"Credit","Debit"),IF(OR(D65="drawings",D65="sales_discount"),"Debit","Credit")) | F65: legal_reserve | G65: الاحتياطي القانوني | H65: Yes
A66: 3120 | B66: General Reserve | C66: Equity | D66: reserves | E66: =IF(OR(C66="Asset",C66="COGS",C66="Expense"),IF(OR(D66="accumulated_depreciation",D66="accumulated_amortization",D66="allowance_doubtful"),"Credit","Debit"),IF(OR(D66="drawings",D66="sales_discount"),"Debit","Credit")) | G66: الاحتياطي العام | H66: Yes
A67: 3200 | B67: Partner Drawings / Dividends | C67: Equity | D67: drawings | E67: =IF(OR(C67="Asset",C67="COGS",C67="Expense"),IF(OR(D67="accumulated_depreciation",D67="accumulated_amortization",D67="allowance_doubtful"),"Credit","Debit"),IF(OR(D67="drawings",D67="sales_discount"),"Debit","Credit")) | F67: drawings | G67: مسحوبات الشركاء / توزيعات الأرباح | H67: Yes
A68: 4010 | B68: Project Revenue — Execution | C68: Revenue | D68: operating_revenue | E68: =IF(OR(C68="Asset",C68="COGS",C68="Expense"),IF(OR(D68="accumulated_depreciation",D68="accumulated_amortization",D68="allowance_doubtful"),"Credit","Debit"),IF(OR(D68="drawings",D68="sales_discount"),"Debit","Credit")) | F68: revenue | G68: إيرادات المشروعات — التنفيذ | H68: Yes
A69: 4020 | B69: Design Fees | C69: Revenue | D69: operating_revenue | E69: =IF(OR(C69="Asset",C69="COGS",C69="Expense"),IF(OR(D69="accumulated_depreciation",D69="accumulated_amortization",D69="allowance_doubtful"),"Credit","Debit"),IF(OR(D69="drawings",D69="sales_discount"),"Debit","Credit")) | F69: design_revenue | G69: أتعاب التصميم | H69: Yes
A70: 4030 | B70: Supervision / Management Fees | C70: Revenue | D70: operating_revenue | E70: =IF(OR(C70="Asset",C70="COGS",C70="Expense"),IF(OR(D70="accumulated_depreciation",D70="accumulated_amortization",D70="allowance_doubtful"),"Credit","Debit"),IF(OR(D70="drawings",D70="sales_discount"),"Debit","Credit")) | G70: أتعاب الإشراف والإدارة | H70: Yes
A71: 4040 | B71: Furniture & Supply Sales | C71: Revenue | D71: operating_revenue | E71: =IF(OR(C71="Asset",C71="COGS",C71="Expense"),IF(OR(D71="accumulated_depreciation",D71="accumulated_amortization",D71="allowance_doubtful"),"Credit","Debit"),IF(OR(D71="drawings",D71="sales_discount"),"Debit","Credit")) | G71: مبيعات أثاث وتوريدات | H71: Yes
A72: 4045 | B72: Equipment Rental Revenue | C72: Revenue | D72: operating_revenue | E72: =IF(OR(C72="Asset",C72="COGS",C72="Expense"),IF(OR(D72="accumulated_depreciation",D72="accumulated_amortization",D72="allowance_doubtful"),"Credit","Debit"),IF(OR(D72="drawings",D72="sales_discount"),"Debit","Credit")) | F72: rental_revenue | G72: إيرادات تأجير المعدات | H72: Yes
A73: 4046 | B73: Installation, Dismantling & Transport Revenue | C73: Revenue | D73: operating_revenue | E73: =IF(OR(C73="Asset",C73="COGS",C73="Expense"),IF(OR(D73="accumulated_depreciation",D73="accumulated_amortization",D73="allowance_doubtful"),"Credit","Debit"),IF(OR(D73="drawings",D73="sales_discount"),"Debit","Credit")) | F73: rental_services | G73: إيرادات التركيب والفك والنقل | H73: Yes
A74: 4050 | B74: Sales Discounts & Allowances | C74: Revenue | D74: sales_discount | E74: =IF(OR(C74="Asset",C74="COGS",C74="Expense"),IF(OR(D74="accumulated_depreciation",D74="accumulated_amortization",D74="allowance_doubtful"),"Credit","Debit"),IF(OR(D74="drawings",D74="sales_discount"),"Debit","Credit")) | F74: sales_discount | G74: خصومات ومسموحات المبيعات | H74: Yes
A75: 4060 | B75: Gain on Disposal of Fixed Assets | C75: Revenue | D75: other_income | E75: =IF(OR(C75="Asset",C75="COGS",C75="Expense"),IF(OR(D75="accumulated_depreciation",D75="accumulated_amortization",D75="allowance_doubtful"),"Credit","Debit"),IF(OR(D75="drawings",D75="sales_discount"),"Debit","Credit")) | F75: disposal_gain | G75: أرباح بيع أصول ثابتة | H75: Yes
A76: 4070 | B76: Rental Income | C76: Revenue | D76: other_income | E76: =IF(OR(C76="Asset",C76="COGS",C76="Expense"),IF(OR(D76="accumulated_depreciation",D76="accumulated_amortization",D76="allowance_doubtful"),"Credit","Debit"),IF(OR(D76="drawings",D76="sales_discount"),"Debit","Credit")) | G76: إيرادات إيجار | H76: Yes
A77: 4075 | B77: Compensation for Lost / Damaged Equipment | C77: Revenue | D77: other_income | E77: =IF(OR(C77="Asset",C77="COGS",C77="Expense"),IF(OR(D77="accumulated_depreciation",D77="accumulated_amortization",D77="allowance_doubtful"),"Credit","Debit"),IF(OR(D77="drawings",D77="sales_discount"),"Debit","Credit")) | F77: rental_compensation | G77: تعويضات المعدات المفقودة / التالفة | H77: Yes
A78: 4080 | B78: Discounts Received | C78: Revenue | D78: other_income | E78: =IF(OR(C78="Asset",C78="COGS",C78="Expense"),IF(OR(D78="accumulated_depreciation",D78="accumulated_amortization",D78="allowance_doubtful"),"Credit","Debit"),IF(OR(D78="drawings",D78="sales_discount"),"Debit","Credit")) | G78: خصم مكتسب | H78: Yes
A79: 4085 | B79: Negotiation Earnings | C79: Revenue | D79: operating_revenue | E79: =IF(OR(C79="Asset",C79="COGS",C79="Expense"),IF(OR(D79="accumulated_depreciation",D79="accumulated_amortization",D79="allowance_doubtful"),"Credit","Debit"),IF(OR(D79="drawings",D79="sales_discount"),"Debit","Credit")) | F79: negotiation_income | G79: أرباح التفاوض | H79: Yes
A80: 4090 | B80: Other Income | C80: Revenue | D80: other_income | E80: =IF(OR(C80="Asset",C80="COGS",C80="Expense"),IF(OR(D80="accumulated_depreciation",D80="accumulated_amortization",D80="allowance_doubtful"),"Credit","Debit"),IF(OR(D80="drawings",D80="sales_discount"),"Debit","Credit")) | F80: other_income | G80: إيرادات أخرى | H80: Yes
A81: 4095 | B81: Interest Income | C81: Revenue | D81: other_income | E81: =IF(OR(C81="Asset",C81="COGS",C81="Expense"),IF(OR(D81="accumulated_depreciation",D81="accumulated_amortization",D81="allowance_doubtful"),"Credit","Debit"),IF(OR(D81="drawings",D81="sales_discount"),"Debit","Credit")) | F81: interest_income | G81: إيرادات فوائد | H81: Yes
A82: 5010 | B82: Materials | C82: COGS | D82: cogs | E82: =IF(OR(C82="Asset",C82="COGS",C82="Expense"),IF(OR(D82="accumulated_depreciation",D82="accumulated_amortization",D82="allowance_doubtful"),"Credit","Debit"),IF(OR(D82="drawings",D82="sales_discount"),"Debit","Credit")) | F82: materials | G82: خامات | H82: Yes
A83: 5020 | B83: Subcontractor Costs | C83: COGS | D83: cogs | E83: =IF(OR(C83="Asset",C83="COGS",C83="Expense"),IF(OR(D83="accumulated_depreciation",D83="accumulated_amortization",D83="allowance_doubtful"),"Credit","Debit"),IF(OR(D83="drawings",D83="sales_discount"),"Debit","Credit")) | G83: تكاليف مقاولي الباطن | H83: Yes
A84: 5030 | B84: Direct Labour (billable) | C84: COGS | D84: cogs | E84: =IF(OR(C84="Asset",C84="COGS",C84="Expense"),IF(OR(D84="accumulated_depreciation",D84="accumulated_amortization",D84="allowance_doubtful"),"Credit","Debit"),IF(OR(D84="drawings",D84="sales_discount"),"Debit","Credit")) | F84: direct_labour | G84: عمالة مباشرة | H84: Yes
A85: 5040 | B85: Site Preparation | C85: COGS | D85: cogs | E85: =IF(OR(C85="Asset",C85="COGS",C85="Expense"),IF(OR(D85="accumulated_depreciation",D85="accumulated_amortization",D85="allowance_doubtful"),"Credit","Debit"),IF(OR(D85="drawings",D85="sales_discount"),"Debit","Credit")) | G85: تجهيز الموقع | H85: Yes
A86: 5050 | B86: Equipment Rental | C86: COGS | D86: cogs | E86: =IF(OR(C86="Asset",C86="COGS",C86="Expense"),IF(OR(D86="accumulated_depreciation",D86="accumulated_amortization",D86="allowance_doubtful"),"Credit","Debit"),IF(OR(D86="drawings",D86="sales_discount"),"Debit","Credit")) | G86: إيجار معدات | H86: Yes
A87: 5060 | B87: Transport & Hauling | C87: COGS | D87: cogs | E87: =IF(OR(C87="Asset",C87="COGS",C87="Expense"),IF(OR(D87="accumulated_depreciation",D87="accumulated_amortization",D87="allowance_doubtful"),"Credit","Debit"),IF(OR(D87="drawings",D87="sales_discount"),"Debit","Credit")) | G87: نقل وتشوين | H87: Yes
A88: 5070 | B88: Design Outsourcing & Renders | C88: COGS | D88: cogs | E88: =IF(OR(C88="Asset",C88="COGS",C88="Expense"),IF(OR(D88="accumulated_depreciation",D88="accumulated_amortization",D88="allowance_doubtful"),"Credit","Debit"),IF(OR(D88="drawings",D88="sales_discount"),"Debit","Credit")) | G88: تصميم خارجي ورندرات | H88: Yes
A89: 5080 | B89: Inventory Adjustments | C89: COGS | D89: cogs | E89: =IF(OR(C89="Asset",C89="COGS",C89="Expense"),IF(OR(D89="accumulated_depreciation",D89="accumulated_amortization",D89="allowance_doubtful"),"Credit","Debit"),IF(OR(D89="drawings",D89="sales_discount"),"Debit","Credit")) | F89: stock_adjust | G89: تسويات المخزون | H89: Yes
A90: 6010 | B90: Rent | C90: Expense | D90: general_admin | E90: =IF(OR(C90="Asset",C90="COGS",C90="Expense"),IF(OR(D90="accumulated_depreciation",D90="accumulated_amortization",D90="allowance_doubtful"),"Credit","Debit"),IF(OR(D90="drawings",D90="sales_discount"),"Debit","Credit")) | G90: الإيجار | H90: Yes
A91: 6015 | B91: Repairs & Maintenance | C91: Expense | D91: general_admin | E91: =IF(OR(C91="Asset",C91="COGS",C91="Expense"),IF(OR(D91="accumulated_depreciation",D91="accumulated_amortization",D91="allowance_doubtful"),"Credit","Debit"),IF(OR(D91="drawings",D91="sales_discount"),"Debit","Credit")) | G91: صيانة وإصلاحات | H91: Yes
A92: 6020 | B92: Software & Subscriptions | C92: Expense | D92: general_admin | E92: =IF(OR(C92="Asset",C92="COGS",C92="Expense"),IF(OR(D92="accumulated_depreciation",D92="accumulated_amortization",D92="allowance_doubtful"),"Credit","Debit"),IF(OR(D92="drawings",D92="sales_discount"),"Debit","Credit")) | G92: برامج واشتراكات | H92: Yes
A93: 6030 | B93: Marketing & Advertising | C93: Expense | D93: marketing | E93: =IF(OR(C93="Asset",C93="COGS",C93="Expense"),IF(OR(D93="accumulated_depreciation",D93="accumulated_amortization",D93="allowance_doubtful"),"Credit","Debit"),IF(OR(D93="drawings",D93="sales_discount"),"Debit","Credit")) | G93: دعاية وإعلان | H93: Yes
A94: 6040 | B94: Utilities (Electricity & Water) | C94: Expense | D94: utilities | E94: =IF(OR(C94="Asset",C94="COGS",C94="Expense"),IF(OR(D94="accumulated_depreciation",D94="accumulated_amortization",D94="allowance_doubtful"),"Credit","Debit"),IF(OR(D94="drawings",D94="sales_discount"),"Debit","Credit")) | G94: كهرباء ومياه | H94: Yes
A95: 6045 | B95: Telephone & Internet | C95: Expense | D95: utilities | E95: =IF(OR(C95="Asset",C95="COGS",C95="Expense"),IF(OR(D95="accumulated_depreciation",D95="accumulated_amortization",D95="allowance_doubtful"),"Credit","Debit"),IF(OR(D95="drawings",D95="sales_discount"),"Debit","Credit")) | G95: هاتف وإنترنت | H95: Yes
A96: 6050 | B96: Office & Admin Salaries | C96: Expense | D96: employee | E96: =IF(OR(C96="Asset",C96="COGS",C96="Expense"),IF(OR(D96="accumulated_depreciation",D96="accumulated_amortization",D96="allowance_doubtful"),"Credit","Debit"),IF(OR(D96="drawings",D96="sales_discount"),"Debit","Credit")) | F96: admin_salaries | G96: رواتب إدارية | H96: Yes
A97: 6055 | B97: Social Insurance & Benefits | C97: Expense | D97: employee | E97: =IF(OR(C97="Asset",C97="COGS",C97="Expense"),IF(OR(D97="accumulated_depreciation",D97="accumulated_amortization",D97="allowance_doubtful"),"Credit","Debit"),IF(OR(D97="drawings",D97="sales_discount"),"Debit","Credit")) | G97: تأمينات اجتماعية ومزايا | H97: Yes
A98: 6060 | B98: Professional Fees (Legal, Audit) | C98: Expense | D98: general_admin | E98: =IF(OR(C98="Asset",C98="COGS",C98="Expense"),IF(OR(D98="accumulated_depreciation",D98="accumulated_amortization",D98="allowance_doubtful"),"Credit","Debit"),IF(OR(D98="drawings",D98="sales_discount"),"Debit","Credit")) | G98: أتعاب مهنية (قانونية ومراجعة) | H98: Yes
A99: 6065 | B99: Bank Charges | C99: Expense | D99: general_admin | E99: =IF(OR(C99="Asset",C99="COGS",C99="Expense"),IF(OR(D99="accumulated_depreciation",D99="accumulated_amortization",D99="allowance_doubtful"),"Credit","Debit"),IF(OR(D99="drawings",D99="sales_discount"),"Debit","Credit")) | F99: bank_charges | G99: مصروفات بنكية | H99: Yes
A100: 6070 | B100: Project Overhead (non-billable) | C100: Expense | D100: other_operating | E100: =IF(OR(C100="Asset",C100="COGS",C100="Expense"),IF(OR(D100="accumulated_depreciation",D100="accumulated_amortization",D100="allowance_doubtful"),"Credit","Debit"),IF(OR(D100="drawings",D100="sales_discount"),"Debit","Credit")) | F100: project_overhead | G100: مصروفات المشروعات غير المحملة | H100: Yes
...

Sheet Tax Codes
A1: BEYOND DESIGN | TAX CODES
A2: VAT and withholding-tax codes with their e-invoice (ETA) tax type / sub-type. Rates are editable
A3: e.g. VAT14 | B3: VAT 14% (standard) | C3: ضريبة القيمة المضافة 14% | D3: vat | E3: 14% | F3: T1 | G3: V009 | H3: Yes
A4: Code | B4: Name | C4: Arabic Name | D4: Kind | E4: Rate | F4: ETA Tax Type | G4: ETA Sub-type | H4: Active
A5: VAT-EXEMPT | B5: VAT exempt | C5: معفى من ضريبة القيمة المضافة | D5: vat | E5: 0 | F5: T1 | G5: V003 | H5: Yes
A6: VAT0-EXP | B6: VAT 0% — exports | C6: ضريبة القيمة المضافة 0% — صادرات | D6: vat | E6: 0 | F6: T1 | G6: V001 | H6: Yes
A7: VAT14 | B7: VAT 14% (standard) | C7: ضريبة القيمة المضافة 14% | D7: vat | E7: 0.14 | F7: T1 | G7: V009 | H7: Yes
A8: WHT1-C | B8: WHT 1% — contracting | C8: خصم وتحصيل 1% — مقاولات | D8: wht | E8: 0.01 | F8: T4 | G8: W001 | H8: Yes
A9: WHT1-S | B9: WHT 1% — supplies | C9: خصم وتحصيل 1% — توريدات | D9: wht | E9: 0.01 | F9: T4 | G9: W002 | H9: Yes
A10: WHT3 | B10: WHT 3% — services | C10: خصم وتحصيل 3% — خدمات | D10: wht | E10: 0.03 | F10: T4 | G10: W004 | H10: Yes
A11: WHT5 | B11: WHT 5% — professional fees | C11: خصم وتحصيل 5% — أتعاب مهنية | D11: wht | E11: 0.05 | F11: T4 | G11: W010 | H11: Yes

Sheet Business Units
A1: BEYOND DESIGN | BUSINESS UNITS
A2: Business units (cost centres / projects). Overhead % = manual share of shared indirect costs
A3: e.g. PRJ-2026-004 | B3: Villa 12 — Mr. Aly | C3: Villa | D3: New Cairo | E3: 420 | F3: 2026-10-01 | G3: In Progress | H3: Cost-Plus % | I3: 25% | K3: 30%
A4: Code | B4: Name / Client | C4: Type | D4: Location | E4: Area (m²) | F4: Start Date | G4: Status | H4: Billing Basis | I4: Fee % | J4: Contract Value | K4: Overhead Allocation % | L4: Customer | M4: Notes

Sheet Parties
A1: BEYOND DESIGN | PARTIES
A2: Customers & suppliers master — tax registration numbers and addresses are needed for e-invoices
A3: e.g. Palm Hills Developments | B3: customer | C3: B | D3: 123456789 | F3: EG | G3: Giza | H3: 6th of October | I3: 26th of July Axis | J3: 12 | N3: VAT14 | O3: WHT1-C
A4: Name | B4: Type | C4: Receiver Type | D4: Tax Registration No. | E4: National ID | F4: Country | G4: Governorate | H4: City / Region | I4: Street | J4: Building No. | K4: Postal Code | L4: Email | M4: Phone | N4: Default VAT | O4: Default WHT | P4: Notes | Q4: Category | R4: Contact Person | S4: Other Phone | T4: WhatsApp | U4: Trade / Specialty | V4: Vehicle / Plate | W4: Bank Details

Sheet Partners
A1: BEYOND DESIGN | PARTNERS
A2: Partners and their default profit share
A3: e.g. Partner name | B3: 25% | C3: Yes
A4: Partner | B4: Default Share % | C4: Still a Partner | D4: Joined | E4: Left | F4: Interest on Capital % | G4: Loan Interest % | H4: Notes

Sheet Partner Shares
A1: BEYOND DESIGN | PARTNER SHARES
A2: Ownership per business unit (overrides the default share)
A3: e.g. Partner name | B3: PRJ-2026-004 | C3: 25%
A4: Partner | B4: Business Unit | C4: Share %

Sheet Fixed Assets
A1: BEYOND DESIGN | FIXED ASSETS
A2: Fixed asset register (its purchase, depreciation and disposal are journal entries with reference FA:<code>)
A3: e.g. FA-0001 | B3: Site pickup truck | C3: 1420 | F3: 2026-01-15 | G3: 600000 | I3: 60
A4: Asset Code | B4: Asset | C4: Asset Account | D4: Accumulated Depreciation Account | E4: Depreciation Expense Account | F4: Date Acquired | G4: Cost | H4: Residual Value | I4: Useful Life (months) | J4: Depreciate From (YYYY-MM) | K4: Depreciation Before Registering | L4: Business Unit | M4: Location | N4: Serial / Plate No. | O4: Notes | P4: Depreciation Method | Q4: Declining Factor | R4: Monthly Depreciation (straight line) | S4: Depreciation to Report End | T4: Book Value at Report End
R5: =IF(OR(A5="",N(I5)=0),0,ROUND((N(G5)-N(H5))/N(I5),2)) | S5: =IF(A5="","",IFERROR(MIN(N(G5)-N(H5),MAX(N(K5),R5*MAX(0,(YEAR(ReportTo)-YEAR(IF(J5<>"",DATE(LEFT(J5,4),MID(J5,6,2),1),F5)))*12+MONTH(ReportTo)-MONTH(IF(J5<>"",DATE(LEFT(J5,4),MID(J5,6,2),1),F5))+1))),"")) | T5: =IF(A5="","",IFERROR(N(G5)-N(S5),""))
R6: =IF(OR(A6="",N(I6)=0),0,ROUND((N(G6)-N(H6))/N(I6),2)) | S6: =IF(A6="","",IFERROR(MIN(N(G6)-N(H6),MAX(N(K6),R6*MAX(0,(YEAR(ReportTo)-YEAR(IF(J6<>"",DATE(LEFT(J6,4),MID(J6,6,2),1),F6)))*12+MONTH(ReportTo)-MONTH(IF(J6<>"",DATE(LEFT(J6,4),MID(J6,6,2),1),F6))+1))),"")) | T6: =IF(A6="","",IFERROR(N(G6)-N(S6),""))
R7: =IF(OR(A7="",N(I7)=0),0,ROUND((N(G7)-N(H7))/N(I7),2)) | S7: =IF(A7="","",IFERROR(MIN(N(G7)-N(H7),MAX(N(K7),R7*MAX(0,(YEAR(ReportTo)-YEAR(IF(J7<>"",DATE(LEFT(J7,4),MID(J7,6,2),1),F7)))*12+MONTH(ReportTo)-MONTH(IF(J7<>"",DATE(LEFT(J7,4),MID(J7,6,2),1),F7))+1))),"")) | T7: =IF(A7="","",IFERROR(N(G7)-N(S7),""))
R8: =IF(OR(A8="",N(I8)=0),0,ROUND((N(G8)-N(H8))/N(I8),2)) | S8: =IF(A8="","",IFERROR(MIN(N(G8)-N(H8),MAX(N(K8),R8*MAX(0,(YEAR(ReportTo)-YEAR(IF(J8<>"",DATE(LEFT(J8,4),MID(J8,6,2),1),F8)))*12+MONTH(ReportTo)-MONTH(IF(J8<>"",DATE(LEFT(J8,4),MID(J8,6,2),1),F8))+1))),"")) | T8: =IF(A8="","",IFERROR(N(G8)-N(S8),""))
R9: =IF(OR(A9="",N(I9)=0),0,ROUND((N(G9)-N(H9))/N(I9),2)) | S9: =IF(A9="","",IFERROR(MIN(N(G9)-N(H9),MAX(N(K9),R9*MAX(0,(YEAR(ReportTo)-YEAR(IF(J9<>"",DATE(LEFT(J9,4),MID(J9,6,2),1),F9)))*12+MONTH(ReportTo)-MONTH(IF(J9<>"",DATE(LEFT(J9,4),MID(J9,6,2),1),F9))+1))),"")) | T9: =IF(A9="","",IFERROR(N(G9)-N(S9),""))
R10: =IF(OR(A10="",N(I10)=0),0,ROUND((N(G10)-N(H10))/N(I10),2)) | S10: =IF(A10="","",IFERROR(MIN(N(G10)-N(H10),MAX(N(K10),R10*MAX(0,(YEAR(ReportTo)-YEAR(IF(J10<>"",DATE(LEFT(J10,4),MID(J10,6,2),1),F10)))*12+MONTH(ReportTo)-MONTH(IF(J10<>"",DATE(LEFT(J10,4),MID(J10,6,2),1),F10))+1))),"")) | T10: =IF(A10="","",IFERROR(N(G10)-N(S10),""))
R11: =IF(OR(A11="",N(I11)=0),0,ROUND((N(G11)-N(H11))/N(I11),2)) | S11: =IF(A11="","",IFERROR(MIN(N(G11)-N(H11),MAX(N(K11),R11*MAX(0,(YEAR(ReportTo)-YEAR(IF(J11<>"",DATE(LEFT(J11,4),MID(J11,6,2),1),F11)))*12+MONTH(ReportTo)-MONTH(IF(J11<>"",DATE(LEFT(J11,4),MID(J11,6,2),1),F11))+1))),"")) | T11: =IF(A11="","",IFERROR(N(G11)-N(S11),""))
R12: =IF(OR(A12="",N(I12)=0),0,ROUND((N(G12)-N(H12))/N(I12),2)) | S12: =IF(A12="","",IFERROR(MIN(N(G12)-N(H12),MAX(N(K12),R12*MAX(0,(YEAR(ReportTo)-YEAR(IF(J12<>"",DATE(LEFT(J12,4),MID(J12,6,2),1),F12)))*12+MONTH(ReportTo)-MONTH(IF(J12<>"",DATE(LEFT(J12,4),MID(J12,6,2),1),F12))+1))),"")) | T12: =IF(A12="","",IFERROR(N(G12)-N(S12),""))
R13: =IF(OR(A13="",N(I13)=0),0,ROUND((N(G13)-N(H13))/N(I13),2)) | S13: =IF(A13="","",IFERROR(MIN(N(G13)-N(H13),MAX(N(K13),R13*MAX(0,(YEAR(ReportTo)-YEAR(IF(J13<>"",DATE(LEFT(J13,4),MID(J13,6,2),1),F13)))*12+MONTH(ReportTo)-MONTH(IF(J13<>"",DATE(LEFT(J13,4),MID(J13,6,2),1),F13))+1))),"")) | T13: =IF(A13="","",IFERROR(N(G13)-N(S13),""))
R14: =IF(OR(A14="",N(I14)=0),0,ROUND((N(G14)-N(H14))/N(I14),2)) | S14: =IF(A14="","",IFERROR(MIN(N(G14)-N(H14),MAX(N(K14),R14*MAX(0,(YEAR(ReportTo)-YEAR(IF(J14<>"",DATE(LEFT(J14,4),MID(J14,6,2),1),F14)))*12+MONTH(ReportTo)-MONTH(IF(J14<>"",DATE(LEFT(J14,4),MID(J14,6,2),1),F14))+1))),"")) | T14: =IF(A14="","",IFERROR(N(G14)-N(S14),""))
R15: =IF(OR(A15="",N(I15)=0),0,ROUND((N(G15)-N(H15))/N(I15),2)) | S15: =IF(A15="","",IFERROR(MIN(N(G15)-N(H15),MAX(N(K15),R15*MAX(0,(YEAR(ReportTo)-YEAR(IF(J15<>"",DATE(LEFT(J15,4),MID(J15,6,2),1),F15)))*12+MONTH(ReportTo)-MONTH(IF(J15<>"",DATE(LEFT(J15,4),MID(J15,6,2),1),F15))+1))),"")) | T15: =IF(A15="","",IFERROR(N(G15)-N(S15),""))
R16: =IF(OR(A16="",N(I16)=0),0,ROUND((N(G16)-N(H16))/N(I16),2)) | S16: =IF(A16="","",IFERROR(MIN(N(G16)-N(H16),MAX(N(K16),R16*MAX(0,(YEAR(ReportTo)-YEAR(IF(J16<>"",DATE(LEFT(J16,4),MID(J16,6,2),1),F16)))*12+MONTH(ReportTo)-MONTH(IF(J16<>"",DATE(LEFT(J16,4),MID(J16,6,2),1),F16))+1))),"")) | T16: =IF(A16="","",IFERROR(N(G16)-N(S16),""))
... R204: =IF(OR(A204="",N(I204)=0),0,ROUND((N(G204)-N(H204))/N(I204),2)) | S204: =IF(A204="","",IFERROR(MIN(N(G204)-N(H204),MAX(N(K204),R204*MAX(0,(YEAR(ReportTo)-YEAR(IF(J204<>"",DATE(LEFT(J204,4),MID(J204,6,2),1),F204)))*12+MONTH(ReportTo)-MONTH(IF(J204<>"",DATE(LEFT(J204,4),MID(J204,6,2),1),F204))+1))),"")) | T204: =IF(A204="","",IFERROR(N(G204)-N(S204),""))

Sheet Warehouses
A1: BEYOND DESIGN | WAREHOUSES
A2: Warehouses / stores and their inventory account
A3: e.g. Site Store — Villa 12 | B3: New Cairo | C3: 1200
A4: Warehouse | B4: Location | C4: Inventory Account
A5: Main Store | C5: 1200

Sheet Stock Items
A1: BEYOND DESIGN | STOCK ITEMS
A2: Item master
A3: e.g. Ceramic tiles 60×60 | B3: m2 | C3: CT-6060 | D3: 50
A4: Item | B4: Unit | C4: SKU | D4: Reorder Level

Sheet Price List
A1: BEYOND DESIGN | PRICE LIST
A2: Unit-rate price list (historical cost × (1 + markup) = client price)
A3: e.g. أعمال البياض | B3: 3.1 | D3: بياض حوائط | E3: م٢ | F3: 219.23 | G3: 30%
A4: Category | B4: Item No. | C4: Sub-category | D4: Description | E4: Unit | F4: Unit Cost | G4: Markup % | H4: Client Price | I4: Notes | J4: ETA Item Code

Sheet BOQ Lines
A1: BEYOND DESIGN | BOQ LINES
A2: Bills of quantities — one row per line; rows with the same BOQ Title + Business Unit form one BOQ
A3: e.g. Interior works | B3: PRJ-2026-004 | C3: Rev 01 | D3: 2026-10-01 | G3: أعمال البياض | I3: 3.1 | J3: بياض حوائط | K3: م٢ | L3: 320 | M3: 285 | N3: 219.23
A4: BOQ Title | B4: Business Unit | C4: Revision | D4: Date | E4: Client | F4: Location | G4: Category | H4: Sub-category | I4: Item No. | J4: Description | K4: Unit | L4: Qty | M4: Unit Price | N4: Unit Cost | O4: Amount
O5: =ROUND(N(L5)*N(M5),2)
O6: =ROUND(N(L6)*N(M6),2)
O7: =ROUND(N(L7)*N(M7),2)
O8: =ROUND(N(L8)*N(M8),2)
O9: =ROUND(N(L9)*N(M9),2)
O10: =ROUND(N(L10)*N(M10),2)
O11: =ROUND(N(L11)*N(M11),2)
O12: =ROUND(N(L12)*N(M12),2)
O13: =ROUND(N(L13)*N(M13),2)
O14: =ROUND(N(L14)*N(M14),2)
O15: =ROUND(N(L15)*N(M15),2)
O16: =ROUND(N(L16)*N(M16),2)
... O204: =ROUND(N(L204)*N(M204),2)

Sheet Direct Costs
A1: BEYOND DESIGN | DIRECT COSTS
A2: Direct costs (cost of revenue) per business unit — materials, subcontractors, site work
A3: e.g. 2026-10-03 | B3: PRJ-2026-004 | C3: 5010 | D3: Cement 50 kg | E3: El-Masry Supplies | H3: 16 | I3: bag | J3: 240 | L3: 2000 | M3: Cash | P3: VAT14 | Q3: WHT1-S
A4: Date | B4: Business Unit | C4: Cost Account | D4: Description | E4: Supplier | F4: Deal Ref. | G4: Deal Status | H4: Qty | I4: Unit | J4: Unit Cost | K4: Negotiation Discount | L4: Paid Now | M4: Payment Method | N4: Paid From | O4: Payable Account | P4: VAT Code | Q4: WHT Code | R4: Total Cost | S4: Input VAT | T4: WHT Withheld | U4: Unpaid | V4: account (effective) | W4: paid_from (effective) | X4: payable_account (effective) | Y4: vat_input account | Z4: wht_payable account | AA4: leg 1 type | AB4: leg 2 type | AC4: leg 3 type | AD4: leg 4 type | AE4: leg 5 type | AF4: revenue | AG4: cost of sales | AH4: expenses | AI4: operating expenses | AJ4: payables | AK4: accruals | AL4: unknown account
R5: =ROUND(N(H5)*N(J5)-N(K5),2) | S5: =ROUND(R5*IFERROR(VLOOKUP(P5,'Tax Codes'!$A$5:$E$300,5,FALSE),0),2) | T5: =ROUND(R5*IFERROR(VLOOKUP(Q5,'Tax Codes'!$A$5:$E$300,5,FALSE),0),2) | U5: =R5+S5-T5-N(L5) | V5: =IF(C5="",INDEX('Chart of Accounts'!$A$5:$A$3000,MATCH("materials",'Chart of Accounts'!$F$5:$F$3000,0)),C5&"") | W5: =IF(N5="",INDEX('Chart of Accounts'!$A$5:$A$3000,MATCH("bank",'Chart of Accounts'!$F$5:$F$3000,0)),N5&"") | X5: =IF(O5="",INDEX('Chart of Accounts'!$A$5:$A$3000,MATCH("ap",'Chart of Accounts'!$F$5:$F$3000,0)),O5&"") | Y5: =INDEX('Chart of Accounts'!$A$5:$A$3000,MATCH("vat_input",'Chart of Accounts'!$F$5:$F$3000,0)) | Z5: =INDEX('Chart of Accounts'!$A$5:$A$3000,MATCH("wht_payable",'Chart of Accounts'!$F$5:$F$3000,0)) | AA5: =IFERROR(INDEX('Chart of Accounts'!$C$5:$C$3000,MATCH(V5&"",'Chart of Accounts'!$A$5:$A$3000,0))&"|"&INDEX('Chart of Accounts'!$D$5:$D$3000,MATCH(V5&"",'Chart of Accounts'!$A$5:$A$3000,0)),"") | AB5: =IFERROR(INDEX('Chart of Accounts'!$C$5:$C$3000,MATCH(Y5&"",'Chart of Accounts'!$A$5:$A$3000,0))&"|"&INDEX('Chart of Accounts'!$D$5:$D$3000,MATCH(Y5&"",'Chart of Accounts'!$A$5:$A$3000,0)),"") | AC5: =IFERROR(INDEX('Chart of Accounts'!$C$5:$C$3000,MATCH(W5&"",'Chart of Accounts'!$A$5:$A$3000,0))&"|"&INDEX('Chart of Accounts'!$D$5:$D$3000,MATCH(W5&"",'Chart of Accounts'!$A$5:$A$3000,0)),"") | AD5: =IFERROR(INDEX('Chart of Accounts'!$C$5:$C$3000,MATCH(X5&"",'Chart of Accounts'!$A$5:$A$3000,0))&"|"&INDEX('Chart of Accounts'!$D$5:$D$3000,MATCH(X5&"",'Chart of Accounts'!$A$5:$A$3000,0)),"") | AE5: =IFERROR(INDEX('Chart of Accounts'!$C$5:$C$3000,MATCH(Z5&"",'Chart of Accounts'!$A$5:$A$3000,0))&"|"&INDEX('Chart of Accounts'!$D$5:$D$3000,MATCH(Z5&"",'Chart of Accounts'!$A$5:$A$3000,0)),"") | AF5: =IF(LEFT(AA5,8)="Revenue|",-N(R5),0)+IF(LEFT(AB5,8)="Revenue|",-N(S5),0)+IF(LEFT(AC5,8)="Revenue|",N(L5),0)+IF(LEFT(AD5,8)="Revenue|",N(U5),0)+IF(LEFT(AE5,8)="Revenue|",N(T5),0) | AG5: =IF(LEFT(AA5,5)="COGS|",N(R5),0)+IF(LEFT(AB5,5)="COGS|",N(S5),0)+IF(LEFT(AC5,5)="COGS|",-N(L5),0)+IF(LEFT(AD5,5)="COGS|",-N(U5),0)+IF(LEFT(AE5,5)="COGS|",-N(T5),0) | AH5: =IF(LEFT(AA5,8)="Expense|",N(R5),0)+IF(LEFT(AB5,8)="Expense|",N(S5),0)+IF(LEFT(AC5,8)="Expense|",-N(L5),0)+IF(LEFT(AD5,8)="Expense|",-N(U5),0)+IF(LEFT(AE5,8)="Expense|",-N(T5),0) | AI5: =IF(ISNUMBER(MATCH(AA5,{"Expense|employee","Expense|general_admin","Expense|marketing","Expense|utilities","Expense|other_operating"},0)),N(R5),0)+IF(ISNUMBER(MATCH(AB5,{"Expense|employee","Expense|general_admin","Expense|marketing","Expense|utilities","Expense|other_operating"},0)),N(S5),0)+IF(ISNUMBER(MATCH(AC5,{"Expense|employee","Expense|general_admin","Expense|marketing","Expense|utilities","Expense|other_operating"},0)),-N(L5),0)+IF(ISNUMBER(MATCH(AD5,{"Expense|employee","Expense|general_admin","Expense|marketing","Expense|utilities","Expense|other_operating"},0)),-N(U5),0)+IF(ISNUMBER(MATCH(AE5,{"Expense|employee","Expense|general_admin","Expense|marketing","Expense|utilities","Expense|other_operating"},0)),-N(T5),0) | AJ5: =IF(AA5="Liability|payable",-N(R5),0)+IF(AB5="Liability|payable",-N(S5),0)+IF(AC5="Liability|payable",N(L5),0)+IF(AD5="Liability|payable",N(U5),0)+IF(AE5="Liability|payable",N(T5),0) | AK5: =IF(AA5="Liability|accrued",-N(R5),0)+IF(AB5="Liability|accrued",-N(S5),0)+IF(AC5="Liability|accrued",N(L5),0)+IF(AD5="Liability|accrued",N(U5),0)+IF(AE5="Liability|accrued",N(T5),0) | AL5: =IF(AND(N(R5)<>0,AA5=""),1,0)+IF(AND(N(S5)<>0,AB5=""),1,0)+IF(AND(N(L5)<>0,AC5=""),1,0)+IF(AND(N(U5)<>0,AD5=""),1,0)+IF(AND(N(T5)<>0,AE5=""),1,0)
R6: =ROUND(N(H6)*N(J6)-N(K6),2) | S6: =ROUND(R6*IFERROR(VLOOKUP(P6,'Tax Codes'!$A$5:$E$300,5,FALSE),0),2) | T6: =ROUND(R6*IFERROR(VLOOKUP(Q6,'Tax Codes'!$A$5:$E$300,5,FALSE),0),2) | U6: =R6+S6-T6-N(L6) | V6: =IF(C6="",INDEX('Chart of Accounts'!$A$5:$A$3000,MATCH("materials",'Chart of Accounts'!$F$5:$F$3000,0)),C6&"") | W6: =IF(N6="",INDEX('Chart of Accounts'!$A$5:$A$3000,MATCH("bank",'Chart of Accounts'!$F$5:$F$3000,0)),N6&"") | X6: =IF(O6="",INDEX('Chart of Accounts'!$A$5:$A$3000,MATCH("ap",'Chart of Accounts'!$F$5:$F$3000,0)),O6&"") | Y6: =INDEX('Chart of Accounts'!$A$5:$A$3000,MATCH("vat_input",'Chart of Accounts'!$F$5:$F$3000,0)) | Z6: =INDEX('Chart of Accounts'!$A$5:$A$3000,MATCH("wht_payable",'Chart of Accounts'!$F$5:$F$3000,0)) | AA6: =IFERROR(INDEX('Chart of Accounts'!$C$5:$C$3000,MATCH(V6&"",'Chart of Accounts'!$A$5:$A$3000,0))&"|"&INDEX('Chart of Accounts'!$D$5:$D$3000,MATCH(V6&"",'Chart of Accounts'!$A$5:$A$3000,0)),"") | AB6: =IFERROR(INDEX('Chart of Accounts'!$C$5:$C$3000,MATCH(Y6&"",'Chart of Accounts'!$A$5:$A$3000,0))&"|"&INDEX('Chart of Accounts'!$D$5:$D$3000,MATCH(Y6&"",'Chart of Accounts'!$A$5:$A$3000,0)),"") | AC6: =IFERROR(INDEX('Chart of Accounts'!$C$5:$C$3000,MATCH(W6&"",'Chart of Accounts'!$A$5:$A$3000,0))&"|"&INDEX('Chart of Accounts'!$D$5:$D$3000,MATCH(W6&"",'Chart of Accounts'!$A$5:$A$3000,0)),"") | AD6: =IFERROR(INDEX('Chart of Accounts'!$C$5:$C$3000,MATCH(X6&"",'Chart of Accounts'!$A$5:$A$3000,0))&"|"&INDEX('Chart of Accounts'!$D$5:$D$3000,MATCH(X6&"",'Chart of Accounts'!$A$5:$A$3000,0)),"") | AE6: =IFERROR(INDEX('Chart of Accounts'!$C$5:$C$3000,MATCH(Z6&"",'Chart of Accounts'!$A$5:$A$3000,0))&"|"&INDEX('Chart of Accounts'!$D$5:$D$3000,MATCH(Z6&"",'Chart of Accounts'!$A$5:$A$3000,0)),"") | AF6: =IF(LEFT(AA6,8)="Revenue|",-N(R6),0)+IF(LEFT(AB6,8)="Revenue|",-N(S6),0)+IF(LEFT(AC6,8)="Revenue|",N(L6),0)+IF(LEFT(AD6,8)="Revenue|",N(U6),0)+IF(LEFT(AE6,8)="Revenue|",N(T6),0) | AG6: =IF(LEFT(AA6,5)="COGS|",N(R6),0)+IF(LEFT(AB6,5)="COGS|",N(S6),0)+IF(LEFT(AC6,5)="COGS|",-N(L6),0)+IF(LEFT(AD6,5)="COGS|",-N(U6),0)+IF(LEFT(AE6,5)="COGS|",-N(T6),0) | AH6: =IF(LEFT(AA6,8)="Expense|",N(R6),0)+IF(LEFT(AB6,8)="Expense|",N(S6),0)+IF(LEFT(AC6,8)="Expense|",-N(L6),0)+IF(LEFT(AD6,8)="Expense|",-N(U6),0)+IF(LEFT(AE6,8)="Expense|",-N(T6),0) | AI6: =IF(ISNUMBER(MATCH(AA6,{"Expense|employee","Expense|general_admin","Expense|marketing","Expense|utilities","Expense|other_operating"},0)),N(R6),0)+IF(ISNUMBER(MATCH(AB6,{"Expense|employee","Expense|general_admin","Expense|marketing","Expense|utilities","Expense|other_operating"},0)),N(S6),0)+IF(ISNUMBER(MATCH(AC6,{"Expense|employee","Expense|general_admin","Expense|marketing","Expense|utilities","Expense|other_operating"},0)),-N(L6),0)+IF(ISNUMBER(MATCH(AD6,{"Expense|employee","Expense|general_admin","Expense|marketing","Expense|utilities","Expense|other_operating"},0)),-N(U6),0)+IF(ISNUMBER(MATCH(AE6,{"Expense|employee","Expense|general_admin","Expense|marketing","Expense|utilities","Expense|other_operating"},0)),-N(T6),0) | AJ6: =IF(AA6="Liability|payable",-N(R6),0)+IF(AB6="Liability|payable",-N(S6),0)+IF(AC6="Liability|payable",N(L6),0)+IF(AD6="Liability|payable",N(U6),0)+IF(AE6="Liability|payable",N(T6),0) | AK6: =IF(AA6="Liability|accrued",-N(R6),0)+IF(AB6="Liability|accrued",-N(S6),0)+IF(AC6="Liability|accrued",N(L6),0)+IF(AD6="Liability|accrued",N(U6),0)+IF(AE6="Liability|accrued",N(T6),0) | AL6: =IF(AND(N(R6)<>0,AA6=""),1,0)+IF(AND(N(S6)<>0,AB6=""),1,0)+IF(AND(N(L6)<>0,AC6=""),1,0)+IF(AND(N(U6)<>0,AD6=""),1,0)+IF(AND(N(T6)<>0,AE6=""),1,0)
R7: =ROUND(N(H7)*N(J7)-N(K7),2) | S7: =ROUND(R7*IFERROR(VLOOKUP(P7,'Tax Codes'!$A$5:$E$300,5,FALSE),0),2) | T7: =ROUND(R7*IFERROR(VLOOKUP(Q7,'Tax Codes'!$A$5:$E$300,5,FALSE),0),2) | U7: =R7+S7-T7-N(L7) | V7: =IF(C7="",INDEX('Chart of Accounts'!$A$5:$A$3000,MATCH("materials",'Chart of Accounts'!$F$5:$F$3000,0)),C7&"") | W7: =IF(N7="",INDEX('Chart of Accounts'!$A$5:$A$3000,MATCH("bank",'Chart of Accounts'!$F$5:$F$3000,0)),N7&"") | X7: =IF(O7="",INDEX('Chart of Accounts'!$A$5:$A$3000,MATCH("ap",'Chart of Accounts'!$F$5:$F$3000,0)),O7&"") | Y7: =INDEX('Chart of Accounts'!$A$5:$A$3000,MATCH("vat_input",'Chart of Accounts'!$F$5:$F$3000,0)) | Z7: =INDEX('Chart of Accounts'!$A$5:$A$3000,MATCH("wht_payable",'Chart of Accounts'!$F$5:$F$3000,0)) | AA7: =IFERROR(INDEX('Chart of Accounts'!$C$5:$C$3000,MATCH(V7&"",'Chart of Accounts'!$A$5:$A$3000,0))&"|"&INDEX('Chart of Accounts'!$D$5:$D$3000,MATCH(V7&"",'Chart of Accounts'!$A$5:$A$3000,0)),"") | AB7: =IFERROR(INDEX('Chart of Accounts'!$C$5:$C$3000,MATCH(Y7&"",'Chart of Accounts'!$A$5:$A$3000,0))&"|"&INDEX('Chart of Accounts'!$D$5:$D$3000,MATCH(Y7&"",'Chart of Accounts'!$A$5:$A$3000,0)),"") | AC7: =IFERROR(INDEX('Chart of Accounts'!$C$5:$C$3000,MATCH(W7&"",'Chart of Accounts'!$A$5:$A$3000,0))&"|"&INDEX('Chart of Accounts'!$D$5:$D$3000,MATCH(W7&"",'Chart of Accounts'!$A$5:$A$3000,0)),"") | AD7: =IFERROR(INDEX('Chart of Accounts'!$C$5:$C$3000,MATCH(X7&"",'Chart of Accounts'!$A$5:$A$3000,0))&"|"&INDEX('Chart of Accounts'!$D$5:$D$3000,MATCH(X7&"",'Chart of Accounts'!$A$5:$A$3000,0)),"") | AE7: =IFERROR(INDEX('Chart of Accounts'!$C$5:$C$3000,MATCH(Z7&"",'Chart of Accounts'!$A$5:$A$3000,0))&"|"&INDEX('Chart of Accounts'!$D$5:$D$3000,MATCH(Z7&"",'Chart of Accounts'!$A$5:$A$3000,0)),"") | AF7: =IF(LEFT(AA7,8)="Revenue|",-N(R7),0)+IF(LEFT(AB7,8)="Revenue|",-N(S7),0)+IF(LEFT(AC7,8)="Revenue|",N(L7),0)+IF(LEFT(AD7,8)="Revenue|",N(U7),0)+IF(LEFT(AE7,8)="Revenue|",N(T7),0) | AG7: =IF(LEFT(AA7,5)="COGS|",N(R7),0)+IF(LEFT(AB7,5)="COGS|",N(S7),0)+IF(LEFT(AC7,5)="COGS|",-N(L7),0)+IF(LEFT(AD7,5)="COGS|",-N(U7),0)+IF(LEFT(AE7,5)="COGS|",-N(T7),0) | AH7: =IF(LEFT(AA7,8)="Expense|",N(R7),0)+IF(LEFT(AB7,8)="Expense|",N(S7),0)+IF(LEFT(AC7,8)="Expense|",-N(L7),0)+IF(LEFT(AD7,8)="Expense|",-N(U7),0)+IF(LEFT(AE7,8)="Expense|",-N(T7),0) | AI7: =IF(ISNUMBER(MATCH(AA7,{"Expense|employee","Expense|general_admin","Expense|marketing","Expense|utilities","Expense|other_operating"},0)),N(R7),0)+IF(ISNUMBER(MATCH(AB7,{"Expense|employee","Expense|general_admin","Expense|marketing","Expense|utilities","Expense|other_operating"},0)),N(S7),0)+IF(ISNUMBER(MATCH(AC7,{"Expense|employee","Expense|general_admin","Expense|marketing","Expense|utilities","Expense|other_operating"},0)),-N(L7),0)+IF(ISNUMBER(MATCH(AD7,{"Expense|employee","Expense|general_admin","Expense|marketing","Expense|utilities","Expense|other_operating"},0)),-N(U7),0)+IF(ISNUMBER(MATCH(AE7,{"Expense|employee","Expense|general_admin","Expense|marketing","Expense|utilities","Expense|other_operating"},0)),-N(T7),0) | AJ7: =IF(AA7="Liability|payable",-N(R7),0)+IF(AB7="Liability|payable",-N(S7),0)+IF(AC7="Liability|payable",N(L7),0)+IF(AD7="Liability|payable",N(U7),0)+IF(AE7="Liability|payable",N(T7),0) | AK7: =IF(AA7="Liability|accrued",-N(R7),0)+IF(AB7="Liability|accrued",-N(S7),0)+IF(AC7="Liability|accrued",N(L7),0)+IF(AD7="Liability|accrued",N(U7),0)+IF(AE7="Liability|accrued",N(T7),0) | AL7: =IF(AND(N(R7)<>0,AA7=""),1,0)+IF(AND(N(S7)<>0,AB7=""),1,0)+IF(AND(N(L7)<>0,AC7=""),1,0)+IF(AND(N(U7)<>0,AD7=""),1,0)+IF(AND(N(T7)<>0,AE7=""),1,0)
R8: =ROUND(N(H8)*N(J8)-N(K8),2) | S8: =ROUND(R8*IFERROR(VLOOKUP(P8,'Tax Codes'!$A$5:$E$300,5,FALSE),0),2) | T8: =ROUND(R8*IFERROR(VLOOKUP(Q8,'Tax Codes'!$A$5:$E$300,5,FALSE),0),2) | U8: =R8+S8-T8-N(L8) | V8: =IF(C8="",INDEX('Chart of Accounts'!$A$5:$A$3000,MATCH("materials",'Chart of Accounts'!$F$5:$F$3000,0)),C8&"") | W8: =IF(N8="",INDEX('Chart of Accounts'!$A$5:$A$3000,MATCH("bank",'Chart of Accounts'!$F$5:$F$3000,0)),N8&"") | X8: =IF(O8="",INDEX('Chart of Accounts'!$A$5:$A$3000,MATCH("ap",'Chart of Accounts'!$F$5:$F$3000,0)),O8&"") | Y8: =INDEX('Chart of Accounts'!$A$5:$A$3000,MATCH("vat_input",'Chart of Accounts'!$F$5:$F$3000,0)) | Z8: =INDEX('Chart of Accounts'!$A$5:$A$3000,MATCH("wht_payable",'Chart of Accounts'!$F$5:$F$3000,0)) | AA8: =IFERROR(INDEX('Chart of Accounts'!$C$5:$C$3000,MATCH(V8&"",'Chart of Accounts'!$A$5:$A$3000,0))&"|"&INDEX('Chart of Accounts'!$D$5:$D$3000,MATCH(V8&"",'Chart of Accounts'!$A$5:$A$3000,0)),"") | AB8: =IFERROR(INDEX('Chart of Accounts'!$C$5:$C$3000,MATCH(Y8&"",'Chart of Accounts'!$A$5:$A$3000,0))&"|"&INDEX('Chart of Accounts'!$D$5:$D$3000,MATCH(Y8&"",'Chart of Accounts'!$A$5:$A$3000,0)),"") | AC8: =IFERROR(INDEX('Chart of Accounts'!$C$5:$C$3000,MATCH(W8&"",'Chart of Accounts'!$A$5:$A$3000,0))&"|"&INDEX('Chart of Accounts'!$D$5:$D$3000,MATCH(W8&"",'Chart of Accounts'!$A$5:$A$3000,0)),"") | AD8: =IFERROR(INDEX('Chart of Accounts'!$C$5:$C$3000,MATCH(X8&"",'Chart of Accounts'!$A$5:$A$3000,0))&"|"&INDEX('Chart of Accounts'!$D$5:$D$3000,MATCH(X8&"",'Chart of Accounts'!$A$5:$A$3000,0)),"") | AE8: =IFERROR(INDEX('Chart of Accounts'!$C$5:$C$3000,MATCH(Z8&"",'Chart of Accounts'!$A$5:$A$3000,0))&"|"&INDEX('Chart of Accounts'!$D$5:$D$3000,MATCH(Z8&"",'Chart of Accounts'!$A$5:$A$3000,0)),"") | AF8: =IF(LEFT(AA8,8)="Revenue|",-N(R8),0)+IF(LEFT(AB8,8)="Revenue|",-N(S8),0)+IF(LEFT(AC8,8)="Revenue|",N(L8),0)+IF(LEFT(AD8,8)="Revenue|",N(U8),0)+IF(LEFT(AE8,8)="Revenue|",N(T8),0) | AG8: =IF(LEFT(AA8,5)="COGS|",N(R8),0)+IF(LEFT(AB8,5)="COGS|",N(S8),0)+IF(LEFT(AC8,5)="COGS|",-N(L8),0)+IF(LEFT(AD8,5)="COGS|",-N(U8),0)+IF(LEFT(AE8,5)="COGS|",-N(T8),0) | AH8: =IF(LEFT(AA8,8)="Expense|",N(R8),0)+IF(LEFT(AB8,8)="Expense|",N(S8),0)+IF(LEFT(AC8,8)="Expense|",-N(L8),0)+IF(LEFT(AD8,8)="Expense|",-N(U8),0)+IF(LEFT(AE8,8)="Expense|",-N(T8),0) | AI8: =IF(ISNUMBER(MATCH(AA8,{"Expense|employee","Expense|general_admin","Expense|marketing","Expense|utilities","Expense|other_operating"},0)),N(R8),0)+IF(ISNUMBER(MATCH(AB8,{"Expense|employee","Expense|general_admin","Expense|marketing","Expense|utilities","Expense|other_operating"},0)),N(S8),0)+IF(ISNUMBER(MATCH(AC8,{"Expense|employee","Expense|general_admin","Expense|marketing","Expense|utilities","Expense|other_operating"},0)),-N(L8),0)+IF(ISNUMBER(MATCH(AD8,{"Expense|employee","Expense|general_admin","Expense|marketing","Expense|utilities","Expense|other_operating"},0)),-N(U8),0)+IF(ISNUMBER(MATCH(AE8,{"Expense|employee","Expense|general_admin","Expense|marketing","Expense|utilities","Expense|other_operating"},0)),-N(T8),0) | AJ8: =IF(AA8="Liability|payable",-N(R8),0)+IF(AB8="Liability|payable",-N(S8),0)+IF(AC8="Liability|payable",N(L8),0)+IF(AD8="Liability|payable",N(U8),0)+IF(AE8="Liability|payable",N(T8),0) | AK8: =IF(AA8="Liability|accrued",-N(R8),0)+IF(AB8="Liability|accrued",-N(S8),0)+IF(AC8="Liability|accrued",N(L8),0)+IF(AD8="Liability|accrued",N(U8),0)+IF(AE8="Liability|accrued",N(T8),0) | AL8: =IF(AND(N(R8)<>0,AA8=""),1,0)+IF(AND(N(S8)<>0,AB8=""),1,0)+IF(AND(N(L8)<>0,AC8=""),1,0)+IF(AND(N(U8)<>0,AD8=""),1,0)+IF(AND(N(T8)<>0,AE8=""),1,0)
R9: =ROUND(N(H9)*N(J9)-N(K9),2) | S9: =ROUND(R9*IFERROR(VLOOKUP(P9,'Tax Codes'!$A$5:$E$300,5,FALSE),0),2) | T9: =ROUND(R9*IFERROR(VLOOKUP(Q9,'Tax Codes'!$A$5:$E$300,5,FALSE),0),2) | U9: =R9+S9-T9-N(L9) | V9: =IF(C9="",INDEX('Chart of Accounts'!$A$5:$A$3000,MATCH("materials",'Chart of Accounts'!$F$5:$F$3000,0)),C9&"") | W9: =IF(N9="",INDEX('Chart of Accounts'!$A$5:$A$3000,MATCH("bank",'Chart of Accounts'!$F$5:$F$3000,0)),N9&"") | X9: =IF(O9="",INDEX('Chart of Accounts'!$A$5:$A$3000,MATCH("ap",'Chart of Accounts'!$F$5:$F$3000,0)),O9&"") | Y9: =INDEX('Chart of Accounts'!$A$5:$A$3000,MATCH("vat_input",'Chart of Accounts'!$F$5:$F$3000,0)) | Z9: =INDEX('Chart of Accounts'!$A$5:$A$3000,MATCH("wht_payable",'Chart of Accounts'!$F$5:$F$3000,0)) | AA9: =IFERROR(INDEX('Chart of Accounts'!$C$5:$C$3000,MATCH(V9&"",'Chart of Accounts'!$A$5:$A$3000,0))&"|"&INDEX('Chart of Accounts'!$D$5:$D$3000,MATCH(V9&"",'Chart of Accounts'!$A$5:$A$3000,0)),"") | AB9: =IFERROR(INDEX('Chart of Accounts'!$C$5:$C$3000,MATCH(Y9&"",'Chart of Accounts'!$A$5:$A$3000,0))&"|"&INDEX('Chart of Accounts'!$D$5:$D$3000,MATCH(Y9&"",'Chart of Accounts'!$A$5:$A$3000,0)),"") | AC9: =IFERROR(INDEX('Chart of Accounts'!$C$5:$C$3000,MATCH(W9&"",'Chart of Accounts'!$A$5:$A$3000,0))&"|"&INDEX('Chart of Accounts'!$D$5:$D$3000,MATCH(W9&"",'Chart of Accounts'!$A$5:$A$3000,0)),"") | AD9: =IFERROR(INDEX('Chart of Accounts'!$C$5:$C$3000,MATCH(X9&"",'Chart of Accounts'!$A$5:$A$3000,0))&"|"&INDEX('Chart of Accounts'!$D$5:$D$3000,MATCH(X9&"",'Chart of Accounts'!$A$5:$A$3000,0)),"") | AE9: =IFERROR(INDEX('Chart of Accounts'!$C$5:$C$3000,MATCH(Z9&"",'Chart of Accounts'!$A$5:$A$3000,0))&"|"&INDEX('Chart of Accounts'!$D$5:$D$3000,MATCH(Z9&"",'Chart of Accounts'!$A$5:$A$3000,0)),"") | AF9: =IF(LEFT(AA9,8)="Revenue|",-N(R9),0)+IF(LEFT(AB9,8)="Revenue|",-N(S9),0)+IF(LEFT(AC9,8)="Revenue|",N(L9),0)+IF(LEFT(AD9,8)="Revenue|",N(U9),0)+IF(LEFT(AE9,8)="Revenue|",N(T9),0) | AG9: =IF(LEFT(AA9,5)="COGS|",N(R9),0)+IF(LEFT(AB9,5)="COGS|",N(S9),0)+IF(LEFT(AC9,5)="COGS|",-N(L9),0)+IF(LEFT(AD9,5)="COGS|",-N(U9),0)+IF(LEFT(AE9,5)="COGS|",-N(T9),0) | AH9: =IF(LEFT(AA9,8)="Expense|",N(R9),0)+IF(LEFT(AB9,8)="Expense|",N(S9),0)+IF(LEFT(AC9,8)="Expense|",-N(L9),0)+IF(LEFT(AD9,8)="Expense|",-N(U9),0)+IF(LEFT(AE9,8)="Expense|",-N(T9),0) | AI9: =IF(ISNUMBER(MATCH(AA9,{"Expense|employee","Expense|general_admin","Expense|marketing","Expense|utilities","Expense|other_operating"},0)),N(R9),0)+IF(ISNUMBER(MATCH(AB9,{"Expense|employee","Expense|general_admin","Expense|marketing","Expense|utilities","Expense|other_operating"},0)),N(S9),0)+IF(ISNUMBER(MATCH(AC9,{"Expense|employee","Expense|general_admin","Expense|marketing","Expense|utilities","Expense|other_operating"},0)),-N(L9),0)+IF(ISNUMBER(MATCH(AD9,{"Expense|employee","Expense|general_admin","Expense|marketing","Expense|utilities","Expense|other_operating"},0)),-N(U9),0)+IF(ISNUMBER(MATCH(AE9,{"Expense|employee","Expense|general_admin","Expense|marketing","Expense|utilities","Expense|other_operating"},0)),-N(T9),0) | AJ9: =IF(AA9="Liability|payable",-N(R9),0)+IF(AB9="Liability|payable",-N(S9),0)+IF(AC9="Liability|payable",N(L9),0)+IF(AD9="Liability|payable",N(U9),0)+IF(AE9="Liability|payable",N(T9),0) | AK9: =IF(AA9="Liability|accrued",-N(R9),0)+IF(AB9="Liability|accrued",-N(S9),0)+IF(AC9="Liability|accrued",N(L9),0)+IF(AD9="Liability|accrued",N(U9),0)+IF(AE9="Liability|accrued",N(T9),0) | AL9: =IF(AND(N(R9)<>0,AA9=""),1,0)+IF(AND(N(S9)<>0,AB9=""),1,0)+IF(AND(N(L9)<>0,AC9=""),1,0)+IF(AND(N(U9)<>0,AD9=""),1,0)+IF(AND(N(T9)<>0,AE9=""),1,0)
R10: =ROUND(N(H10)*N(J10)-N(K10),2) | S10: =ROUND(R10*IFERROR(VLOOKUP(P10,'Tax Codes'!$A$5:$E$300,5,FALSE),0),2) | T10: =ROUND(R10*IFERROR(VLOOKUP(Q10,'Tax Codes'!$A$5:$E$300,5,FALSE),0),2) | U10: =R10+S10-T10-N(L10) | V10: =IF(C10="",INDEX('Chart of Accounts'!$A$5:$A$3000,MATCH("materials",'Chart of Accounts'!$F$5:$F$3000,0)),C10&"") | W10: =IF(N10="",INDEX('Chart of Accounts'!$A$5:$A$3000,MATCH("bank",'Chart of Accounts'!$F$5:$F$3000,0)),N10&"") | X10: =IF(O10="",INDEX('Chart of Accounts'!$A$5:$A$3000,MATCH("ap",'Chart of Accounts'!$F$5:$F$3000,0)),O10&"") | Y10: =INDEX('Chart of Accounts'!$A$5:$A$3000,MATCH("vat_input",'Chart of Accounts'!$F$5:$F$3000,0)) | Z10: =INDEX('Chart of Accounts'!$A$5:$A$3000,MATCH("wht_payable",'Chart of Accounts'!$F$5:$F$3000,0)) | AA10: =IFERROR(INDEX('Chart of Accounts'!$C$5:$C$3000,MATCH(V10&"",'Chart of Accounts'!$A$5:$A$3000,0))&"|"&INDEX('Chart of Accounts'!$D$5:$D$3000,MATCH(V10&"",'Chart of Accounts'!$A$5:$A$3000,0)),"") | AB10: =IFERROR(INDEX('Chart of Accounts'!$C$5:$C$3000,MATCH(Y10&"",'Chart of Accounts'!$A$5:$A$3000,0))&"|"&INDEX('Chart of Accounts'!$D$5:$D$3000,MATCH(Y10&"",'Chart of Accounts'!$A$5:$A$3000,0)),"") | AC10: =IFERROR(INDEX('Chart of Accounts'!$C$5:$C$3000,MATCH(W10&"",'Chart of Accounts'!$A$5:$A$3000,0))&"|"&INDEX('Chart of Accounts'!$D$5:$D$3000,MATCH(W10&"",'Chart of Accounts'!$A$5:$A$3000,0)),"") | AD10: =IFERROR(INDEX('Chart of Accounts'!$C$5:$C$3000,MATCH(X10&"",'Chart of Accounts'!$A$5:$A$3000,0))&"|"&INDEX('Chart of Accounts'!$D$5:$D$3000,MATCH(X10&"",'Chart of Accounts'!$A$5:$A$3000,0)),"") | AE10: =IFERROR(INDEX('Chart of Accounts'!$C$5:$C$3000,MATCH(Z10&"",'Chart of Accounts'!$A$5:$A$3000,0))&"|"&INDEX('Chart of Accounts'!$D$5:$D$3000,MATCH(Z10&"",'Chart of Accounts'!$A$5:$A$3000,0)),"") | AF10: =IF(LEFT(AA10,8)="Revenue|",-N(R10),0)+IF(LEFT(AB10,8)="Revenue|",-N(S10),0)+IF(LEFT(AC10,8)="Revenue|",N(L10),0)+IF(LEFT(AD10,8)="Revenue|",N(U10),0)+IF(LEFT(AE10,8)="Revenue|",N(T10),0) | AG10: =IF(LEFT(AA10,5)="COGS|",N(R10),0)+IF(LEFT(AB10,5)="COGS|",N(S10),0)+IF(LEFT(AC10,5)="COGS|",-N(L10),0)+IF(LEFT(AD10,5)="COGS|",-N(U10),0)+IF(LEFT(AE10,5)="COGS|",-N(T10),0) | AH10: =IF(LEFT(AA10,8)="Expense|",N(R10),0)+IF(LEFT(AB10,8)="Expense|",N(S10),0)+IF(LEFT(AC10,8)="Expense|",-N(L10),0)+IF(LEFT(AD10,8)="Expense|",-N(U10),0)+IF(LEFT(AE10,8)="Expense|",-N(T10),0) | AI10: =IF(ISNUMBER(MATCH(AA10,{"Expense|employee","Expense|general_admin","Expense|marketing","Expense|utilities","Expense|other_operating"},0)),N(R10),0)+IF(ISNUMBER(MATCH(AB10,{"Expense|employee","Expense|general_admin","Expense|marketing","Expense|utilities","Expense|other_operating"},0)),N(S10),0)+IF(ISNUMBER(MATCH(AC10,{"Expense|employee","Expense|general_admin","Expense|marketing","Expense|utilities","Expense|other_operating"},0)),-N(L10),0)+IF(ISNUMBER(MATCH(AD10,{"Expense|employee","Expense|general_admin","Expense|marketing","Expense|utilities","Expense|other_operating"},0)),-N(U10),0)+IF(ISNUMBER(MATCH(AE10,{"Expense|employee","Expense|general_admin","Expense|marketing","Expense|utilities","Expense|other_operating"},0)),-N(T10),0) | AJ10: =IF(AA10="Liability|payable",-N(R10),0)+IF(AB10="Liability|payable",-N(S10),0)+IF(AC10="Liability|payable",N(L10),0)+IF(AD10="Liability|payable",N(U10),0)+IF(AE10="Liability|payable",N(T10),0) | AK10: =IF(AA10="Liability|accrued",-N(R10),0)+IF(AB10="Liability|accrued",-N(S10),0)+IF(AC10="Liability|accrued",N(L10),0)+IF(AD10="Liability|accrued",N(U10),0)+IF(AE10="Liability|accrued",N(T10),0) | AL10: =IF(AND(N(R10)<>0,AA10=""),1,0)+IF(AND(N(S10)<>0,AB10=""),1,0)+IF(AND(N(L10)<>0,AC10=""),1,0)+IF(AND(N(U10)<>0,AD10=""),1,0)+IF(AND(N(T10)<>0,AE10=""),1,0)
R11: =ROUND(N(H11)*N(J11)-N(K11),2) | S11: =ROUND(R11*IFERROR(VLOOKUP(P11,'Tax Codes'!$A$5:$E$300,5,FALSE),0),2) | T11: =ROUND(R11*IFERROR(VLOOKUP(Q11,'Tax Codes'!$A$5:$E$300,5,FALSE),0),2) | U11: =R11+S11-T11-N(L11) | V11: =IF(C11="",INDEX('Chart of Accounts'!$A$5:$A$3000,MATCH("materials",'Chart of Accounts'!$F$5:$F$3000,0)),C11&"") | W11: =IF(N11="",INDEX('Chart of Accounts'!$A$5:$A$3000,MATCH("bank",'Chart of Accounts'!$F$5:$F$3000,0)),N11&"") | X11: =IF(O11="",INDEX('Chart of Accounts'!$A$5:$A$3000,MATCH("ap",'Chart of Accounts'!$F$5:$F$3000,0)),O11&"") | Y11: =INDEX('Chart of Accounts'!$A$5:$A$3000,MATCH("vat_input",'Chart of Accounts'!$F$5:$F$3000,0)) | Z11: =INDEX('Chart of Accounts'!$A$5:$A$3000,MATCH("wht_payable",'Chart of Accounts'!$F$5:$F$3000,0)) | AA11: =IFERROR(INDEX('Chart of Accounts'!$C$5:$C$3000,MATCH(V11&"",'Chart of Accounts'!$A$5:$A$3000,0))&"|"&INDEX('Chart of Accounts'!$D$5:$D$3000,MATCH(V11&"",'Chart of Accounts'!$A$5:$A$3000,0)),"") | AB11: =IFERROR(INDEX('Chart of Accounts'!$C$5:$C$3000,MATCH(Y11&"",'Chart of Accounts'!$A$5:$A$3000,0))&"|"&INDEX('Chart of Accounts'!$D$5:$D$3000,MATCH(Y11&"",'Chart of Accounts'!$A$5:$A$3000,0)),"") | AC11: =IFERROR(INDEX('Chart of Accounts'!$C$5:$C$3000,MATCH(W11&"",'Chart of Accounts'!$A$5:$A$3000,0))&"|"&INDEX('Chart of Accounts'!$D$5:$D$3000,MATCH(W11&"",'Chart of Accounts'!$A$5:$A$3000,0)),"") | AD11: =IFERROR(INDEX('Chart of Accounts'!$C$5:$C$3000,MATCH(X11&"",'Chart of Accounts'!$A$5:$A$3000,0))&"|"&INDEX('Chart of Accounts'!$D$5:$D$3000,MATCH(X11&"",'Chart of Accounts'!$A$5:$A$3000,0)),"") | AE11: =IFERROR(INDEX('Chart of Accounts'!$C$5:$C$3000,MATCH(Z11&"",'Chart of Accounts'!$A$5:$A$3000,0))&"|"&INDEX('Chart of Accounts'!$D$5:$D$3000,MATCH(Z11&"",'Chart of Accounts'!$A$5:$A$3000,0)),"") | AF11: =IF(LEFT(AA11,8)="Revenue|",-N(R11),0)+IF(LEFT(AB11,8)="Revenue|",-N(S11),0)+IF(LEFT(AC11,8)="Revenue|",N(L11),0)+IF(LEFT(AD11,8)="Revenue|",N(U11),0)+IF(LEFT(AE11,8)="Revenue|",N(T11),0) | AG11: =IF(LEFT(AA11,5)="COGS|",N(R11),0)+IF(LEFT(AB11,5)="COGS|",N(S11),0)+IF(LEFT(AC11,5)="COGS|",-N(L11),0)+IF(LEFT(AD11,5)="COGS|",-N(U11),0)+IF(LEFT(AE11,5)="COGS|",-N(T11),0) | AH11: =IF(LEFT(AA11,8)="Expense|",N(R11),0)+IF(LEFT(AB11,8)="Expense|",N(S11),0)+IF(LEFT(AC11,8)="Expense|",-N(L11),0)+IF(LEFT(AD11,8)="Expense|",-N(U11),0)+IF(LEFT(AE11,8)="Expense|",-N(T11),0) | AI11: =IF(ISNUMBER(MATCH(AA11,{"Expense|employee","Expense|general_admin","Expense|marketing","Expense|utilities","Expense|other_operating"},0)),N(R11),0)+IF(ISNUMBER(MATCH(AB11,{"Expense|employee","Expense|general_admin","Expense|marketing","Expense|utilities","Expense|other_operating"},0)),N(S11),0)+IF(ISNUMBER(MATCH(AC11,{"Expense|employee","Expense|general_admin","Expense|marketing","Expense|utilities","Expense|other_operating"},0)),-N(L11),0)+IF(ISNUMBER(MATCH(AD11,{"Expense|employee","Expense|general_admin","Expense|marketing","Expense|utilities","Expense|other_operating"},0)),-N(U11),0)+IF(ISNUMBER(MATCH(AE11,{"Expense|employee","Expense|general_admin","Expense|marketing","Expense|utilities","Expense|other_operating"},0)),-N(T11),0) | AJ11: =IF(AA11="Liability|payable",-N(R11),0)+IF(AB11="Liability|payable",-N(S11),0)+IF(AC11="Liability|payable",N(L11),0)+IF(AD11="Liability|payable",N(U11),0)+IF(AE11="Liability|payable",N(T11),0) | AK11: =IF(AA11="Liability|accrued",-N(R11),0)+IF(AB11="Liability|accrued",-N(S11),0)+IF(AC11="Liability|accrued",N(L11),0)+IF(AD11="Liability|accrued",N(U11),0)+IF(AE11="Liability|accrued",N(T11),0) | AL11: =IF(AND(N(R11)<>0,AA11=""),1,0)+IF(AND(N(S11)<>0,AB11=""),1,0)+IF(AND(N(L11)<>0,AC11=""),1,0)+IF(AND(N(U11)<>0,AD11=""),1,0)+IF(AND(N(T11)<>0,AE11=""),1,0)
R12: =ROUND(N(H12)*N(J12)-N(K12),2) | S12: =ROUND(R12*IFERROR(VLOOKUP(P12,'Tax Codes'!$A$5:$E$300,5,FALSE),0),2) | T12: =ROUND(R12*IFERROR(VLOOKUP(Q12,'Tax Codes'!$A$5:$E$300,5,FALSE),0),2) | U12: =R12+S12-T12-N(L12) | V12: =IF(C12="",INDEX('Chart of Accounts'!$A$5:$A$3000,MATCH("materials",'Chart of Accounts'!$F$5:$F$3000,0)),C12&"") | W12: =IF(N12="",INDEX('Chart of Accounts'!$A$5:$A$3000,MATCH("bank",'Chart of Accounts'!$F$5:$F$3000,0)),N12&"") | X12: =IF(O12="",INDEX('Chart of Accounts'!$A$5:$A$3000,MATCH("ap",'Chart of Accounts'!$F$5:$F$3000,0)),O12&"") | Y12: =INDEX('Chart of Accounts'!$A$5:$A$3000,MATCH("vat_input",'Chart of Accounts'!$F$5:$F$3000,0)) | Z12: =INDEX('Chart of Accounts'!$A$5:$A$3000,MATCH("wht_payable",'Chart of Accounts'!$F$5:$F$3000,0)) | AA12: =IFERROR(INDEX('Chart of Accounts'!$C$5:$C$3000,MATCH(V12&"",'Chart of Accounts'!$A$5:$A$3000,0))&"|"&INDEX('Chart of Accounts'!$D$5:$D$3000,MATCH(V12&"",'Chart of Accounts'!$A$5:$A$3000,0)),"") | AB12: =IFERROR(INDEX('Chart of Accounts'!$C$5:$C$3000,MATCH(Y12&"",'Chart of Accounts'!$A$5:$A$3000,0))&"|"&INDEX('Chart of Accounts'!$D$5:$D$3000,MATCH(Y12&"",'Chart of Accounts'!$A$5:$A$3000,0)),"") | AC12: =IFERROR(INDEX('Chart of Accounts'!$C$5:$C$3000,MATCH(W12&"",'Chart of Accounts'!$A$5:$A$3000,0))&"|"&INDEX('Chart of Accounts'!$D$5:$D$3000,MATCH(W12&"",'Chart of Accounts'!$A$5:$A$3000,0)),"") | AD12: =IFERROR(INDEX('Chart of Accounts'!$C$5:$C$3000,MATCH(X12&"",'Chart of Accounts'!$A$5:$A$3000,0))&"|"&INDEX('Chart of Accounts'!$D$5:$D$3000,MATCH(X12&"",'Chart of Accounts'!$A$5:$A$3000,0)),"") | AE12: =IFERROR(INDEX('Chart of Accounts'!$C$5:$C$3000,MATCH(Z12&"",'Chart of Accounts'!$A$5:$A$3000,0))&"|"&INDEX('Chart of Accounts'!$D$5:$D$3000,MATCH(Z12&"",'Chart of Accounts'!$A$5:$A$3000,0)),"") | AF12: =IF(LEFT(AA12,8)="Revenue|",-N(R12),0)+IF(LEFT(AB12,8)="Revenue|",-N(S12),0)+IF(LEFT(AC12,8)="Revenue|",N(L12),0)+IF(LEFT(AD12,8)="Revenue|",N(U12),0)+IF(LEFT(AE12,8)="Revenue|",N(T12),0) | AG12: =IF(LEFT(AA12,5)="COGS|",N(R12),0)+IF(LEFT(AB12,5)="COGS|",N(S12),0)+IF(LEFT(AC12,5)="COGS|",-N(L12),0)+IF(LEFT(AD12,5)="COGS|",-N(U12),0)+IF(LEFT(AE12,5)="COGS|",-N(T12),0) | AH12: =IF(LEFT(AA12,8)="Expense|",N(R12),0)+IF(LEFT(AB12,8)="Expense|",N(S12),0)+IF(LEFT(AC12,8)="Expense|",-N(L12),0)+IF(LEFT(AD12,8)="Expense|",-N(U12),0)+IF(LEFT(AE12,8)="Expense|",-N(T12),0) | AI12: =IF(ISNUMBER(MATCH(AA12,{"Expense|employee","Expense|general_admin","Expense|marketing","Expense|utilities","Expense|other_operating"},0)),N(R12),0)+IF(ISNUMBER(MATCH(AB12,{"Expense|employee","Expense|general_admin","Expense|marketing","Expense|utilities","Expense|other_operating"},0)),N(S12),0)+IF(ISNUMBER(MATCH(AC12,{"Expense|employee","Expense|general_admin","Expense|marketing","Expense|utilities","Expense|other_operating"},0)),-N(L12),0)+IF(ISNUMBER(MATCH(AD12,{"Expense|employee","Expense|general_admin","Expense|marketing","Expense|utilities","Expense|other_operating"},0)),-N(U12),0)+IF(ISNUMBER(MATCH(AE12,{"Expense|employee","Expense|general_admin","Expense|marketing","Expense|utilities","Expense|other_operating"},0)),-N(T12),0) | AJ12: =IF(AA12="Liability|payable",-N(R12),0)+IF(AB12="Liability|payable",-N(S12),0)+IF(AC12="Liability|payable",N(L12),0)+IF(AD12="Liability|payable",N(U12),0)+IF(AE12="Liability|payable",N(T12),0) | AK12: =IF(AA12="Liability|accrued",-N(R12),0)+IF(AB12="Liability|accrued",-N(S12),0)+IF(AC12="Liability|accrued",N(L12),0)+IF(AD12="Liability|accrued",N(U12),0)+IF(AE12="Liability|accrued",N(T12),0) | AL12: =IF(AND(N(R12)<>0,AA12=""),1,0)+IF(AND(N(S12)<>0,AB12=""),1,0)+IF(AND(N(L12)<>0,AC12=""),1,0)+IF(AND(N(U12)<>0,AD12=""),1,0)+IF(AND(N(T12)<>0,AE12=""),1,0)
R13: =ROUND(N(H13)*N(J13)-N(K13),2) | S13: =ROUND(R13*IFERROR(VLOOKUP(P13,'Tax Codes'!$A$5:$E$300,5,FALSE),0),2) | T13: =ROUND(R13*IFERROR(VLOOKUP(Q13,'Tax Codes'!$A$5:$E$300,5,FALSE),0),2) | U13: =R13+S13-T13-N(L13) | V13: =IF(C13="",INDEX('Chart of Accounts'!$A$5:$A$3000,MATCH("materials",'Chart of Accounts'!$F$5:$F$3000,0)),C13&"") | W13: =IF(N13="",INDEX('Chart of Accounts'!$A$5:$A$3000,MATCH("bank",'Chart of Accounts'!$F$5:$F$3000,0)),N13&"") | X13: =IF(O13="",INDEX('Chart of Accounts'!$A$5:$A$3000,MATCH("ap",'Chart of Accounts'!$F$5:$F$3000,0)),O13&"") | Y13: =INDEX('Chart of Accounts'!$A$5:$A$3000,MATCH("vat_input",'Chart of Accounts'!$F$5:$F$3000,0)) | Z13: =INDEX('Chart of Accounts'!$A$5:$A$3000,MATCH("wht_payable",'Chart of Accounts'!$F$5:$F$3000,0)) | AA13: =IFERROR(INDEX('Chart of Accounts'!$C$5:$C$3000,MATCH(V13&"",'Chart of Accounts'!$A$5:$A$3000,0))&"|"&INDEX('Chart of Accounts'!$D$5:$D$3000,MATCH(V13&"",'Chart of Accounts'!$A$5:$A$3000,0)),"") | AB13: =IFERROR(INDEX('Chart of Accounts'!$C$5:$C$3000,MATCH(Y13&"",'Chart of Accounts'!$A$5:$A$3000,0))&"|"&INDEX('Chart of Accounts'!$D$5:$D$3000,MATCH(Y13&"",'Chart of Accounts'!$A$5:$A$3000,0)),"") | AC13: =IFERROR(INDEX('Chart of Accounts'!$C$5:$C$3000,MATCH(W13&"",'Chart of Accounts'!$A$5:$A$3000,0))&"|"&INDEX('Chart of Accounts'!$D$5:$D$3000,MATCH(W13&"",'Chart of Accounts'!$A$5:$A$3000,0)),"") | AD13: =IFERROR(INDEX('Chart of Accounts'!$C$5:$C$3000,MATCH(X13&"",'Chart of Accounts'!$A$5:$A$3000,0))&"|"&INDEX('Chart of Accounts'!$D$5:$D$3000,MATCH(X13&"",'Chart of Accounts'!$A$5:$A$3000,0)),"") | AE13: =IFERROR(INDEX('Chart of Accounts'!$C$5:$C$3000,MATCH(Z13&"",'Chart of Accounts'!$A$5:$A$3000,0))&"|"&INDEX('Chart of Accounts'!$D$5:$D$3000,MATCH(Z13&"",'Chart of Accounts'!$A$5:$A$3000,0)),"") | AF13: =IF(LEFT(AA13,8)="Revenue|",-N(R13),0)+IF(LEFT(AB13,8)="Revenue|",-N(S13),0)+IF(LEFT(AC13,8)="Revenue|",N(L13),0)+IF(LEFT(AD13,8)="Revenue|",N(U13),0)+IF(LEFT(AE13,8)="Revenue|",N(T13),0) | AG13: =IF(LEFT(AA13,5)="COGS|",N(R13),0)+IF(LEFT(AB13,5)="COGS|",N(S13),0)+IF(LEFT(AC13,5)="COGS|",-N(L13),0)+IF(LEFT(AD13,5)="COGS|",-N(U13),0)+IF(LEFT(AE13,5)="COGS|",-N(T13),0) | AH13: =IF(LEFT(AA13,8)="Expense|",N(R13),0)+IF(LEFT(AB13,8)="Expense|",N(S13),0)+IF(LEFT(AC13,8)="Expense|",-N(L13),0)+IF(LEFT(AD13,8)="Expense|",-N(U13),0)+IF(LEFT(AE13,8)="Expense|",-N(T13),0) | AI13: =IF(ISNUMBER(MATCH(AA13,{"Expense|employee","Expense|general_admin","Expense|marketing","Expense|utilities","Expense|other_operating"},0)),N(R13),0)+IF(ISNUMBER(MATCH(AB13,{"Expense|employee","Expense|general_admin","Expense|marketing","Expense|utilities","Expense|other_operating"},0)),N(S13),0)+IF(ISNUMBER(MATCH(AC13,{"Expense|employee","Expense|general_admin","Expense|marketing","Expense|utilities","Expense|other_operating"},0)),-N(L13),0)+IF(ISNUMBER(MATCH(AD13,{"Expense|employee","Expense|general_admin","Expense|marketing","Expense|utilities","Expense|other_operating"},0)),-N(U13),0)+IF(ISNUMBER(MATCH(AE13,{"Expense|employee","Expense|general_admin","Expense|marketing","Expense|utilities","Expense|other_operating"},0)),-N(T13),0) | AJ13: =IF(AA13="Liability|payable",-N(R13),0)+IF(AB13="Liability|payable",-N(S13),0)+IF(AC13="Liability|payable",N(L13),0)+IF(AD13="Liability|payable",N(U13),0)+IF(AE13="Liability|payable",N(T13),0) | AK13: =IF(AA13="Liability|accrued",-N(R13),0)+IF(AB13="Liability|accrued",-N(S13),0)+IF(AC13="Liability|accrued",N(L13),0)+IF(AD13="Liability|accrued",N(U13),0)+IF(AE13="Liability|accrued",N(T13),0) | AL13: =IF(AND(N(R13)<>0,AA13=""),1,0)+IF(AND(N(S13)<>0,AB13=""),1,0)+IF(AND(N(L13)<>0,AC13=""),1,0)+IF(AND(N(U13)<>0,AD13=""),1,0)+IF(AND(N(T13)<>0,AE13=""),1,0)
R14: =ROUND(N(H14)*N(J14)-N(K14),2) | S14: =ROUND(R14*IFERROR(VLOOKUP(P14,'Tax Codes'!$A$5:$E$300,5,FALSE),0),2) | T14: =ROUND(R14*IFERROR(VLOOKUP(Q14,'Tax Codes'!$A$5:$E$300,5,FALSE),0),2) | U14: =R14+S14-T14-N(L14) | V14: =IF(C14="",INDEX('Chart of Accounts'!$A$5:$A$3000,MATCH("materials",'Chart of Accounts'!$F$5:$F$3000,0)),C14&"") | W14: =IF(N14="",INDEX('Chart of Accounts'!$A$5:$A$3000,MATCH("bank",'Chart of Accounts'!$F$5:$F$3000,0)),N14&"") | X14: =IF(O14="",INDEX('Chart of Accounts'!$A$5:$A$3000,MATCH("ap",'Chart of Accounts'!$F$5:$F$3000,0)),O14&"") | Y14: =INDEX('Chart of Accounts'!$A$5:$A$3000,MATCH("vat_input",'Chart of Accounts'!$F$5:$F$3000,0)) | Z14: =INDEX('Chart of Accounts'!$A$5:$A$3000,MATCH("wht_payable",'Chart of Accounts'!$F$5:$F$3000,0)) | AA14: =IFERROR(INDEX('Chart of Accounts'!$C$5:$C$3000,MATCH(V14&"",'Chart of Accounts'!$A$5:$A$3000,0))&"|"&INDEX('Chart of Accounts'!$D$5:$D$3000,MATCH(V14&"",'Chart of Accounts'!$A$5:$A$3000,0)),"") | AB14: =IFERROR(INDEX('Chart of Accounts'!$C$5:$C$3000,MATCH(Y14&"",'Chart of Accounts'!$A$5:$A$3000,0))&"|"&INDEX('Chart of Accounts'!$D$5:$D$3000,MATCH(Y14&"",'Chart of Accounts'!$A$5:$A$3000,0)),"") | AC14: =IFERROR(INDEX('Chart of Accounts'!$C$5:$C$3000,MATCH(W14&"",'Chart of Accounts'!$A$5:$A$3000,0))&"|"&INDEX('Chart of Accounts'!$D$5:$D$3000,MATCH(W14&"",'Chart of Accounts'!$A$5:$A$3000,0)),"") | AD14: =IFERROR(INDEX('Chart of Accounts'!$C$5:$C$3000,MATCH(X14&"",'Chart of Accounts'!$A$5:$A$3000,0))&"|"&INDEX('Chart of Accounts'!$D$5:$D$3000,MATCH(X14&"",'Chart of Accounts'!$A$5:$A$3000,0)),"") | AE14: =IFERROR(INDEX('Chart of Accounts'!$C$5:$C$3000,MATCH(Z14&"",'Chart of Accounts'!$A$5:$A$3000,0))&"|"&INDEX('Chart of Accounts'!$D$5:$D$3000,MATCH(Z14&"",'Chart of Accounts'!$A$5:$A$3000,0)),"") | AF14: =IF(LEFT(AA14,8)="Revenue|",-N(R14),0)+IF(LEFT(AB14,8)="Revenue|",-N(S14),0)+IF(LEFT(AC14,8)="Revenue|",N(L14),0)+IF(LEFT(AD14,8)="Revenue|",N(U14),0)+IF(LEFT(AE14,8)="Revenue|",N(T14),0) | AG14: =IF(LEFT(AA14,5)="COGS|",N(R14),0)+IF(LEFT(AB14,5)="COGS|",N(S14),0)+IF(LEFT(AC14,5)="COGS|",-N(L14),0)+IF(LEFT(AD14,5)="COGS|",-N(U14),0)+IF(LEFT(AE14,5)="COGS|",-N(T14),0) | AH14: =IF(LEFT(AA14,8)="Expense|",N(R14),0)+IF(LEFT(AB14,8)="Expense|",N(S14),0)+IF(LEFT(AC14,8)="Expense|",-N(L14),0)+IF(LEFT(AD14,8)="Expense|",-N(U14),0)+IF(LEFT(AE14,8)="Expense|",-N(T14),0) | AI14: =IF(ISNUMBER(MATCH(AA14,{"Expense|employee","Expense|general_admin","Expense|marketing","Expense|utilities","Expense|other_operating"},0)),N(R14),0)+IF(ISNUMBER(MATCH(AB14,{"Expense|employee","Expense|general_admin","Expense|marketing","Expense|utilities","Expense|other_operating"},0)),N(S14),0)+IF(ISNUMBER(MATCH(AC14,{"Expense|employee","Expense|general_admin","Expense|marketing","Expense|utilities","Expense|other_operating"},0)),-N(L14),0)+IF(ISNUMBER(MATCH(AD14,{"Expense|employee","Expense|general_admin","Expense|marketing","Expense|utilities","Expense|other_operating"},0)),-N(U14),0)+IF(ISNUMBER(MATCH(AE14,{"Expense|employee","Expense|general_admin","Expense|marketing","Expense|utilities","Expense|other_operating"},0)),-N(T14),0) | AJ14: =IF(AA14="Liability|payable",-N(R14),0)+IF(AB14="Liability|payable",-N(S14),0)+IF(AC14="Liability|payable",N(L14),0)+IF(AD14="Liability|payable",N(U14),0)+IF(AE14="Liability|payable",N(T14),0) | AK14: =IF(AA14="Liability|accrued",-N(R14),0)+IF(AB14="Liability|accrued",-N(S14),0)+IF(AC14="Liability|accrued",N(L14),0)+IF(AD14="Liability|accrued",N(U14),0)+IF(AE14="Liability|accrued",N(T14),0) | AL14: =IF(AND(N(R14)<>0,AA14=""),1,0)+IF(AND(N(S14)<>0,AB14=""),1,0)+IF(AND(N(L14)<>0,AC14=""),1,0)+IF(AND(N(U14)<>0,AD14=""),1,0)+IF(AND(N(T14)<>0,AE14=""),1,0)
R15: =ROUND(N(H15)*N(J15)-N(K15),2) | S15: =ROUND(R15*IFERROR(VLOOKUP(P15,'Tax Codes'!$A$5:$E$300,5,FALSE),0),2) | T15: =ROUND(R15*IFERROR(VLOOKUP(Q15,'Tax Codes'!$A$5:$E$300,5,FALSE),0),2) | U15: =R15+S15-T15-N(L15) | V15: =IF(C15="",INDEX('Chart of Accounts'!$A$5:$A$3000,MATCH("materials",'Chart of Accounts'!$F$5:$F$3000,0)),C15&"") | W15: =IF(N15="",INDEX('Chart of Accounts'!$A$5:$A$3000,MATCH("bank",'Chart of Accounts'!$F$5:$F$3000,0)),N15&"") | X15: =IF(O15="",INDEX('Chart of Accounts'!$A$5:$A$3000,MATCH("ap",'Chart of Accounts'!$F$5:$F$3000,0)),O15&"") | Y15: =INDEX('Chart of Accounts'!$A$5:$A$3000,MATCH("vat_input",'Chart of Accounts'!$F$5:$F$3000,0)) | Z15: =INDEX('Chart of Accounts'!$A$5:$A$3000,MATCH("wht_payable",'Chart of Accounts'!$F$5:$F$3000,0)) | AA15: =IFERROR(INDEX('Chart of Accounts'!$C$5:$C$3000,MATCH(V15&"",'Chart of Accounts'!$A$5:$A$3000,0))&"|"&INDEX('Chart of Accounts'!$D$5:$D$3000,MATCH(V15&"",'Chart of Accounts'!$A$5:$A$3000,0)),"") | AB15: =IFERROR(INDEX('Chart of Accounts'!$C$5:$C$3000,MATCH(Y15&"",'Chart of Accounts'!$A$5:$A$3000,0))&"|"&INDEX('Chart of Accounts'!$D$5:$D$3000,MATCH(Y15&"",'Chart of Accounts'!$A$5:$A$3000,0)),"") | AC15: =IFERROR(INDEX('Chart of Accounts'!$C$5:$C$3000,MATCH(W15&"",'Chart of Accounts'!$A$5:$A$3000,0))&"|"&INDEX('Chart of Accounts'!$D$5:$D$3000,MATCH(W15&"",'Chart of Accounts'!$A$5:$A$3000,0)),"") | AD15: =IFERROR(INDEX('Chart of Accounts'!$C$5:$C$3000,MATCH(X15&"",'Chart of Accounts'!$A$5:$A$3000,0))&"|"&INDEX('Chart of Accounts'!$D$5:$D$3000,MATCH(X15&"",'Chart of Accounts'!$A$5:$A$3000,0)),"") | AE15: =IFERROR(INDEX('Chart of Accounts'!$C$5:$C$3000,MATCH(Z15&"",'Chart of Accounts'!$A$5:$A$3000,0))&"|"&INDEX('Chart of Accounts'!$D$5:$D$3000,MATCH(Z15&"",'Chart of Accounts'!$A$5:$A$3000,0)),"") | AF15: =IF(LEFT(AA15,8)="Revenue|",-N(R15),0)+IF(LEFT(AB15,8)="Revenue|",-N(S15),0)+IF(LEFT(AC15,8)="Revenue|",N(L15),0)+IF(LEFT(AD15,8)="Revenue|",N(U15),0)+IF(LEFT(AE15,8)="Revenue|",N(T15),0) | AG15: =IF(LEFT(AA15,5)="COGS|",N(R15),0)+IF(LEFT(AB15,5)="COGS|",N(S15),0)+IF(LEFT(AC15,5)="COGS|",-N(L15),0)+IF(LEFT(AD15,5)="COGS|",-N(U15),0)+IF(LEFT(AE15,5)="COGS|",-N(T15),0) | AH15: =IF(LEFT(AA15,8)="Expense|",N(R15),0)+IF(LEFT(AB15,8)="Expense|",N(S15),0)+IF(LEFT(AC15,8)="Expense|",-N(L15),0)+IF(LEFT(AD15,8)="Expense|",-N(U15),0)+IF(LEFT(AE15,8)="Expense|",-N(T15),0) | AI15: =IF(ISNUMBER(MATCH(AA15,{"Expense|employee","Expense|general_admin","Expense|marketing","Expense|utilities","Expense|other_operating"},0)),N(R15),0)+IF(ISNUMBER(MATCH(AB15,{"Expense|employee","Expense|general_admin","Expense|marketing","Expense|utilities","Expense|other_operating"},0)),N(S15),0)+IF(ISNUMBER(MATCH(AC15,{"Expense|employee","Expense|general_admin","Expense|marketing","Expense|utilities","Expense|other_operating"},0)),-N(L15),0)+IF(ISNUMBER(MATCH(AD15,{"Expense|employee","Expense|general_admin","Expense|marketing","Expense|utilities","Expense|other_operating"},0)),-N(U15),0)+IF(ISNUMBER(MATCH(AE15,{"Expense|employee","Expense|general_admin","Expense|marketing","Expense|utilities","Expense|other_operating"},0)),-N(T15),0) | AJ15: =IF(AA15="Liability|payable",-N(R15),0)+IF(AB15="Liability|payable",-N(S15),0)+IF(AC15="Liability|payable",N(L15),0)+IF(AD15="Liability|payable",N(U15),0)+IF(AE15="Liability|payable",N(T15),0) | AK15: =IF(AA15="Liability|accrued",-N(R15),0)+IF(AB15="Liability|accrued",-N(S15),0)+IF(AC15="Liability|accrued",N(L15),0)+IF(AD15="Liability|accrued",N(U15),0)+IF(AE15="Liability|accrued",N(T15),0) | AL15: =IF(AND(N(R15)<>0,AA15=""),1,0)+IF(AND(N(S15)<>0,AB15=""),1,0)+IF(AND(N(L15)<>0,AC15=""),1,0)+IF(AND(N(U15)<>0,AD15=""),1,0)+IF(AND(N(T15)<>0,AE15=""),1,0)
R16: =ROUND(N(H16)*N(J16)-N(K16),2) | S16: =ROUND(R16*IFERROR(VLOOKUP(P16,'Tax Codes'!$A$5:$E$300,5,FALSE),0),2) | T16: =ROUND(R16*IFERROR(VLOOKUP(Q16,'Tax Codes'!$A$5:$E$300,5,FALSE),0),2) | U16: =R16+S16-T16-N(L16) | V16: =IF(C16="",INDEX('Chart of Accounts'!$A$5:$A$3000,MATCH("materials",'Chart of Accounts'!$F$5:$F$3000,0)),C16&"") | W16: =IF(N16="",INDEX('Chart of Accounts'!$A$5:$A$3000,MATCH("bank",'Chart of Accounts'!$F$5:$F$3000,0)),N16&"") | X16: =IF(O16="",INDEX('Chart of Accounts'!$A$5:$A$3000,MATCH("ap",'Chart of Accounts'!$F$5:$F$3000,0)),O16&"") | Y16: =INDEX('Chart of Accounts'!$A$5:$A$3000,MATCH("vat_input",'Chart of Accounts'!$F$5:$F$3000,0)) | Z16: =INDEX('Chart of Accounts'!$A$5:$A$3000,MATCH("wht_payable",'Chart of Accounts'!$F$5:$F$3000,0)) | AA16: =IFERROR(INDEX('Chart of Accounts'!$C$5:$C$3000,MATCH(V16&"",'Chart of Accounts'!$A$5:$A$3000,0))&"|"&INDEX('Chart of Accounts'!$D$5:$D$3000,MATCH(V16&"",'Chart of Accounts'!$A$5:$A$3000,0)),"") | AB16: =IFERROR(INDEX('Chart of Accounts'!$C$5:$C$3000,MATCH(Y16&"",'Chart of Accounts'!$A$5:$A$3000,0))&"|"&INDEX('Chart of Accounts'!$D$5:$D$3000,MATCH(Y16&"",'Chart of Accounts'!$A$5:$A$3000,0)),"") | AC16: =IFERROR(INDEX('Chart of Accounts'!$C$5:$C$3000,MATCH(W16&"",'Chart of Accounts'!$A$5:$A$3000,0))&"|"&INDEX('Chart of Accounts'!$D$5:$D$3000,MATCH(W16&"",'Chart of Accounts'!$A$5:$A$3000,0)),"") | AD16: =IFERROR(INDEX('Chart of Accounts'!$C$5:$C$3000,MATCH(X16&"",'Chart of Accounts'!$A$5:$A$3000,0))&"|"&INDEX('Chart of Accounts'!$D$5:$D$3000,MATCH(X16&"",'Chart of Accounts'!$A$5:$A$3000,0)),"") | AE16: =IFERROR(INDEX('Chart of Accounts'!$C$5:$C$3000,MATCH(Z16&"",'Chart of Accounts'!$A$5:$A$3000,0))&"|"&INDEX('Chart of Accounts'!$D$5:$D$3000,MATCH(Z16&"",'Chart of Accounts'!$A$5:$A$3000,0)),"") | AF16: =IF(LEFT(AA16,8)="Revenue|",-N(R16),0)+IF(LEFT(AB16,8)="Revenue|",-N(S16),0)+IF(LEFT(AC16,8)="Revenue|",N(L16),0)+IF(LEFT(AD16,8)="Revenue|",N(U16),0)+IF(LEFT(AE16,8)="Revenue|",N(T16),0) | AG16: =IF(LEFT(AA16,5)="COGS|",N(R16),0)+IF(LEFT(AB16,5)="COGS|",N(S16),0)+IF(LEFT(AC16,5)="COGS|",-N(L16),0)+IF(LEFT(AD16,5)="COGS|",-N(U16),0)+IF(LEFT(AE16,5)="COGS|",-N(T16),0) | AH16: =IF(LEFT(AA16,8)="Expense|",N(R16),0)+IF(LEFT(AB16,8)="Expense|",N(S16),0)+IF(LEFT(AC16,8)="Expense|",-N(L16),0)+IF(LEFT(AD16,8)="Expense|",-N(U16),0)+IF(LEFT(AE16,8)="Expense|",-N(T16),0) | AI16: =IF(ISNUMBER(MATCH(AA16,{"Expense|employee","Expense|general_admin","Expense|marketing","Expense|utilities","Expense|other_operating"},0)),N(R16),0)+IF(ISNUMBER(MATCH(AB16,{"Expense|employee","Expense|general_admin","Expense|marketing","Expense|utilities","Expense|other_operating"},0)),N(S16),0)+IF(ISNUMBER(MATCH(AC16,{"Expense|employee","Expense|general_admin","Expense|marketing","Expense|utilities","Expense|other_operating"},0)),-N(L16),0)+IF(ISNUMBER(MATCH(AD16,{"Expense|employee","Expense|general_admin","Expense|marketing","Expense|utilities","Expense|other_operating"},0)),-N(U16),0)+IF(ISNUMBER(MATCH(AE16,{"Expense|employee","Expense|general_admin","Expense|marketing","Expense|utilities","Expense|other_operating"},0)),-N(T16),0) | AJ16: =IF(AA16="Liability|payable",-N(R16),0)+IF(AB16="Liability|payable",-N(S16),0)+IF(AC16="Liability|payable",N(L16),0)+IF(AD16="Liability|payable",N(U16),0)+IF(AE16="Liability|payable",N(T16),0) | AK16: =IF(AA16="Liability|accrued",-N(R16),0)+IF(AB16="Liability|accrued",-N(S16),0)+IF(AC16="Liability|accrued",N(L16),0)+IF(AD16="Liability|accrued",N(U16),0)+IF(AE16="Liability|accrued",N(T16),0) | AL16: =IF(AND(N(R16)<>0,AA16=""),1,0)+IF(AND(N(S16)<>0,AB16=""),1,0)+IF(AND(N(L16)<>0,AC16=""),1,0)+IF(AND(N(U16)<>0,AD16=""),1,0)+IF(AND(N(T16)<>0,AE16=""),1,0)
... R204: =ROUND(N(H204)*N(J204)-N(K204),2) | S204: =ROUND(R204*IFERROR(VLOOKUP(P204,'Tax Codes'!$A$5:$E$300,5,FALSE),0),2) | T204: =ROUND(R204*IFERROR(VLOOKUP(Q204,'Tax Codes'!$A$5:$E$300,5,FALSE),0),2) | U204: =R204+S204-T204-N(L204) | V204: =IF(C204="",INDEX('Chart of Accounts'!$A$5:$A$3000,MATCH("materials",'Chart of Accounts'!$F$5:$F$3000,0)),C204&"") | W204: =IF(N204="",INDEX('Chart of Accounts'!$A$5:$A$3000,MATCH("bank",'Chart of Accounts'!$F$5:$F$3000,0)),N204&"") | X204: =IF(O204="",INDEX('Chart of Accounts'!$A$5:$A$3000,MATCH("ap",'Chart of Accounts'!$F$5:$F$3000,0)),O204&"") | Y204: =INDEX('Chart of Accounts'!$A$5:$A$3000,MATCH("vat_input",'Chart of Accounts'!$F$5:$F$3000,0)) | Z204: =INDEX('Chart of Accounts'!$A$5:$A$3000,MATCH("wht_payable",'Chart of Accounts'!$F$5:$F$3000,0)) | AA204: =IFERROR(INDEX('Chart of Accounts'!$C$5:$C$3000,MATCH(V204&"",'Chart of Accounts'!$A$5:$A$3000,0))&"|"&INDEX('Chart of Accounts'!$D$5:$D$3000,MATCH(V204&"",'Chart of Accounts'!$A$5:$A$3000,0)),"") | AB204: =IFERROR(INDEX('Chart of Accounts'!$C$5:$C$3000,MATCH(Y204&"",'Chart of Accounts'!$A$5:$A$3000,0))&"|"&INDEX('Chart of Accounts'!$D$5:$D$3000,MATCH(Y204&"",'Chart of Accounts'!$A$5:$A$3000,0)),"") | AC204: =IFERROR(INDEX('Chart of Accounts'!$C$5:$C$3000,MATCH(W204&"",'Chart of Accounts'!$A$5:$A$3000,0))&"|"&INDEX('Chart of Accounts'!$D$5:$D$3000,MATCH(W204&"",'Chart of Accounts'!$A$5:$A$3000,0)),"") | AD204: =IFERROR(INDEX('Chart of Accounts'!$C$5:$C$3000,MATCH(X204&"",'Chart of Accounts'!$A$5:$A$3000,0))&"|"&INDEX('Chart of Accounts'!$D$5:$D$3000,MATCH(X204&"",'Chart of Accounts'!$A$5:$A$3000,0)),"") | AE204: =IFERROR(INDEX('Chart of Accounts'!$C$5:$C$3000,MATCH(Z204&"",'Chart of Accounts'!$A$5:$A$3000,0))&"|"&INDEX('Chart of Accounts'!$D$5:$D$3000,MATCH(Z204&"",'Chart of Accounts'!$A$5:$A$3000,0)),"") | AF204: =IF(LEFT(AA204,8)="Revenue|",-N(R204),0)+IF(LEFT(AB204,8)="Revenue|",-N(S204),0)+IF(LEFT(AC204,8)="Revenue|",N(L204),0)+IF(LEFT(AD204,8)="Revenue|",N(U204),0)+IF(LEFT(AE204,8)="Revenue|",N(T204),0) | AG204: =IF(LEFT(AA204,5)="COGS|",N(R204),0)+IF(LEFT(AB204,5)="COGS|",N(S204),0)+IF(LEFT(AC204,5)="COGS|",-N(L204),0)+IF(LEFT(AD204,5)="COGS|",-N(U204),0)+IF(LEFT(AE204,5)="COGS|",-N(T204),0) | AH204: =IF(LEFT(AA204,8)="Expense|",N(R204),0)+IF(LEFT(AB204,8)="Expense|",N(S204),0)+IF(LEFT(AC204,8)="Expense|",-N(L204),0)+IF(LEFT(AD204,8)="Expense|",-N(U204),0)+IF(LEFT(AE204,8)="Expense|",-N(T204),0) | AI204: =IF(ISNUMBER(MATCH(AA204,{"Expense|employee","Expense|general_admin","Expense|marketing","Expense|utilities","Expense|other_operating"},0)),N(R204),0)+IF(ISNUMBER(MATCH(AB204,{"Expense|employee","Expense|general_admin","Expense|marketing","Expense|utilities","Expense|other_operating"},0)),N(S204),0)+IF(ISNUMBER(MATCH(AC204,{"Expense|employee","Expense|general_admin","Expense|marketing","Expense|utilities","Expense|other_operating"},0)),-N(L204),0)+IF(ISNUMBER(MATCH(AD204,{"Expense|employee","Expense|general_admin","Expense|marketing","Expense|utilities","Expense|other_operating"},0)),-N(U204),0)+IF(ISNUMBER(MATCH(AE204,{"Expense|employee","Expense|general_admin","Expense|marketing","Expense|utilities","Expense|other_operating"},0)),-N(T204),0) | AJ204: =IF(AA204="Liability|payable",-N(R204),0)+IF(AB204="Liability|payable",-N(S204),0)+IF(AC204="Liability|payable",N(L204),0)+IF(AD204="Liability|payable",N(U204),0)+IF(AE204="Liability|payable",N(T204),0) | AK204: =IF(AA204="Liability|accrued",-N(R204),0)+IF(AB204="Liability|accrued",-N(S204),0)+IF(AC204="Liability|accrued",N(L204),0)+IF(AD204="Liability|accrued",N(U204),0)+IF(AE204="Liability|accrued",N(T204),0) | AL204: =IF(AND(N(R204)<>0,AA204=""),1,0)+IF(AND(N(S204)<>0,AB204=""),1,0)+IF(AND(N(L204)<>0,AC204=""),1,0)+IF(AND(N(U204)<>0,AD204=""),1,0)+IF(AND(N(T204)<>0,AE204=""),1,0)

Sheet Operating Expenses
A1: BEYOND DESIGN | OPERATING EXPENSES
A2: Operating expenses. Leave Business Unit blank for shared overhead (allocated by Overhead %). Paid Now blank = paid in full
A3: e.g. 2026-10-01 | C3: 6010 | D3: Office rent — Oct | E3: Landlord | F3: 15000 | H3: Bank Transfer
A4: Date | B4: Business Unit | C4: Expense Account | D4: Description | E4: Supplier | F4: Amount | G4: Paid Now | H4: Payment Method | I4: Paid From | J4: Payable Account | K4: VAT Code | L4: WHT Code | M4: Input VAT | N4: WHT Withheld | O4: Paid (effective) | P4: Unpaid | Q4: account (effective) | R4: paid_from (effective) | S4: payable_account (effective) | T4: vat_input account | U4: wht_payable account | V4: leg 1 type | W4: leg 2 type | X4: leg 3 type | Y4: leg 4 type | Z4: leg 5 type | AA4: revenue | AB4: cost of sales | AC4: expenses | AD4: operating expenses | AE4: payables | AF4: accruals | AG4: unknown account
M5: =ROUND(N(F5)*IFERROR(VLOOKUP(K5,'Tax Codes'!$A$5:$E$300,5,FALSE),0),2) | N5: =ROUND(N(F5)*IFERROR(VLOOKUP(L5,'Tax Codes'!$A$5:$E$300,5,FALSE),0),2) | O5: =IF(G5="",N(F5)+M5-N5,N(G5)) | P5: =N(F5)+M5-N5-O5 | Q5: =IF(C5="",INDEX('Chart of Accounts'!$A$5:$A$3000,MATCH("other_overhead",'Chart of Accounts'!$F$5:$F$3000,0)),C5&"") | R5: =IF(I5="",INDEX('Chart of Accounts'!$A$5:$A$3000,MATCH("bank",'Chart of Accounts'!$F$5:$F$3000,0)),I5&"") | S5: =IF(J5="",INDEX('Chart of Accounts'!$A$5:$A$3000,MATCH("ap",'Chart of Accounts'!$F$5:$F$3000,0)),J5&"") | T5: =INDEX('Chart of Accounts'!$A$5:$A$3000,MATCH("vat_input",'Chart of Accounts'!$F$5:$F$3000,0)) | U5: =INDEX('Chart of Accounts'!$A$5:$A$3000,MATCH("wht_payable",'Chart of Accounts'!$F$5:$F$3000,0)) | V5: =IFERROR(INDEX('Chart of Accounts'!$C$5:$C$3000,MATCH(Q5&"",'Chart of Accounts'!$A$5:$A$3000,0))&"|"&INDEX('Chart of Accounts'!$D$5:$D$3000,MATCH(Q5&"",'Chart of Accounts'!$A$5:$A$3000,0)),"") | W5: =IFERROR(INDEX('Chart of Accounts'!$C$5:$C$3000,MATCH(T5&"",'Chart of Accounts'!$A$5:$A$3000,0))&"|"&INDEX('Chart of Accounts'!$D$5:$D$3000,MATCH(T5&"",'Chart of Accounts'!$A$5:$A$3000,0)),"") | X5: =IFERROR(INDEX('Chart of Accounts'!$C$5:$C$3000,MATCH(R5&"",'Chart of Accounts'!$A$5:$A$3000,0))&"|"&INDEX('Chart of Accounts'!$D$5:$D$3000,MATCH(R5&"",'Chart of Accounts'!$A$5:$A$3000,0)),"") | Y5: =IFERROR(INDEX('Chart of Accounts'!$C$5:$C$3000,MATCH(S5&"",'Chart of Accounts'!$A$5:$A$3000,0))&"|"&INDEX('Chart of Accounts'!$D$5:$D$3000,MATCH(S5&"",'Chart of Accounts'!$A$5:$A$3000,0)),"") | Z5: =IFERROR(INDEX('Chart of Accounts'!$C$5:$C$3000,MATCH(U5&"",'Chart of Accounts'!$A$5:$A$3000,0))&"|"&INDEX('Chart of Accounts'!$D$5:$D$3000,MATCH(U5&"",'Chart of Accounts'!$A$5:$A$3000,0)),"") | AA5: =IF(LEFT(V5,8)="Revenue|",-N(F5),0)+IF(LEFT(W5,8)="Revenue|",-N(M5),0)+IF(LEFT(X5,8)="Revenue|",N(O5),0)+IF(LEFT(Y5,8)="Revenue|",N(P5),0)+IF(LEFT(Z5,8)="Revenue|",N(N5),0) | AB5: =IF(LEFT(V5,5)="COGS|",N(F5),0)+IF(LEFT(W5,5)="COGS|",N(M5),0)+IF(LEFT(X5,5)="COGS|",-N(O5),0)+IF(LEFT(Y5,5)="COGS|",-N(P5),0)+IF(LEFT(Z5,5)="COGS|",-N(N5),0) | AC5: =IF(LEFT(V5,8)="Expense|",N(F5),0)+IF(LEFT(W5,8)="Expense|",N(M5),0)+IF(LEFT(X5,8)="Expense|",-N(O5),0)+IF(LEFT(Y5,8)="Expense|",-N(P5),0)+IF(LEFT(Z5,8)="Expense|",-N(N5),0) | AD5: =IF(ISNUMBER(MATCH(V5,{"Expense|employee","Expense|general_admin","Expense|marketing","Expense|utilities","Expense|other_operating"},0)),N(F5),0)+IF(ISNUMBER(MATCH(W5,{"Expense|employee","Expense|general_admin","Expense|marketing","Expense|utilities","Expense|other_operating"},0)),N(M5),0)+IF(ISNUMBER(MATCH(X5,{"Expense|employee","Expense|general_admin","Expense|marketing","Expense|utilities","Expense|other_operating"},0)),-N(O5),0)+IF(ISNUMBER(MATCH(Y5,{"Expense|employee","Expense|general_admin","Expense|marketing","Expense|utilities","Expense|other_operating"},0)),-N(P5),0)+IF(ISNUMBER(MATCH(Z5,{"Expense|employee","Expense|general_admin","Expense|marketing","Expense|utilities","Expense|other_operating"},0)),-N(N5),0) | AE5: =IF(V5="Liability|payable",-N(F5),0)+IF(W5="Liability|payable",-N(M5),0)+IF(X5="Liability|payable",N(O5),0)+IF(Y5="Liability|payable",N(P5),0)+IF(Z5="Liability|payable",N(N5),0) | AF5: =IF(V5="Liability|accrued",-N(F5),0)+IF(W5="Liability|accrued",-N(M5),0)+IF(X5="Liability|accrued",N(O5),0)+IF(Y5="Liability|accrued",N(P5),0)+IF(Z5="Liability|accrued",N(N5),0) | AG5: =IF(AND(N(F5)<>0,V5=""),1,0)+IF(AND(N(M5)<>0,W5=""),1,0)+IF(AND(N(O5)<>0,X5=""),1,0)+IF(AND(N(P5)<>0,Y5=""),1,0)+IF(AND(N(N5)<>0,Z5=""),1,0)
M6: =ROUND(N(F6)*IFERROR(VLOOKUP(K6,'Tax Codes'!$A$5:$E$300,5,FALSE),0),2) | N6: =ROUND(N(F6)*IFERROR(VLOOKUP(L6,'Tax Codes'!$A$5:$E$300,5,FALSE),0),2) | O6: =IF(G6="",N(F6)+M6-N6,N(G6)) | P6: =N(F6)+M6-N6-O6 | Q6: =IF(C6="",INDEX('Chart of Accounts'!$A$5:$A$3000,MATCH("other_overhead",'Chart of Accounts'!$F$5:$F$3000,0)),C6&"") | R6: =IF(I6="",INDEX('Chart of Accounts'!$A$5:$A$3000,MATCH("bank",'Chart of Accounts'!$F$5:$F$3000,0)),I6&"") | S6: =IF(J6="",INDEX('Chart of Accounts'!$A$5:$A$3000,MATCH("ap",'Chart of Accounts'!$F$5:$F$3000,0)),J6&"") | T6: =INDEX('Chart of Accounts'!$A$5:$A$3000,MATCH("vat_input",'Chart of Accounts'!$F$5:$F$3000,0)) | U6: =INDEX('Chart of Accounts'!$A$5:$A$3000,MATCH("wht_payable",'Chart of Accounts'!$F$5:$F$3000,0)) | V6: =IFERROR(INDEX('Chart of Accounts'!$C$5:$C$3000,MATCH(Q6&"",'Chart of Accounts'!$A$5:$A$3000,0))&"|"&INDEX('Chart of Accounts'!$D$5:$D$3000,MATCH(Q6&"",'Chart of Accounts'!$A$5:$A$3000,0)),"") | W6: =IFERROR(INDEX('Chart of Accounts'!$C$5:$C$3000,MATCH(T6&"",'Chart of Accounts'!$A$5:$A$3000,0))&"|"&INDEX('Chart of Accounts'!$D$5:$D$3000,MATCH(T6&"",'Chart of Accounts'!$A$5:$A$3000,0)),"") | X6: =IFERROR(INDEX('Chart of Accounts'!$C$5:$C$3000,MATCH(R6&"",'Chart of Accounts'!$A$5:$A$3000,0))&"|"&INDEX('Chart of Accounts'!$D$5:$D$3000,MATCH(R6&"",'Chart of Accounts'!$A$5:$A$3000,0)),"") | Y6: =IFERROR(INDEX('Chart of Accounts'!$C$5:$C$3000,MATCH(S6&"",'Chart of Accounts'!$A$5:$A$3000,0))&"|"&INDEX('Chart of Accounts'!$D$5:$D$3000,MATCH(S6&"",'Chart of Accounts'!$A$5:$A$3000,0)),"") | Z6: =IFERROR(INDEX('Chart of Accounts'!$C$5:$C$3000,MATCH(U6&"",'Chart of Accounts'!$A$5:$A$3000,0))&"|"&INDEX('Chart of Accounts'!$D$5:$D$3000,MATCH(U6&"",'Chart of Accounts'!$A$5:$A$3000,0)),"") | AA6: =IF(LEFT(V6,8)="Revenue|",-N(F6),0)+IF(LEFT(W6,8)="Revenue|",-N(M6),0)+IF(LEFT(X6,8)="Revenue|",N(O6),0)+IF(LEFT(Y6,8)="Revenue|",N(P6),0)+IF(LEFT(Z6,8)="Revenue|",N(N6),0) | AB6: =IF(LEFT(V6,5)="COGS|",N(F6),0)+IF(LEFT(W6,5)="COGS|",N(M6),0)+IF(LEFT(X6,5)="COGS|",-N(O6),0)+IF(LEFT(Y6,5)="COGS|",-N(P6),0)+IF(LEFT(Z6,5)="COGS|",-N(N6),0) | AC6: =IF(LEFT(V6,8)="Expense|",N(F6),0)+IF(LEFT(W6,8)="Expense|",N(M6),0)+IF(LEFT(X6,8)="Expense|",-N(O6),0)+IF(LEFT(Y6,8)="Expense|",-N(P6),0)+IF(LEFT(Z6,8)="Expense|",-N(N6),0) | AD6: =IF(ISNUMBER(MATCH(V6,{"Expense|employee","Expense|general_admin","Expense|marketing","Expense|utilities","Expense|other_operating"},0)),N(F6),0)+IF(ISNUMBER(MATCH(W6,{"Expense|employee","Expense|general_admin","Expense|marketing","Expense|utilities","Expense|other_operating"},0)),N(M6),0)+IF(ISNUMBER(MATCH(X6,{"Expense|employee","Expense|general_admin","Expense|marketing","Expense|utilities","Expense|other_operating"},0)),-N(O6),0)+IF(ISNUMBER(MATCH(Y6,{"Expense|employee","Expense|general_admin","Expense|marketing","Expense|utilities","Expense|other_operating"},0)),-N(P6),0)+IF(ISNUMBER(MATCH(Z6,{"Expense|employee","Expense|general_admin","Expense|marketing","Expense|utilities","Expense|other_operating"},0)),-N(N6),0) | AE6: =IF(V6="Liability|payable",-N(F6),0)+IF(W6="Liability|payable",-N(M6),0)+IF(X6="Liability|payable",N(O6),0)+IF(Y6="Liability|payable",N(P6),0)+IF(Z6="Liability|payable",N(N6),0) | AF6: =IF(V6="Liability|accrued",-N(F6),0)+IF(W6="Liability|accrued",-N(M6),0)+IF(X6="Liability|accrued",N(O6),0)+IF(Y6="Liability|accrued",N(P6),0)+IF(Z6="Liability|accrued",N(N6),0) | AG6: =IF(AND(N(F6)<>0,V6=""),1,0)+IF(AND(N(M6)<>0,W6=""),1,0)+IF(AND(N(O6)<>0,X6=""),1,0)+IF(AND(N(P6)<>0,Y6=""),1,0)+IF(AND(N(N6)<>0,Z6=""),1,0)
M7: =ROUND(N(F7)*IFERROR(VLOOKUP(K7,'Tax Codes'!$A$5:$E$300,5,FALSE),0),2) | N7: =ROUND(N(F7)*IFERROR(VLOOKUP(L7,'Tax Codes'!$A$5:$E$300,5,FALSE),0),2) | O7: =IF(G7="",N(F7)+M7-N7,N(G7)) | P7: =N(F7)+M7-N7-O7 | Q7: =IF(C7="",INDEX('Chart of Accounts'!$A$5:$A$3000,MATCH("other_overhead",'Chart of Accounts'!$F$5:$F$3000,0)),C7&"") | R7: =IF(I7="",INDEX('Chart of Accounts'!$A$5:$A$3000,MATCH("bank",'Chart of Accounts'!$F$5:$F$3000,0)),I7&"") | S7: =IF(J7="",INDEX('Chart of Accounts'!$A$5:$A$3000,MATCH("ap",'Chart of Accounts'!$F$5:$F$3000,0)),J7&"") | T7: =INDEX('Chart of Accounts'!$A$5:$A$3000,MATCH("vat_input",'Chart of Accounts'!$F$5:$F$3000,0)) | U7: =INDEX('Chart of Accounts'!$A$5:$A$3000,MATCH("wht_payable",'Chart of Accounts'!$F$5:$F$3000,0)) | V7: =IFERROR(INDEX('Chart of Accounts'!$C$5:$C$3000,MATCH(Q7&"",'Chart of Accounts'!$A$5:$A$3000,0))&"|"&INDEX('Chart of Accounts'!$D$5:$D$3000,MATCH(Q7&"",'Chart of Accounts'!$A$5:$A$3000,0)),"") | W7: =IFERROR(INDEX('Chart of Accounts'!$C$5:$C$3000,MATCH(T7&"",'Chart of Accounts'!$A$5:$A$3000,0))&"|"&INDEX('Chart of Accounts'!$D$5:$D$3000,MATCH(T7&"",'Chart of Accounts'!$A$5:$A$3000,0)),"") | X7: =IFERROR(INDEX('Chart of Accounts'!$C$5:$C$3000,MATCH(R7&"",'Chart of Accounts'!$A$5:$A$3000,0))&"|"&INDEX('Chart of Accounts'!$D$5:$D$3000,MATCH(R7&"",'Chart of Accounts'!$A$5:$A$3000,0)),"") | Y7: =IFERROR(INDEX('Chart of Accounts'!$C$5:$C$3000,MATCH(S7&"",'Chart of Accounts'!$A$5:$A$3000,0))&"|"&INDEX('Chart of Accounts'!$D$5:$D$3000,MATCH(S7&"",'Chart of Accounts'!$A$5:$A$3000,0)),"") | Z7: =IFERROR(INDEX('Chart of Accounts'!$C$5:$C$3000,MATCH(U7&"",'Chart of Accounts'!$A$5:$A$3000,0))&"|"&INDEX('Chart of Accounts'!$D$5:$D$3000,MATCH(U7&"",'Chart of Accounts'!$A$5:$A$3000,0)),"") | AA7: =IF(LEFT(V7,8)="Revenue|",-N(F7),0)+IF(LEFT(W7,8)="Revenue|",-N(M7),0)+IF(LEFT(X7,8)="Revenue|",N(O7),0)+IF(LEFT(Y7,8)="Revenue|",N(P7),0)+IF(LEFT(Z7,8)="Revenue|",N(N7),0) | AB7: =IF(LEFT(V7,5)="COGS|",N(F7),0)+IF(LEFT(W7,5)="COGS|",N(M7),0)+IF(LEFT(X7,5)="COGS|",-N(O7),0)+IF(LEFT(Y7,5)="COGS|",-N(P7),0)+IF(LEFT(Z7,5)="COGS|",-N(N7),0) | AC7: =IF(LEFT(V7,8)="Expense|",N(F7),0)+IF(LEFT(W7,8)="Expense|",N(M7),0)+IF(LEFT(X7,8)="Expense|",-N(O7),0)+IF(LEFT(Y7,8)="Expense|",-N(P7),0)+IF(LEFT(Z7,8)="Expense|",-N(N7),0) | AD7: =IF(ISNUMBER(MATCH(V7,{"Expense|employee","Expense|general_admin","Expense|marketing","Expense|utilities","Expense|other_operating"},0)),N(F7),0)+IF(ISNUMBER(MATCH(W7,{"Expense|employee","Expense|general_admin","Expense|marketing","Expense|utilities","Expense|other_operating"},0)),N(M7),0)+IF(ISNUMBER(MATCH(X7,{"Expense|employee","Expense|general_admin","Expense|marketing","Expense|utilities","Expense|other_operating"},0)),-N(O7),0)+IF(ISNUMBER(MATCH(Y7,{"Expense|employee","Expense|general_admin","Expense|marketing","Expense|utilities","Expense|other_operating"},0)),-N(P7),0)+IF(ISNUMBER(MATCH(Z7,{"Expense|employee","Expense|general_admin","Expense|marketing","Expense|utilities","Expense|other_operating"},0)),-N(N7),0) | AE7: =IF(V7="Liability|payable",-N(F7),0)+IF(W7="Liability|payable",-N(M7),0)+IF(X7="Liability|payable",N(O7),0)+IF(Y7="Liability|payable",N(P7),0)+IF(Z7="Liability|payable",N(N7),0) | AF7: =IF(V7="Liability|accrued",-N(F7),0)+IF(W7="Liability|accrued",-N(M7),0)+IF(X7="Liability|accrued",N(O7),0)+IF(Y7="Liability|accrued",N(P7),0)+IF(Z7="Liability|accrued",N(N7),0) | AG7: =IF(AND(N(F7)<>0,V7=""),1,0)+IF(AND(N(M7)<>0,W7=""),1,0)+IF(AND(N(O7)<>0,X7=""),1,0)+IF(AND(N(P7)<>0,Y7=""),1,0)+IF(AND(N(N7)<>0,Z7=""),1,0)
M8: =ROUND(N(F8)*IFERROR(VLOOKUP(K8,'Tax Codes'!$A$5:$E$300,5,FALSE),0),2) | N8: =ROUND(N(F8)*IFERROR(VLOOKUP(L8,'Tax Codes'!$A$5:$E$300,5,FALSE),0),2) | O8: =IF(G8="",N(F8)+M8-N8,N(G8)) | P8: =N(F8)+M8-N8-O8 | Q8: =IF(C8="",INDEX('Chart of Accounts'!$A$5:$A$3000,MATCH("other_overhead",'Chart of Accounts'!$F$5:$F$3000,0)),C8&"") | R8: =IF(I8="",INDEX('Chart of Accounts'!$A$5:$A$3000,MATCH("bank",'Chart of Accounts'!$F$5:$F$3000,0)),I8&"") | S8: =IF(J8="",INDEX('Chart of Accounts'!$A$5:$A$3000,MATCH("ap",'Chart of Accounts'!$F$5:$F$3000,0)),J8&"") | T8: =INDEX('Chart of Accounts'!$A$5:$A$3000,MATCH("vat_input",'Chart of Accounts'!$F$5:$F$3000,0)) | U8: =INDEX('Chart of Accounts'!$A$5:$A$3000,MATCH("wht_payable",'Chart of Accounts'!$F$5:$F$3000,0)) | V8: =IFERROR(INDEX('Chart of Accounts'!$C$5:$C$3000,MATCH(Q8&"",'Chart of Accounts'!$A$5:$A$3000,0))&"|"&INDEX('Chart of Accounts'!$D$5:$D$3000,MATCH(Q8&"",'Chart of Accounts'!$A$5:$A$3000,0)),"") | W8: =IFERROR(INDEX('Chart of Accounts'!$C$5:$C$3000,MATCH(T8&"",'Chart of Accounts'!$A$5:$A$3000,0))&"|"&INDEX('Chart of Accounts'!$D$5:$D$3000,MATCH(T8&"",'Chart of Accounts'!$A$5:$A$3000,0)),"") | X8: =IFERROR(INDEX('Chart of Accounts'!$C$5:$C$3000,MATCH(R8&"",'Chart of Accounts'!$A$5:$A$3000,0))&"|"&INDEX('Chart of Accounts'!$D$5:$D$3000,MATCH(R8&"",'Chart of Accounts'!$A$5:$A$3000,0)),"") | Y8: =IFERROR(INDEX('Chart of Accounts'!$C$5:$C$3000,MATCH(S8&"",'Chart of Accounts'!$A$5:$A$3000,0))&"|"&INDEX('Chart of Accounts'!$D$5:$D$3000,MATCH(S8&"",'Chart of Accounts'!$A$5:$A$3000,0)),"") | Z8: =IFERROR(INDEX('Chart of Accounts'!$C$5:$C$3000,MATCH(U8&"",'Chart of Accounts'!$A$5:$A$3000,0))&"|"&INDEX('Chart of Accounts'!$D$5:$D$3000,MATCH(U8&"",'Chart of Accounts'!$A$5:$A$3000,0)),"") | AA8: =IF(LEFT(V8,8)="Revenue|",-N(F8),0)+IF(LEFT(W8,8)="Revenue|",-N(M8),0)+IF(LEFT(X8,8)="Revenue|",N(O8),0)+IF(LEFT(Y8,8)="Revenue|",N(P8),0)+IF(LEFT(Z8,8)="Revenue|",N(N8),0) | AB8: =IF(LEFT(V8,5)="COGS|",N(F8),0)+IF(LEFT(W8,5)="COGS|",N(M8),0)+IF(LEFT(X8,5)="COGS|",-N(O8),0)+IF(LEFT(Y8,5)="COGS|",-N(P8),0)+IF(LEFT(Z8,5)="COGS|",-N(N8),0) | AC8: =IF(LEFT(V8,8)="Expense|",N(F8),0)+IF(LEFT(W8,8)="Expense|",N(M8),0)+IF(LEFT(X8,8)="Expense|",-N(O8),0)+IF(LEFT(Y8,8)="Expense|",-N(P8),0)+IF(LEFT(Z8,8)="Expense|",-N(N8),0) | AD8: =IF(ISNUMBER(MATCH(V8,{"Expense|employee","Expense|general_admin","Expense|marketing","Expense|utilities","Expense|other_operating"},0)),N(F8),0)+IF(ISNUMBER(MATCH(W8,{"Expense|employee","Expense|general_admin","Expense|marketing","Expense|utilities","Expense|other_operating"},0)),N(M8),0)+IF(ISNUMBER(MATCH(X8,{"Expense|employee","Expense|general_admin","Expense|marketing","Expense|utilities","Expense|other_operating"},0)),-N(O8),0)+IF(ISNUMBER(MATCH(Y8,{"Expense|employee","Expense|general_admin","Expense|marketing","Expense|utilities","Expense|other_operating"},0)),-N(P8),0)+IF(ISNUMBER(MATCH(Z8,{"Expense|employee","Expense|general_admin","Expense|marketing","Expense|utilities","Expense|other_operating"},0)),-N(N8),0) | AE8: =IF(V8="Liability|payable",-N(F8),0)+IF(W8="Liability|payable",-N(M8),0)+IF(X8="Liability|payable",N(O8),0)+IF(Y8="Liability|payable",N(P8),0)+IF(Z8="Liability|payable",N(N8),0) | AF8: =IF(V8="Liability|accrued",-N(F8),0)+IF(W8="Liability|accrued",-N(M8),0)+IF(X8="Liability|accrued",N(O8),0)+IF(Y8="Liability|accrued",N(P8),0)+IF(Z8="Liability|accrued",N(N8),0) | AG8: =IF(AND(N(F8)<>0,V8=""),1,0)+IF(AND(N(M8)<>0,W8=""),1,0)+IF(AND(N(O8)<>0,X8=""),1,0)+IF(AND(N(P8)<>0,Y8=""),1,0)+IF(AND(N(N8)<>0,Z8=""),1,0)
M9: =ROUND(N(F9)*IFERROR(VLOOKUP(K9,'Tax Codes'!$A$5:$E$300,5,FALSE),0),2) | N9: =ROUND(N(F9)*IFERROR(VLOOKUP(L9,'Tax Codes'!$A$5:$E$300,5,FALSE),0),2) | O9: =IF(G9="",N(F9)+M9-N9,N(G9)) | P9: =N(F9)+M9-N9-O9 | Q9: =IF(C9="",INDEX('Chart of Accounts'!$A$5:$A$3000,MATCH("other_overhead",'Chart of Accounts'!$F$5:$F$3000,0)),C9&"") | R9: =IF(I9="",INDEX('Chart of Accounts'!$A$5:$A$3000,MATCH("bank",'Chart of Accounts'!$F$5:$F$3000,0)),I9&"") | S9: =IF(J9="",INDEX('Chart of Accounts'!$A$5:$A$3000,MATCH("ap",'Chart of Accounts'!$F$5:$F$3000,0)),J9&"") | T9: =INDEX('Chart of Accounts'!$A$5:$A$3000,MATCH("vat_input",'Chart of Accounts'!$F$5:$F$3000,0)) | U9: =INDEX('Chart of Accounts'!$A$5:$A$3000,MATCH("wht_payable",'Chart of Accounts'!$F$5:$F$3000,0)) | V9: =IFERROR(INDEX('Chart of Accounts'!$C$5:$C$3000,MATCH(Q9&"",'Chart of Accounts'!$A$5:$A$3000,0))&"|"&INDEX('Chart of Accounts'!$D$5:$D$3000,MATCH(Q9&"",'Chart of Accounts'!$A$5:$A$3000,0)),"") | W9: =IFERROR(INDEX('Chart of Accounts'!$C$5:$C$3000,MATCH(T9&"",'Chart of Accounts'!$A$5:$A$3000,0))&"|"&INDEX('Chart of Accounts'!$D$5:$D$3000,MATCH(T9&"",'Chart of Accounts'!$A$5:$A$3000,0)),"") | X9: =IFERROR(INDEX('Chart of Accounts'!$C$5:$C$3000,MATCH(R9&"",'Chart of Accounts'!$A$5:$A$3000,0))&"|"&INDEX('Chart of Accounts'!$D$5:$D$3000,MATCH(R9&"",'Chart of Accounts'!$A$5:$A$3000,0)),"") | Y9: =IFERROR(INDEX('Chart of Accounts'!$C$5:$C$3000,MATCH(S9&"",'Chart of Accounts'!$A$5:$A$3000,0))&"|"&INDEX('Chart of Accounts'!$D$5:$D$3000,MATCH(S9&"",'Chart of Accounts'!$A$5:$A$3000,0)),"") | Z9: =IFERROR(INDEX('Chart of Accounts'!$C$5:$C$3000,MATCH(U9&"",'Chart of Accounts'!$A$5:$A$3000,0))&"|"&INDEX('Chart of Accounts'!$D$5:$D$3000,MATCH(U9&"",'Chart of Accounts'!$A$5:$A$3000,0)),"") | AA9: =IF(LEFT(V9,8)="Revenue|",-N(F9),0)+IF(LEFT(W9,8)="Revenue|",-N(M9),0)+IF(LEFT(X9,8)="Revenue|",N(O9),0)+IF(LEFT(Y9,8)="Revenue|",N(P9),0)+IF(LEFT(Z9,8)="Revenue|",N(N9),0) | AB9: =IF(LEFT(V9,5)="COGS|",N(F9),0)+IF(LEFT(W9,5)="COGS|",N(M9),0)+IF(LEFT(X9,5)="COGS|",-N(O9),0)+IF(LEFT(Y9,5)="COGS|",-N(P9),0)+IF(LEFT(Z9,5)="COGS|",-N(N9),0) | AC9: =IF(LEFT(V9,8)="Expense|",N(F9),0)+IF(LEFT(W9,8)="Expense|",N(M9),0)+IF(LEFT(X9,8)="Expense|",-N(O9),0)+IF(LEFT(Y9,8)="Expense|",-N(P9),0)+IF(LEFT(Z9,8)="Expense|",-N(N9),0) | AD9: =IF(ISNUMBER(MATCH(V9,{"Expense|employee","Expense|general_admin","Expense|marketing","Expense|utilities","Expense|other_operating"},0)),N(F9),0)+IF(ISNUMBER(MATCH(W9,{"Expense|employee","Expense|general_admin","Expense|marketing","Expense|utilities","Expense|other_operating"},0)),N(M9),0)+IF(ISNUMBER(MATCH(X9,{"Expense|employee","Expense|general_admin","Expense|marketing","Expense|utilities","Expense|other_operating"},0)),-N(O9),0)+IF(ISNUMBER(MATCH(Y9,{"Expense|employee","Expense|general_admin","Expense|marketing","Expense|utilities","Expense|other_operating"},0)),-N(P9),0)+IF(ISNUMBER(MATCH(Z9,{"Expense|employee","Expense|general_admin","Expense|marketing","Expense|utilities","Expense|other_operating"},0)),-N(N9),0) | AE9: =IF(V9="Liability|payable",-N(F9),0)+IF(W9="Liability|payable",-N(M9),0)+IF(X9="Liability|payable",N(O9),0)+IF(Y9="Liability|payable",N(P9),0)+IF(Z9="Liability|payable",N(N9),0) | AF9: =IF(V9="Liability|accrued",-N(F9),0)+IF(W9="Liability|accrued",-N(M9),0)+IF(X9="Liability|accrued",N(O9),0)+IF(Y9="Liability|accrued",N(P9),0)+IF(Z9="Liability|accrued",N(N9),0) | AG9: =IF(AND(N(F9)<>0,V9=""),1,0)+IF(AND(N(M9)<>0,W9=""),1,0)+IF(AND(N(O9)<>0,X9=""),1,0)+IF(AND(N(P9)<>0,Y9=""),1,0)+IF(AND(N(N9)<>0,Z9=""),1,0)
M10: =ROUND(N(F10)*IFERROR(VLOOKUP(K10,'Tax Codes'!$A$5:$E$300,5,FALSE),0),2) | N10: =ROUND(N(F10)*IFERROR(VLOOKUP(L10,'Tax Codes'!$A$5:$E$300,5,FALSE),0),2) | O10: =IF(G10="",N(F10)+M10-N10,N(G10)) | P10: =N(F10)+M10-N10-O10 | Q10: =IF(C10="",INDEX('Chart of Accounts'!$A$5:$A$3000,MATCH("other_overhead",'Chart of Accounts'!$F$5:$F$3000,0)),C10&"") | R10: =IF(I10="",INDEX('Chart of Accounts'!$A$5:$A$3000,MATCH("bank",'Chart of Accounts'!$F$5:$F$3000,0)),I10&"") | S10: =IF(J10="",INDEX('Chart of Accounts'!$A$5:$A$3000,MATCH("ap",'Chart of Accounts'!$F$5:$F$3000,0)),J10&"") | T10: =INDEX('Chart of Accounts'!$A$5:$A$3000,MATCH("vat_input",'Chart of Accounts'!$F$5:$F$3000,0)) | U10: =INDEX('Chart of Accounts'!$A$5:$A$3000,MATCH("wht_payable",'Chart of Accounts'!$F$5:$F$3000,0)) | V10: =IFERROR(INDEX('Chart of Accounts'!$C$5:$C$3000,MATCH(Q10&"",'Chart of Accounts'!$A$5:$A$3000,0))&"|"&INDEX('Chart of Accounts'!$D$5:$D$3000,MATCH(Q10&"",'Chart of Accounts'!$A$5:$A$3000,0)),"") | W10: =IFERROR(INDEX('Chart of Accounts'!$C$5:$C$3000,MATCH(T10&"",'Chart of Accounts'!$A$5:$A$3000,0))&"|"&INDEX('Chart of Accounts'!$D$5:$D$3000,MATCH(T10&"",'Chart of Accounts'!$A$5:$A$3000,0)),"") | X10: =IFERROR(INDEX('Chart of Accounts'!$C$5:$C$3000,MATCH(R10&"",'Chart of Accounts'!$A$5:$A$3000,0))&"|"&INDEX('Chart of Accounts'!$D$5:$D$3000,MATCH(R10&"",'Chart of Accounts'!$A$5:$A$3000,0)),"") | Y10: =IFERROR(INDEX('Chart of Accounts'!$C$5:$C$3000,MATCH(S10&"",'Chart of Accounts'!$A$5:$A$3000,0))&"|"&INDEX('Chart of Accounts'!$D$5:$D$3000,MATCH(S10&"",'Chart of Accounts'!$A$5:$A$3000,0)),"") | Z10: =IFERROR(INDEX('Chart of Accounts'!$C$5:$C$3000,MATCH(U10&"",'Chart of Accounts'!$A$5:$A$3000,0))&"|"&INDEX('Chart of Accounts'!$D$5:$D$3000,MATCH(U10&"",'Chart of Accounts'!$A$5:$A$3000,0)),"") | AA10: =IF(LEFT(V10,8)="Revenue|",-N(F10),0)+IF(LEFT(W10,8)="Revenue|",-N(M10),0)+IF(LEFT(X10,8)="Revenue|",N(O10),0)+IF(LEFT(Y10,8)="Revenue|",N(P10),0)+IF(LEFT(Z10,8)="Revenue|",N(N10),0) | AB10: =IF(LEFT(V10,5)="COGS|",N(F10),0)+IF(LEFT(W10,5)="COGS|",N(M10),0)+IF(LEFT(X10,5)="COGS|",-N(O10),0)+IF(LEFT(Y10,5)="COGS|",-N(P10),0)+IF(LEFT(Z10,5)="COGS|",-N(N10),0) | AC10: =IF(LEFT(V10,8)="Expense|",N(F10),0)+IF(LEFT(W10,8)="Expense|",N(M10),0)+IF(LEFT(X10,8)="Expense|",-N(O10),0)+IF(LEFT(Y10,8)="Expense|",-N(P10),0)+IF(LEFT(Z10,8)="Expense|",-N(N10),0) | AD10: =IF(ISNUMBER(MATCH(V10,{"Expense|employee","Expense|general_admin","Expense|marketing","Expense|utilities","Expense|other_operating"},0)),N(F10),0)+IF(ISNUMBER(MATCH(W10,{"Expense|employee","Expense|general_admin","Expense|marketing","Expense|utilities","Expense|other_operating"},0)),N(M10),0)+IF(ISNUMBER(MATCH(X10,{"Expense|employee","Expense|general_admin","Expense|marketing","Expense|utilities","Expense|other_operating"},0)),-N(O10),0)+IF(ISNUMBER(MATCH(Y10,{"Expense|employee","Expense|general_admin","Expense|marketing","Expense|utilities","Expense|other_operating"},0)),-N(P10),0)+IF(ISNUMBER(MATCH(Z10,{"Expense|employee","Expense|general_admin","Expense|marketing","Expense|utilities","Expense|other_operating"},0)),-N(N10),0) | AE10: =IF(V10="Liability|payable",-N(F10),0)+IF(W10="Liability|payable",-N(M10),0)+IF(X10="Liability|payable",N(O10),0)+IF(Y10="Liability|payable",N(P10),0)+IF(Z10="Liability|payable",N(N10),0) | AF10: =IF(V10="Liability|accrued",-N(F10),0)+IF(W10="Liability|accrued",-N(M10),0)+IF(X10="Liability|accrued",N(O10),0)+IF(Y10="Liability|accrued",N(P10),0)+IF(Z10="Liability|accrued",N(N10),0) | AG10: =IF(AND(N(F10)<>0,V10=""),1,0)+IF(AND(N(M10)<>0,W10=""),1,0)+IF(AND(N(O10)<>0,X10=""),1,0)+IF(AND(N(P10)<>0,Y10=""),1,0)+IF(AND(N(N10)<>0,Z10=""),1,0)
M11: =ROUND(N(F11)*IFERROR(VLOOKUP(K11,'Tax Codes'!$A$5:$E$300,5,FALSE),0),2) | N11: =ROUND(N(F11)*IFERROR(VLOOKUP(L11,'Tax Codes'!$A$5:$E$300,5,FALSE),0),2) | O11: =IF(G11="",N(F11)+M11-N11,N(G11)) | P11: =N(F11)+M11-N11-O11 | Q11: =IF(C11="",INDEX('Chart of Accounts'!$A$5:$A$3000,MATCH("other_overhead",'Chart of Accounts'!$F$5:$F$3000,0)),C11&"") | R11: =IF(I11="",INDEX('Chart of Accounts'!$A$5:$A$3000,MATCH("bank",'Chart of Accounts'!$F$5:$F$3000,0)),I11&"") | S11: =IF(J11="",INDEX('Chart of Accounts'!$A$5:$A$3000,MATCH("ap",'Chart of Accounts'!$F$5:$F$3000,0)),J11&"") | T11: =INDEX('Chart of Accounts'!$A$5:$A$3000,MATCH("vat_input",'Chart of Accounts'!$F$5:$F$3000,0)) | U11: =INDEX('Chart of Accounts'!$A$5:$A$3000,MATCH("wht_payable",'Chart of Accounts'!$F$5:$F$3000,0)) | V11: =IFERROR(INDEX('Chart of Accounts'!$C$5:$C$3000,MATCH(Q11&"",'Chart of Accounts'!$A$5:$A$3000,0))&"|"&INDEX('Chart of Accounts'!$D$5:$D$3000,MATCH(Q11&"",'Chart of Accounts'!$A$5:$A$3000,0)),"") | W11: =IFERROR(INDEX('Chart of Accounts'!$C$5:$C$3000,MATCH(T11&"",'Chart of Accounts'!$A$5:$A$3000,0))&"|"&INDEX('Chart of Accounts'!$D$5:$D$3000,MATCH(T11&"",'Chart of Accounts'!$A$5:$A$3000,0)),"") | X11: =IFERROR(INDEX('Chart of Accounts'!$C$5:$C$3000,MATCH(R11&"",'Chart of Accounts'!$A$5:$A$3000,0))&"|"&INDEX('Chart of Accounts'!$D$5:$D$3000,MATCH(R11&"",'Chart of Accounts'!$A$5:$A$3000,0)),"") | Y11: =IFERROR(INDEX('Chart of Accounts'!$C$5:$C$3000,MATCH(S11&"",'Chart of Accounts'!$A$5:$A$3000,0))&"|"&INDEX('Chart of Accounts'!$D$5:$D$3000,MATCH(S11&"",'Chart of Accounts'!$A$5:$A$3000,0)),"") | Z11: =IFERROR(INDEX('Chart of Accounts'!$C$5:$C$3000,MATCH(U11&"",'Chart of Accounts'!$A$5:$A$3000,0))&"|"&INDEX('Chart of Accounts'!$D$5:$D$3000,MATCH(U11&"",'Chart of Accounts'!$A$5:$A$3000,0)),"") | AA11: =IF(LEFT(V11,8)="Revenue|",-N(F11),0)+IF(LEFT(W11,8)="Revenue|",-N(M11),0)+IF(LEFT(X11,8)="Revenue|",N(O11),0)+IF(LEFT(Y11,8)="Revenue|",N(P11),0)+IF(LEFT(Z11,8)="Revenue|",N(N11),0) | AB11: =IF(LEFT(V11,5)="COGS|",N(F11),0)+IF(LEFT(W11,5)="COGS|",N(M11),0)+IF(LEFT(X11,5)="COGS|",-N(O11),0)+IF(LEFT(Y11,5)="COGS|",-N(P11),0)+IF(LEFT(Z11,5)="COGS|",-N(N11),0) | AC11: =IF(LEFT(V11,8)="Expense|",N(F11),0)+IF(LEFT(W11,8)="Expense|",N(M11),0)+IF(LEFT(X11,8)="Expense|",-N(O11),0)+IF(LEFT(Y11,8)="Expense|",-N(P11),0)+IF(LEFT(Z11,8)="Expense|",-N(N11),0) | AD11: =IF(ISNUMBER(MATCH(V11,{"Expense|employee","Expense|general_admin","Expense|marketing","Expense|utilities","Expense|other_operating"},0)),N(F11),0)+IF(ISNUMBER(MATCH(W11,{"Expense|employee","Expense|general_admin","Expense|marketing","Expense|utilities","Expense|other_operating"},0)),N(M11),0)+IF(ISNUMBER(MATCH(X11,{"Expense|employee","Expense|general_admin","Expense|marketing","Expense|utilities","Expense|other_operating"},0)),-N(O11),0)+IF(ISNUMBER(MATCH(Y11,{"Expense|employee","Expense|general_admin","Expense|marketing","Expense|utilities","Expense|other_operating"},0)),-N(P11),0)+IF(ISNUMBER(MATCH(Z11,{"Expense|employee","Expense|general_admin","Expense|marketing","Expense|utilities","Expense|other_operating"},0)),-N(N11),0) | AE11: =IF(V11="Liability|payable",-N(F11),0)+IF(W11="Liability|payable",-N(M11),0)+IF(X11="Liability|payable",N(O11),0)+IF(Y11="Liability|payable",N(P11),0)+IF(Z11="Liability|payable",N(N11),0) | AF11: =IF(V11="Liability|accrued",-N(F11),0)+IF(W11="Liability|accrued",-N(M11),0)+IF(X11="Liability|accrued",N(O11),0)+IF(Y11="Liability|accrued",N(P11),0)+IF(Z11="Liability|accrued",N(N11),0) | AG11: =IF(AND(N(F11)<>0,V11=""),1,0)+IF(AND(N(M11)<>0,W11=""),1,0)+IF(AND(N(O11)<>0,X11=""),1,0)+IF(AND(N(P11)<>0,Y11=""),1,0)+IF(AND(N(N11)<>0,Z11=""),1,0)
M12: =ROUND(N(F12)*IFERROR(VLOOKUP(K12,'Tax Codes'!$A$5:$E$300,5,FALSE),0),2) | N12: =ROUND(N(F12)*IFERROR(VLOOKUP(L12,'Tax Codes'!$A$5:$E$300,5,FALSE),0),2) | O12: =IF(G12="",N(F12)+M12-N12,N(G12)) | P12: =N(F12)+M12-N12-O12 | Q12: =IF(C12="",INDEX('Chart of Accounts'!$A$5:$A$3000,MATCH("other_overhead",'Chart of Accounts'!$F$5:$F$3000,0)),C12&"") | R12: =IF(I12="",INDEX('Chart of Accounts'!$A$5:$A$3000,MATCH("bank",'Chart of Accounts'!$F$5:$F$3000,0)),I12&"") | S12: =IF(J12="",INDEX('Chart of Accounts'!$A$5:$A$3000,MATCH("ap",'Chart of Accounts'!$F$5:$F$3000,0)),J12&"") | T12: =INDEX('Chart of Accounts'!$A$5:$A$3000,MATCH("vat_input",'Chart of Accounts'!$F$5:$F$3000,0)) | U12: =INDEX('Chart of Accounts'!$A$5:$A$3000,MATCH("wht_payable",'Chart of Accounts'!$F$5:$F$3000,0)) | V12: =IFERROR(INDEX('Chart of Accounts'!$C$5:$C$3000,MATCH(Q12&"",'Chart of Accounts'!$A$5:$A$3000,0))&"|"&INDEX('Chart of Accounts'!$D$5:$D$3000,MATCH(Q12&"",'Chart of Accounts'!$A$5:$A$3000,0)),"") | W12: =IFERROR(INDEX('Chart of Accounts'!$C$5:$C$3000,MATCH(T12&"",'Chart of Accounts'!$A$5:$A$3000,0))&"|"&INDEX('Chart of Accounts'!$D$5:$D$3000,MATCH(T12&"",'Chart of Accounts'!$A$5:$A$3000,0)),"") | X12: =IFERROR(INDEX('Chart of Accounts'!$C$5:$C$3000,MATCH(R12&"",'Chart of Accounts'!$A$5:$A$3000,0))&"|"&INDEX('Chart of Accounts'!$D$5:$D$3000,MATCH(R12&"",'Chart of Accounts'!$A$5:$A$3000,0)),"") | Y12: =IFERROR(INDEX('Chart of Accounts'!$C$5:$C$3000,MATCH(S12&"",'Chart of Accounts'!$A$5:$A$3000,0))&"|"&INDEX('Chart of Accounts'!$D$5:$D$3000,MATCH(S12&"",'Chart of Accounts'!$A$5:$A$3000,0)),"") | Z12: =IFERROR(INDEX('Chart of Accounts'!$C$5:$C$3000,MATCH(U12&"",'Chart of Accounts'!$A$5:$A$3000,0))&"|"&INDEX('Chart of Accounts'!$D$5:$D$3000,MATCH(U12&"",'Chart of Accounts'!$A$5:$A$3000,0)),"") | AA12: =IF(LEFT(V12,8)="Revenue|",-N(F12),0)+IF(LEFT(W12,8)="Revenue|",-N(M12),0)+IF(LEFT(X12,8)="Revenue|",N(O12),0)+IF(LEFT(Y12,8)="Revenue|",N(P12),0)+IF(LEFT(Z12,8)="Revenue|",N(N12),0) | AB12: =IF(LEFT(V12,5)="COGS|",N(F12),0)+IF(LEFT(W12,5)="COGS|",N(M12),0)+IF(LEFT(X12,5)="COGS|",-N(O12),0)+IF(LEFT(Y12,5)="COGS|",-N(P12),0)+IF(LEFT(Z12,5)="COGS|",-N(N12),0) | AC12: =IF(LEFT(V12,8)="Expense|",N(F12),0)+IF(LEFT(W12,8)="Expense|",N(M12),0)+IF(LEFT(X12,8)="Expense|",-N(O12),0)+IF(LEFT(Y12,8)="Expense|",-N(P12),0)+IF(LEFT(Z12,8)="Expense|",-N(N12),0) | AD12: =IF(ISNUMBER(MATCH(V12,{"Expense|employee","Expense|general_admin","Expense|marketing","Expense|utilities","Expense|other_operating"},0)),N(F12),0)+IF(ISNUMBER(MATCH(W12,{"Expense|employee","Expense|general_admin","Expense|marketing","Expense|utilities","Expense|other_operating"},0)),N(M12),0)+IF(ISNUMBER(MATCH(X12,{"Expense|employee","Expense|general_admin","Expense|marketing","Expense|utilities","Expense|other_operating"},0)),-N(O12),0)+IF(ISNUMBER(MATCH(Y12,{"Expense|employee","Expense|general_admin","Expense|marketing","Expense|utilities","Expense|other_operating"},0)),-N(P12),0)+IF(ISNUMBER(MATCH(Z12,{"Expense|employee","Expense|general_admin","Expense|marketing","Expense|utilities","Expense|other_operating"},0)),-N(N12),0) | AE12: =IF(V12="Liability|payable",-N(F12),0)+IF(W12="Liability|payable",-N(M12),0)+IF(X12="Liability|payable",N(O12),0)+IF(Y12="Liability|payable",N(P12),0)+IF(Z12="Liability|payable",N(N12),0) | AF12: =IF(V12="Liability|accrued",-N(F12),0)+IF(W12="Liability|accrued",-N(M12),0)+IF(X12="Liability|accrued",N(O12),0)+IF(Y12="Liability|accrued",N(P12),0)+IF(Z12="Liability|accrued",N(N12),0) | AG12: =IF(AND(N(F12)<>0,V12=""),1,0)+IF(AND(N(M12)<>0,W12=""),1,0)+IF(AND(N(O12)<>0,X12=""),1,0)+IF(AND(N(P12)<>0,Y12=""),1,0)+IF(AND(N(N12)<>0,Z12=""),1,0)
M13: =ROUND(N(F13)*IFERROR(VLOOKUP(K13,'Tax Codes'!$A$5:$E$300,5,FALSE),0),2) | N13: =ROUND(N(F13)*IFERROR(VLOOKUP(L13,'Tax Codes'!$A$5:$E$300,5,FALSE),0),2) | O13: =IF(G13="",N(F13)+M13-N13,N(G13)) | P13: =N(F13)+M13-N13-O13 | Q13: =IF(C13="",INDEX('Chart of Accounts'!$A$5:$A$3000,MATCH("other_overhead",'Chart of Accounts'!$F$5:$F$3000,0)),C13&"") | R13: =IF(I13="",INDEX('Chart of Accounts'!$A$5:$A$3000,MATCH("bank",'Chart of Accounts'!$F$5:$F$3000,0)),I13&"") | S13: =IF(J13="",INDEX('Chart of Accounts'!$A$5:$A$3000,MATCH("ap",'Chart of Accounts'!$F$5:$F$3000,0)),J13&"") | T13: =INDEX('Chart of Accounts'!$A$5:$A$3000,MATCH("vat_input",'Chart of Accounts'!$F$5:$F$3000,0)) | U13: =INDEX('Chart of Accounts'!$A$5:$A$3000,MATCH("wht_payable",'Chart of Accounts'!$F$5:$F$3000,0)) | V13: =IFERROR(INDEX('Chart of Accounts'!$C$5:$C$3000,MATCH(Q13&"",'Chart of Accounts'!$A$5:$A$3000,0))&"|"&INDEX('Chart of Accounts'!$D$5:$D$3000,MATCH(Q13&"",'Chart of Accounts'!$A$5:$A$3000,0)),"") | W13: =IFERROR(INDEX('Chart of Accounts'!$C$5:$C$3000,MATCH(T13&"",'Chart of Accounts'!$A$5:$A$3000,0))&"|"&INDEX('Chart of Accounts'!$D$5:$D$3000,MATCH(T13&"",'Chart of Accounts'!$A$5:$A$3000,0)),"") | X13: =IFERROR(INDEX('Chart of Accounts'!$C$5:$C$3000,MATCH(R13&"",'Chart of Accounts'!$A$5:$A$3000,0))&"|"&INDEX('Chart of Accounts'!$D$5:$D$3000,MATCH(R13&"",'Chart of Accounts'!$A$5:$A$3000,0)),"") | Y13: =IFERROR(INDEX('Chart of Accounts'!$C$5:$C$3000,MATCH(S13&"",'Chart of Accounts'!$A$5:$A$3000,0))&"|"&INDEX('Chart of Accounts'!$D$5:$D$3000,MATCH(S13&"",'Chart of Accounts'!$A$5:$A$3000,0)),"") | Z13: =IFERROR(INDEX('Chart of Accounts'!$C$5:$C$3000,MATCH(U13&"",'Chart of Accounts'!$A$5:$A$3000,0))&"|"&INDEX('Chart of Accounts'!$D$5:$D$3000,MATCH(U13&"",'Chart of Accounts'!$A$5:$A$3000,0)),"") | AA13: =IF(LEFT(V13,8)="Revenue|",-N(F13),0)+IF(LEFT(W13,8)="Revenue|",-N(M13),0)+IF(LEFT(X13,8)="Revenue|",N(O13),0)+IF(LEFT(Y13,8)="Revenue|",N(P13),0)+IF(LEFT(Z13,8)="Revenue|",N(N13),0) | AB13: =IF(LEFT(V13,5)="COGS|",N(F13),0)+IF(LEFT(W13,5)="COGS|",N(M13),0)+IF(LEFT(X13,5)="COGS|",-N(O13),0)+IF(LEFT(Y13,5)="COGS|",-N(P13),0)+IF(LEFT(Z13,5)="COGS|",-N(N13),0) | AC13: =IF(LEFT(V13,8)="Expense|",N(F13),0)+IF(LEFT(W13,8)="Expense|",N(M13),0)+IF(LEFT(X13,8)="Expense|",-N(O13),0)+IF(LEFT(Y13,8)="Expense|",-N(P13),0)+IF(LEFT(Z13,8)="Expense|",-N(N13),0) | AD13: =IF(ISNUMBER(MATCH(V13,{"Expense|employee","Expense|general_admin","Expense|marketing","Expense|utilities","Expense|other_operating"},0)),N(F13),0)+IF(ISNUMBER(MATCH(W13,{"Expense|employee","Expense|general_admin","Expense|marketing","Expense|utilities","Expense|other_operating"},0)),N(M13),0)+IF(ISNUMBER(MATCH(X13,{"Expense|employee","Expense|general_admin","Expense|marketing","Expense|utilities","Expense|other_operating"},0)),-N(O13),0)+IF(ISNUMBER(MATCH(Y13,{"Expense|employee","Expense|general_admin","Expense|marketing","Expense|utilities","Expense|other_operating"},0)),-N(P13),0)+IF(ISNUMBER(MATCH(Z13,{"Expense|employee","Expense|general_admin","Expense|marketing","Expense|utilities","Expense|other_operating"},0)),-N(N13),0) | AE13: =IF(V13="Liability|payable",-N(F13),0)+IF(W13="Liability|payable",-N(M13),0)+IF(X13="Liability|payable",N(O13),0)+IF(Y13="Liability|payable",N(P13),0)+IF(Z13="Liability|payable",N(N13),0) | AF13: =IF(V13="Liability|accrued",-N(F13),0)+IF(W13="Liability|accrued",-N(M13),0)+IF(X13="Liability|accrued",N(O13),0)+IF(Y13="Liability|accrued",N(P13),0)+IF(Z13="Liability|accrued",N(N13),0) | AG13: =IF(AND(N(F13)<>0,V13=""),1,0)+IF(AND(N(M13)<>0,W13=""),1,0)+IF(AND(N(O13)<>0,X13=""),1,0)+IF(AND(N(P13)<>0,Y13=""),1,0)+IF(AND(N(N13)<>0,Z13=""),1,0)
M14: =ROUND(N(F14)*IFERROR(VLOOKUP(K14,'Tax Codes'!$A$5:$E$300,5,FALSE),0),2) | N14: =ROUND(N(F14)*IFERROR(VLOOKUP(L14,'Tax Codes'!$A$5:$E$300,5,FALSE),0),2) | O14: =IF(G14="",N(F14)+M14-N14,N(G14)) | P14: =N(F14)+M14-N14-O14 | Q14: =IF(C14="",INDEX('Chart of Accounts'!$A$5:$A$3000,MATCH("other_overhead",'Chart of Accounts'!$F$5:$F$3000,0)),C14&"") | R14: =IF(I14="",INDEX('Chart of Accounts'!$A$5:$A$3000,MATCH("bank",'Chart of Accounts'!$F$5:$F$3000,0)),I14&"") | S14: =IF(J14="",INDEX('Chart of Accounts'!$A$5:$A$3000,MATCH("ap",'Chart of Accounts'!$F$5:$F$3000,0)),J14&"") | T14: =INDEX('Chart of Accounts'!$A$5:$A$3000,MATCH("vat_input",'Chart of Accounts'!$F$5:$F$3000,0)) | U14: =INDEX('Chart of Accounts'!$A$5:$A$3000,MATCH("wht_payable",'Chart of Accounts'!$F$5:$F$3000,0)) | V14: =IFERROR(INDEX('Chart of Accounts'!$C$5:$C$3000,MATCH(Q14&"",'Chart of Accounts'!$A$5:$A$3000,0))&"|"&INDEX('Chart of Accounts'!$D$5:$D$3000,MATCH(Q14&"",'Chart of Accounts'!$A$5:$A$3000,0)),"") | W14: =IFERROR(INDEX('Chart of Accounts'!$C$5:$C$3000,MATCH(T14&"",'Chart of Accounts'!$A$5:$A$3000,0))&"|"&INDEX('Chart of Accounts'!$D$5:$D$3000,MATCH(T14&"",'Chart of Accounts'!$A$5:$A$3000,0)),"") | X14: =IFERROR(INDEX('Chart of Accounts'!$C$5:$C$3000,MATCH(R14&"",'Chart of Accounts'!$A$5:$A$3000,0))&"|"&INDEX('Chart of Accounts'!$D$5:$D$3000,MATCH(R14&"",'Chart of Accounts'!$A$5:$A$3000,0)),"") | Y14: =IFERROR(INDEX('Chart of Accounts'!$C$5:$C$3000,MATCH(S14&"",'Chart of Accounts'!$A$5:$A$3000,0))&"|"&INDEX('Chart of Accounts'!$D$5:$D$3000,MATCH(S14&"",'Chart of Accounts'!$A$5:$A$3000,0)),"") | Z14: =IFERROR(INDEX('Chart of Accounts'!$C$5:$C$3000,MATCH(U14&"",'Chart of Accounts'!$A$5:$A$3000,0))&"|"&INDEX('Chart of Accounts'!$D$5:$D$3000,MATCH(U14&"",'Chart of Accounts'!$A$5:$A$3000,0)),"") | AA14: =IF(LEFT(V14,8)="Revenue|",-N(F14),0)+IF(LEFT(W14,8)="Revenue|",-N(M14),0)+IF(LEFT(X14,8)="Revenue|",N(O14),0)+IF(LEFT(Y14,8)="Revenue|",N(P14),0)+IF(LEFT(Z14,8)="Revenue|",N(N14),0) | AB14: =IF(LEFT(V14,5)="COGS|",N(F14),0)+IF(LEFT(W14,5)="COGS|",N(M14),0)+IF(LEFT(X14,5)="COGS|",-N(O14),0)+IF(LEFT(Y14,5)="COGS|",-N(P14),0)+IF(LEFT(Z14,5)="COGS|",-N(N14),0) | AC14: =IF(LEFT(V14,8)="Expense|",N(F14),0)+IF(LEFT(W14,8)="Expense|",N(M14),0)+IF(LEFT(X14,8)="Expense|",-N(O14),0)+IF(LEFT(Y14,8)="Expense|",-N(P14),0)+IF(LEFT(Z14,8)="Expense|",-N(N14),0) | AD14: =IF(ISNUMBER(MATCH(V14,{"Expense|employee","Expense|general_admin","Expense|marketing","Expense|utilities","Expense|other_operating"},0)),N(F14),0)+IF(ISNUMBER(MATCH(W14,{"Expense|employee","Expense|general_admin","Expense|marketing","Expense|utilities","Expense|other_operating"},0)),N(M14),0)+IF(ISNUMBER(MATCH(X14,{"Expense|employee","Expense|general_admin","Expense|marketing","Expense|utilities","Expense|other_operating"},0)),-N(O14),0)+IF(ISNUMBER(MATCH(Y14,{"Expense|employee","Expense|general_admin","Expense|marketing","Expense|utilities","Expense|other_operating"},0)),-N(P14),0)+IF(ISNUMBER(MATCH(Z14,{"Expense|employee","Expense|general_admin","Expense|marketing","Expense|utilities","Expense|other_operating"},0)),-N(N14),0) | AE14: =IF(V14="Liability|payable",-N(F14),0)+IF(W14="Liability|payable",-N(M14),0)+IF(X14="Liability|payable",N(O14),0)+IF(Y14="Liability|payable",N(P14),0)+IF(Z14="Liability|payable",N(N14),0) | AF14: =IF(V14="Liability|accrued",-N(F14),0)+IF(W14="Liability|accrued",-N(M14),0)+IF(X14="Liability|accrued",N(O14),0)+IF(Y14="Liability|accrued",N(P14),0)+IF(Z14="Liability|accrued",N(N14),0) | AG14: =IF(AND(N(F14)<>0,V14=""),1,0)+IF(AND(N(M14)<>0,W14=""),1,0)+IF(AND(N(O14)<>0,X14=""),1,0)+IF(AND(N(P14)<>0,Y14=""),1,0)+IF(AND(N(N14)<>0,Z14=""),1,0)
M15: =ROUND(N(F15)*IFERROR(VLOOKUP(K15,'Tax Codes'!$A$5:$E$300,5,FALSE),0),2) | N15: =ROUND(N(F15)*IFERROR(VLOOKUP(L15,'Tax Codes'!$A$5:$E$300,5,FALSE),0),2) | O15: =IF(G15="",N(F15)+M15-N15,N(G15)) | P15: =N(F15)+M15-N15-O15 | Q15: =IF(C15="",INDEX('Chart of Accounts'!$A$5:$A$3000,MATCH("other_overhead",'Chart of Accounts'!$F$5:$F$3000,0)),C15&"") | R15: =IF(I15="",INDEX('Chart of Accounts'!$A$5:$A$3000,MATCH("bank",'Chart of Accounts'!$F$5:$F$3000,0)),I15&"") | S15: =IF(J15="",INDEX('Chart of Accounts'!$A$5:$A$3000,MATCH("ap",'Chart of Accounts'!$F$5:$F$3000,0)),J15&"") | T15: =INDEX('Chart of Accounts'!$A$5:$A$3000,MATCH("vat_input",'Chart of Accounts'!$F$5:$F$3000,0)) | U15: =INDEX('Chart of Accounts'!$A$5:$A$3000,MATCH("wht_payable",'Chart of Accounts'!$F$5:$F$3000,0)) | V15: =IFERROR(INDEX('Chart of Accounts'!$C$5:$C$3000,MATCH(Q15&"",'Chart of Accounts'!$A$5:$A$3000,0))&"|"&INDEX('Chart of Accounts'!$D$5:$D$3000,MATCH(Q15&"",'Chart of Accounts'!$A$5:$A$3000,0)),"") | W15: =IFERROR(INDEX('Chart of Accounts'!$C$5:$C$3000,MATCH(T15&"",'Chart of Accounts'!$A$5:$A$3000,0))&"|"&INDEX('Chart of Accounts'!$D$5:$D$3000,MATCH(T15&"",'Chart of Accounts'!$A$5:$A$3000,0)),"") | X15: =IFERROR(INDEX('Chart of Accounts'!$C$5:$C$3000,MATCH(R15&"",'Chart of Accounts'!$A$5:$A$3000,0))&"|"&INDEX('Chart of Accounts'!$D$5:$D$3000,MATCH(R15&"",'Chart of Accounts'!$A$5:$A$3000,0)),"") | Y15: =IFERROR(INDEX('Chart of Accounts'!$C$5:$C$3000,MATCH(S15&"",'Chart of Accounts'!$A$5:$A$3000,0))&"|"&INDEX('Chart of Accounts'!$D$5:$D$3000,MATCH(S15&"",'Chart of Accounts'!$A$5:$A$3000,0)),"") | Z15: =IFERROR(INDEX('Chart of Accounts'!$C$5:$C$3000,MATCH(U15&"",'Chart of Accounts'!$A$5:$A$3000,0))&"|"&INDEX('Chart of Accounts'!$D$5:$D$3000,MATCH(U15&"",'Chart of Accounts'!$A$5:$A$3000,0)),"") | AA15: =IF(LEFT(V15,8)="Revenue|",-N(F15),0)+IF(LEFT(W15,8)="Revenue|",-N(M15),0)+IF(LEFT(X15,8)="Revenue|",N(O15),0)+IF(LEFT(Y15,8)="Revenue|",N(P15),0)+IF(LEFT(Z15,8)="Revenue|",N(N15),0) | AB15: =IF(LEFT(V15,5)="COGS|",N(F15),0)+IF(LEFT(W15,5)="COGS|",N(M15),0)+IF(LEFT(X15,5)="COGS|",-N(O15),0)+IF(LEFT(Y15,5)="COGS|",-N(P15),0)+IF(LEFT(Z15,5)="COGS|",-N(N15),0) | AC15: =IF(LEFT(V15,8)="Expense|",N(F15),0)+IF(LEFT(W15,8)="Expense|",N(M15),0)+IF(LEFT(X15,8)="Expense|",-N(O15),0)+IF(LEFT(Y15,8)="Expense|",-N(P15),0)+IF(LEFT(Z15,8)="Expense|",-N(N15),0) | AD15: =IF(ISNUMBER(MATCH(V15,{"Expense|employee","Expense|general_admin","Expense|marketing","Expense|utilities","Expense|other_operating"},0)),N(F15),0)+IF(ISNUMBER(MATCH(W15,{"Expense|employee","Expense|general_admin","Expense|marketing","Expense|utilities","Expense|other_operating"},0)),N(M15),0)+IF(ISNUMBER(MATCH(X15,{"Expense|employee","Expense|general_admin","Expense|marketing","Expense|utilities","Expense|other_operating"},0)),-N(O15),0)+IF(ISNUMBER(MATCH(Y15,{"Expense|employee","Expense|general_admin","Expense|marketing","Expense|utilities","Expense|other_operating"},0)),-N(P15),0)+IF(ISNUMBER(MATCH(Z15,{"Expense|employee","Expense|general_admin","Expense|marketing","Expense|utilities","Expense|other_operating"},0)),-N(N15),0) | AE15: =IF(V15="Liability|payable",-N(F15),0)+IF(W15="Liability|payable",-N(M15),0)+IF(X15="Liability|payable",N(O15),0)+IF(Y15="Liability|payable",N(P15),0)+IF(Z15="Liability|payable",N(N15),0) | AF15: =IF(V15="Liability|accrued",-N(F15),0)+IF(W15="Liability|accrued",-N(M15),0)+IF(X15="Liability|accrued",N(O15),0)+IF(Y15="Liability|accrued",N(P15),0)+IF(Z15="Liability|accrued",N(N15),0) | AG15: =IF(AND(N(F15)<>0,V15=""),1,0)+IF(AND(N(M15)<>0,W15=""),1,0)+IF(AND(N(O15)<>0,X15=""),1,0)+IF(AND(N(P15)<>0,Y15=""),1,0)+IF(AND(N(N15)<>0,Z15=""),1,0)
M16: =ROUND(N(F16)*IFERROR(VLOOKUP(K16,'Tax Codes'!$A$5:$E$300,5,FALSE),0),2) | N16: =ROUND(N(F16)*IFERROR(VLOOKUP(L16,'Tax Codes'!$A$5:$E$300,5,FALSE),0),2) | O16: =IF(G16="",N(F16)+M16-N16,N(G16)) | P16: =N(F16)+M16-N16-O16 | Q16: =IF(C16="",INDEX('Chart of Accounts'!$A$5:$A$3000,MATCH("other_overhead",'Chart of Accounts'!$F$5:$F$3000,0)),C16&"") | R16: =IF(I16="",INDEX('Chart of Accounts'!$A$5:$A$3000,MATCH("bank",'Chart of Accounts'!$F$5:$F$3000,0)),I16&"") | S16: =IF(J16="",INDEX('Chart of Accounts'!$A$5:$A$3000,MATCH("ap",'Chart of Accounts'!$F$5:$F$3000,0)),J16&"") | T16: =INDEX('Chart of Accounts'!$A$5:$A$3000,MATCH("vat_input",'Chart of Accounts'!$F$5:$F$3000,0)) | U16: =INDEX('Chart of Accounts'!$A$5:$A$3000,MATCH("wht_payable",'Chart of Accounts'!$F$5:$F$3000,0)) | V16: =IFERROR(INDEX('Chart of Accounts'!$C$5:$C$3000,MATCH(Q16&"",'Chart of Accounts'!$A$5:$A$3000,0))&"|"&INDEX('Chart of Accounts'!$D$5:$D$3000,MATCH(Q16&"",'Chart of Accounts'!$A$5:$A$3000,0)),"") | W16: =IFERROR(INDEX('Chart of Accounts'!$C$5:$C$3000,MATCH(T16&"",'Chart of Accounts'!$A$5:$A$3000,0))&"|"&INDEX('Chart of Accounts'!$D$5:$D$3000,MATCH(T16&"",'Chart of Accounts'!$A$5:$A$3000,0)),"") | X16: =IFERROR(INDEX('Chart of Accounts'!$C$5:$C$3000,MATCH(R16&"",'Chart of Accounts'!$A$5:$A$3000,0))&"|"&INDEX('Chart of Accounts'!$D$5:$D$3000,MATCH(R16&"",'Chart of Accounts'!$A$5:$A$3000,0)),"") | Y16: =IFERROR(INDEX('Chart of Accounts'!$C$5:$C$3000,MATCH(S16&"",'Chart of Accounts'!$A$5:$A$3000,0))&"|"&INDEX('Chart of Accounts'!$D$5:$D$3000,MATCH(S16&"",'Chart of Accounts'!$A$5:$A$3000,0)),"") | Z16: =IFERROR(INDEX('Chart of Accounts'!$C$5:$C$3000,MATCH(U16&"",'Chart of Accounts'!$A$5:$A$3000,0))&"|"&INDEX('Chart of Accounts'!$D$5:$D$3000,MATCH(U16&"",'Chart of Accounts'!$A$5:$A$3000,0)),"") | AA16: =IF(LEFT(V16,8)="Revenue|",-N(F16),0)+IF(LEFT(W16,8)="Revenue|",-N(M16),0)+IF(LEFT(X16,8)="Revenue|",N(O16),0)+IF(LEFT(Y16,8)="Revenue|",N(P16),0)+IF(LEFT(Z16,8)="Revenue|",N(N16),0) | AB16: =IF(LEFT(V16,5)="COGS|",N(F16),0)+IF(LEFT(W16,5)="COGS|",N(M16),0)+IF(LEFT(X16,5)="COGS|",-N(O16),0)+IF(LEFT(Y16,5)="COGS|",-N(P16),0)+IF(LEFT(Z16,5)="COGS|",-N(N16),0) | AC16: =IF(LEFT(V16,8)="Expense|",N(F16),0)+IF(LEFT(W16,8)="Expense|",N(M16),0)+IF(LEFT(X16,8)="Expense|",-N(O16),0)+IF(LEFT(Y16,8)="Expense|",-N(P16),0)+IF(LEFT(Z16,8)="Expense|",-N(N16),0) | AD16: =IF(ISNUMBER(MATCH(V16,{"Expense|employee","Expense|general_admin","Expense|marketing","Expense|utilities","Expense|other_operating"},0)),N(F16),0)+IF(ISNUMBER(MATCH(W16,{"Expense|employee","Expense|general_admin","Expense|marketing","Expense|utilities","Expense|other_operating"},0)),N(M16),0)+IF(ISNUMBER(MATCH(X16,{"Expense|employee","Expense|general_admin","Expense|marketing","Expense|utilities","Expense|other_operating"},0)),-N(O16),0)+IF(ISNUMBER(MATCH(Y16,{"Expense|employee","Expense|general_admin","Expense|marketing","Expense|utilities","Expense|other_operating"},0)),-N(P16),0)+IF(ISNUMBER(MATCH(Z16,{"Expense|employee","Expense|general_admin","Expense|marketing","Expense|utilities","Expense|other_operating"},0)),-N(N16),0) | AE16: =IF(V16="Liability|payable",-N(F16),0)+IF(W16="Liability|payable",-N(M16),0)+IF(X16="Liability|payable",N(O16),0)+IF(Y16="Liability|payable",N(P16),0)+IF(Z16="Liability|payable",N(N16),0) | AF16: =IF(V16="Liability|accrued",-N(F16),0)+IF(W16="Liability|accrued",-N(M16),0)+IF(X16="Liability|accrued",N(O16),0)+IF(Y16="Liability|accrued",N(P16),0)+IF(Z16="Liability|accrued",N(N16),0) | AG16: =IF(AND(N(F16)<>0,V16=""),1,0)+IF(AND(N(M16)<>0,W16=""),1,0)+IF(AND(N(O16)<>0,X16=""),1,0)+IF(AND(N(P16)<>0,Y16=""),1,0)+IF(AND(N(N16)<>0,Z16=""),1,0)
... M204: =ROUND(N(F204)*IFERROR(VLOOKUP(K204,'Tax Codes'!$A$5:$E$300,5,FALSE),0),2) | N204: =ROUND(N(F204)*IFERROR(VLOOKUP(L204,'Tax Codes'!$A$5:$E$300,5,FALSE),0),2) | O204: =IF(G204="",N(F204)+M204-N204,N(G204)) | P204: =N(F204)+M204-N204-O204 | Q204: =IF(C204="",INDEX('Chart of Accounts'!$A$5:$A$3000,MATCH("other_overhead",'Chart of Accounts'!$F$5:$F$3000,0)),C204&"") | R204: =IF(I204="",INDEX('Chart of Accounts'!$A$5:$A$3000,MATCH("bank",'Chart of Accounts'!$F$5:$F$3000,0)),I204&"") | S204: =IF(J204="",INDEX('Chart of Accounts'!$A$5:$A$3000,MATCH("ap",'Chart of Accounts'!$F$5:$F$3000,0)),J204&"") | T204: =INDEX('Chart of Accounts'!$A$5:$A$3000,MATCH("vat_input",'Chart of Accounts'!$F$5:$F$3000,0)) | U204: =INDEX('Chart of Accounts'!$A$5:$A$3000,MATCH("wht_payable",'Chart of Accounts'!$F$5:$F$3000,0)) | V204: =IFERROR(INDEX('Chart of Accounts'!$C$5:$C$3000,MATCH(Q204&"",'Chart of Accounts'!$A$5:$A$3000,0))&"|"&INDEX('Chart of Accounts'!$D$5:$D$3000,MATCH(Q204&"",'Chart of Accounts'!$A$5:$A$3000,0)),"") | W204: =IFERROR(INDEX('Chart of Accounts'!$C$5:$C$3000,MATCH(T204&"",'Chart of Accounts'!$A$5:$A$3000,0))&"|"&INDEX('Chart of Accounts'!$D$5:$D$3000,MATCH(T204&"",'Chart of Accounts'!$A$5:$A$3000,0)),"") | X204: =IFERROR(INDEX('Chart of Accounts'!$C$5:$C$3000,MATCH(R204&"",'Chart of Accounts'!$A$5:$A$3000,0))&"|"&INDEX('Chart of Accounts'!$D$5:$D$3000,MATCH(R204&"",'Chart of Accounts'!$A$5:$A$3000,0)),"") | Y204: =IFERROR(INDEX('Chart of Accounts'!$C$5:$C$3000,MATCH(S204&"",'Chart of Accounts'!$A$5:$A$3000,0))&"|"&INDEX('Chart of Accounts'!$D$5:$D$3000,MATCH(S204&"",'Chart of Accounts'!$A$5:$A$3000,0)),"") | Z204: =IFERROR(INDEX('Chart of Accounts'!$C$5:$C$3000,MATCH(U204&"",'Chart of Accounts'!$A$5:$A$3000,0))&"|"&INDEX('Chart of Accounts'!$D$5:$D$3000,MATCH(U204&"",'Chart of Accounts'!$A$5:$A$3000,0)),"") | AA204: =IF(LEFT(V204,8)="Revenue|",-N(F204),0)+IF(LEFT(W204,8)="Revenue|",-N(M204),0)+IF(LEFT(X204,8)="Revenue|",N(O204),0)+IF(LEFT(Y204,8)="Revenue|",N(P204),0)+IF(LEFT(Z204,8)="Revenue|",N(N204),0) | AB204: =IF(LEFT(V204,5)="COGS|",N(F204),0)+IF(LEFT(W204,5)="COGS|",N(M204),0)+IF(LEFT(X204,5)="COGS|",-N(O204),0)+IF(LEFT(Y204,5)="COGS|",-N(P204),0)+IF(LEFT(Z204,5)="COGS|",-N(N204),0) | AC204: =IF(LEFT(V204,8)="Expense|",N(F204),0)+IF(LEFT(W204,8)="Expense|",N(M204),0)+IF(LEFT(X204,8)="Expense|",-N(O204),0)+IF(LEFT(Y204,8)="Expense|",-N(P204),0)+IF(LEFT(Z204,8)="Expense|",-N(N204),0) | AD204: =IF(ISNUMBER(MATCH(V204,{"Expense|employee","Expense|general_admin","Expense|marketing","Expense|utilities","Expense|other_operating"},0)),N(F204),0)+IF(ISNUMBER(MATCH(W204,{"Expense|employee","Expense|general_admin","Expense|marketing","Expense|utilities","Expense|other_operating"},0)),N(M204),0)+IF(ISNUMBER(MATCH(X204,{"Expense|employee","Expense|general_admin","Expense|marketing","Expense|utilities","Expense|other_operating"},0)),-N(O204),0)+IF(ISNUMBER(MATCH(Y204,{"Expense|employee","Expense|general_admin","Expense|marketing","Expense|utilities","Expense|other_operating"},0)),-N(P204),0)+IF(ISNUMBER(MATCH(Z204,{"Expense|employee","Expense|general_admin","Expense|marketing","Expense|utilities","Expense|other_operating"},0)),-N(N204),0) | AE204: =IF(V204="Liability|payable",-N(F204),0)+IF(W204="Liability|payable",-N(M204),0)+IF(X204="Liability|payable",N(O204),0)+IF(Y204="Liability|payable",N(P204),0)+IF(Z204="Liability|payable",N(N204),0) | AF204: =IF(V204="Liability|accrued",-N(F204),0)+IF(W204="Liability|accrued",-N(M204),0)+IF(X204="Liability|accrued",N(O204),0)+IF(Y204="Liability|accrued",N(P204),0)+IF(Z204="Liability|accrued",N(N204),0) | AG204: =IF(AND(N(F204)<>0,V204=""),1,0)+IF(AND(N(M204)<>0,W204=""),1,0)+IF(AND(N(O204)<>0,X204=""),1,0)+IF(AND(N(P204)<>0,Y204=""),1,0)+IF(AND(N(N204)<>0,Z204=""),1,0)

Sheet Payroll
A1: BEYOND DESIGN | PAYROLL
A2: Payroll accruals — wages earned (and paid now) per worker
A3: e.g. 2026-10-31 | B3: PRJ-2026-004 | C3: Ahmed Ali | D3: Site engineer | E3: Direct Labour (Cost of Revenue) | G3: 2026-10 | H3: Monthly | I3: 1 | J3: 12000 | K3: 12000
A4: Date | B4: Business Unit | C4: Employee / Worker | D4: Position | E4: Cost Classification | F4: Expense Account | G4: Period | H4: Rate Basis | I4: Days / Months | J4: Rate | K4: Paid Now | L4: Payment Method | M4: Paid From | N4: Payroll Payable Account | O4: Gross Pay | P4: Unpaid | Q4: account (effective) | R4: paid_from (effective) | S4: payable_account (effective) | T4: leg 1 type | U4: leg 2 type | V4: leg 3 type | W4: revenue | X4: cost of sales | Y4: expenses | Z4: operating expenses | AA4: payables | AB4: accruals | AC4: unknown account
O5: =ROUND(N(I5)*N(J5),2) | P5: =O5-N(K5) | Q5: =IF(F5<>"",F5&"",IF(LEFT(E5,6)="Indire",INDEX('Chart of Accounts'!$A$5:$A$3000,MATCH("project_overhead",'Chart of Accounts'!$F$5:$F$3000,0)),IF(LEFT(E5,6)="Admini",INDEX('Chart of Accounts'!$A$5:$A$3000,MATCH("admin_salaries",'Chart of Accounts'!$F$5:$F$3000,0)),INDEX('Chart of Accounts'!$A$5:$A$3000,MATCH("direct_labour",'Chart of Accounts'!$F$5:$F$3000,0))))) | R5: =IF(M5="",INDEX('Chart of Accounts'!$A$5:$A$3000,MATCH("bank",'Chart of Accounts'!$F$5:$F$3000,0)),M5&"") | S5: =IF(N5="",INDEX('Chart of Accounts'!$A$5:$A$3000,MATCH("accrued_payroll",'Chart of Accounts'!$F$5:$F$3000,0)),N5&"") | T5: =IFERROR(INDEX('Chart of Accounts'!$C$5:$C$3000,MATCH(Q5&"",'Chart of Accounts'!$A$5:$A$3000,0))&"|"&INDEX('Chart of Accounts'!$D$5:$D$3000,MATCH(Q5&"",'Chart of Accounts'!$A$5:$A$3000,0)),"") | U5: =IFERROR(INDEX('Chart of Accounts'!$C$5:$C$3000,MATCH(R5&"",'Chart of Accounts'!$A$5:$A$3000,0))&"|"&INDEX('Chart of Accounts'!$D$5:$D$3000,MATCH(R5&"",'Chart of Accounts'!$A$5:$A$3000,0)),"") | V5: =IFERROR(INDEX('Chart of Accounts'!$C$5:$C$3000,MATCH(S5&"",'Chart of Accounts'!$A$5:$A$3000,0))&"|"&INDEX('Chart of Accounts'!$D$5:$D$3000,MATCH(S5&"",'Chart of Accounts'!$A$5:$A$3000,0)),"") | W5: =IF(LEFT(T5,8)="Revenue|",-N(O5),0)+IF(LEFT(U5,8)="Revenue|",N(K5),0)+IF(LEFT(V5,8)="Revenue|",N(P5),0) | X5: =IF(LEFT(T5,5)="COGS|",N(O5),0)+IF(LEFT(U5,5)="COGS|",-N(K5),0)+IF(LEFT(V5,5)="COGS|",-N(P5),0) | Y5: =IF(LEFT(T5,8)="Expense|",N(O5),0)+IF(LEFT(U5,8)="Expense|",-N(K5),0)+IF(LEFT(V5,8)="Expense|",-N(P5),0) | Z5: =IF(ISNUMBER(MATCH(T5,{"Expense|employee","Expense|general_admin","Expense|marketing","Expense|utilities","Expense|other_operating"},0)),N(O5),0)+IF(ISNUMBER(MATCH(U5,{"Expense|employee","Expense|general_admin","Expense|marketing","Expense|utilities","Expense|other_operating"},0)),-N(K5),0)+IF(ISNUMBER(MATCH(V5,{"Expense|employee","Expense|general_admin","Expense|marketing","Expense|utilities","Expense|other_operating"},0)),-N(P5),0) | AA5: =IF(T5="Liability|payable",-N(O5),0)+IF(U5="Liability|payable",N(K5),0)+IF(V5="Liability|payable",N(P5),0) | AB5: =IF(T5="Liability|accrued",-N(O5),0)+IF(U5="Liability|accrued",N(K5),0)+IF(V5="Liability|accrued",N(P5),0) | AC5: =IF(AND(N(O5)<>0,T5=""),1,0)+IF(AND(N(K5)<>0,U5=""),1,0)+IF(AND(N(P5)<>0,V5=""),1,0)
O6: =ROUND(N(I6)*N(J6),2) | P6: =O6-N(K6) | Q6: =IF(F6<>"",F6&"",IF(LEFT(E6,6)="Indire",INDEX('Chart of Accounts'!$A$5:$A$3000,MATCH("project_overhead",'Chart of Accounts'!$F$5:$F$3000,0)),IF(LEFT(E6,6)="Admini",INDEX('Chart of Accounts'!$A$5:$A$3000,MATCH("admin_salaries",'Chart of Accounts'!$F$5:$F$3000,0)),INDEX('Chart of Accounts'!$A$5:$A$3000,MATCH("direct_labour",'Chart of Accounts'!$F$5:$F$3000,0))))) | R6: =IF(M6="",INDEX('Chart of Accounts'!$A$5:$A$3000,MATCH("bank",'Chart of Accounts'!$F$5:$F$3000,0)),M6&"") | S6: =IF(N6="",INDEX('Chart of Accounts'!$A$5:$A$3000,MATCH("accrued_payroll",'Chart of Accounts'!$F$5:$F$3000,0)),N6&"") | T6: =IFERROR(INDEX('Chart of Accounts'!$C$5:$C$3000,MATCH(Q6&"",'Chart of Accounts'!$A$5:$A$3000,0))&"|"&INDEX('Chart of Accounts'!$D$5:$D$3000,MATCH(Q6&"",'Chart of Accounts'!$A$5:$A$3000,0)),"") | U6: =IFERROR(INDEX('Chart of Accounts'!$C$5:$C$3000,MATCH(R6&"",'Chart of Accounts'!$A$5:$A$3000,0))&"|"&INDEX('Chart of Accounts'!$D$5:$D$3000,MATCH(R6&"",'Chart of Accounts'!$A$5:$A$3000,0)),"") | V6: =IFERROR(INDEX('Chart of Accounts'!$C$5:$C$3000,MATCH(S6&"",'Chart of Accounts'!$A$5:$A$3000,0))&"|"&INDEX('Chart of Accounts'!$D$5:$D$3000,MATCH(S6&"",'Chart of Accounts'!$A$5:$A$3000,0)),"") | W6: =IF(LEFT(T6,8)="Revenue|",-N(O6),0)+IF(LEFT(U6,8)="Revenue|",N(K6),0)+IF(LEFT(V6,8)="Revenue|",N(P6),0) | X6: =IF(LEFT(T6,5)="COGS|",N(O6),0)+IF(LEFT(U6,5)="COGS|",-N(K6),0)+IF(LEFT(V6,5)="COGS|",-N(P6),0) | Y6: =IF(LEFT(T6,8)="Expense|",N(O6),0)+IF(LEFT(U6,8)="Expense|",-N(K6),0)+IF(LEFT(V6,8)="Expense|",-N(P6),0) | Z6: =IF(ISNUMBER(MATCH(T6,{"Expense|employee","Expense|general_admin","Expense|marketing","Expense|utilities","Expense|other_operating"},0)),N(O6),0)+IF(ISNUMBER(MATCH(U6,{"Expense|employee","Expense|general_admin","Expense|marketing","Expense|utilities","Expense|other_operating"},0)),-N(K6),0)+IF(ISNUMBER(MATCH(V6,{"Expense|employee","Expense|general_admin","Expense|marketing","Expense|utilities","Expense|other_operating"},0)),-N(P6),0) | AA6: =IF(T6="Liability|payable",-N(O6),0)+IF(U6="Liability|payable",N(K6),0)+IF(V6="Liability|payable",N(P6),0) | AB6: =IF(T6="Liability|accrued",-N(O6),0)+IF(U6="Liability|accrued",N(K6),0)+IF(V6="Liability|accrued",N(P6),0) | AC6: =IF(AND(N(O6)<>0,T6=""),1,0)+IF(AND(N(K6)<>0,U6=""),1,0)+IF(AND(N(P6)<>0,V6=""),1,0)
O7: =ROUND(N(I7)*N(J7),2) | P7: =O7-N(K7) | Q7: =IF(F7<>"",F7&"",IF(LEFT(E7,6)="Indire",INDEX('Chart of Accounts'!$A$5:$A$3000,MATCH("project_overhead",'Chart of Accounts'!$F$5:$F$3000,0)),IF(LEFT(E7,6)="Admini",INDEX('Chart of Accounts'!$A$5:$A$3000,MATCH("admin_salaries",'Chart of Accounts'!$F$5:$F$3000,0)),INDEX('Chart of Accounts'!$A$5:$A$3000,MATCH("direct_labour",'Chart of Accounts'!$F$5:$F$3000,0))))) | R7: =IF(M7="",INDEX('Chart of Accounts'!$A$5:$A$3000,MATCH("bank",'Chart of Accounts'!$F$5:$F$3000,0)),M7&"") | S7: =IF(N7="",INDEX('Chart of Accounts'!$A$5:$A$3000,MATCH("accrued_payroll",'Chart of Accounts'!$F$5:$F$3000,0)),N7&"") | T7: =IFERROR(INDEX('Chart of Accounts'!$C$5:$C$3000,MATCH(Q7&"",'Chart of Accounts'!$A$5:$A$3000,0))&"|"&INDEX('Chart of Accounts'!$D$5:$D$3000,MATCH(Q7&"",'Chart of Accounts'!$A$5:$A$3000,0)),"") | U7: =IFERROR(INDEX('Chart of Accounts'!$C$5:$C$3000,MATCH(R7&"",'Chart of Accounts'!$A$5:$A$3000,0))&"|"&INDEX('Chart of Accounts'!$D$5:$D$3000,MATCH(R7&"",'Chart of Accounts'!$A$5:$A$3000,0)),"") | V7: =IFERROR(INDEX('Chart of Accounts'!$C$5:$C$3000,MATCH(S7&"",'Chart of Accounts'!$A$5:$A$3000,0))&"|"&INDEX('Chart of Accounts'!$D$5:$D$3000,MATCH(S7&"",'Chart of Accounts'!$A$5:$A$3000,0)),"") | W7: =IF(LEFT(T7,8)="Revenue|",-N(O7),0)+IF(LEFT(U7,8)="Revenue|",N(K7),0)+IF(LEFT(V7,8)="Revenue|",N(P7),0) | X7: =IF(LEFT(T7,5)="COGS|",N(O7),0)+IF(LEFT(U7,5)="COGS|",-N(K7),0)+IF(LEFT(V7,5)="COGS|",-N(P7),0) | Y7: =IF(LEFT(T7,8)="Expense|",N(O7),0)+IF(LEFT(U7,8)="Expense|",-N(K7),0)+IF(LEFT(V7,8)="Expense|",-N(P7),0) | Z7: =IF(ISNUMBER(MATCH(T7,{"Expense|employee","Expense|general_admin","Expense|marketing","Expense|utilities","Expense|other_operating"},0)),N(O7),0)+IF(ISNUMBER(MATCH(U7,{"Expense|employee","Expense|general_admin","Expense|marketing","Expense|utilities","Expense|other_operating"},0)),-N(K7),0)+IF(ISNUMBER(MATCH(V7,{"Expense|employee","Expense|general_admin","Expense|marketing","Expense|utilities","Expense|other_operating"},0)),-N(P7),0) | AA7: =IF(T7="Liability|payable",-N(O7),0)+IF(U7="Liability|payable",N(K7),0)+IF(V7="Liability|payable",N(P7),0) | AB7: =IF(T7="Liability|accrued",-N(O7),0)+IF(U7="Liability|accrued",N(K7),0)+IF(V7="Liability|accrued",N(P7),0) | AC7: =IF(AND(N(O7)<>0,T7=""),1,0)+IF(AND(N(K7)<>0,U7=""),1,0)+IF(AND(N(P7)<>0,V7=""),1,0)
O8: =ROUND(N(I8)*N(J8),2) | P8: =O8-N(K8) | Q8: =IF(F8<>"",F8&"",IF(LEFT(E8,6)="Indire",INDEX('Chart of Accounts'!$A$5:$A$3000,MATCH("project_overhead",'Chart of Accounts'!$F$5:$F$3000,0)),IF(LEFT(E8,6)="Admini",INDEX('Chart of Accounts'!$A$5:$A$3000,MATCH("admin_salaries",'Chart of Accounts'!$F$5:$F$3000,0)),INDEX('Chart of Accounts'!$A$5:$A$3000,MATCH("direct_labour",'Chart of Accounts'!$F$5:$F$3000,0))))) | R8: =IF(M8="",INDEX('Chart of Accounts'!$A$5:$A$3000,MATCH("bank",'Chart of Accounts'!$F$5:$F$3000,0)),M8&"") | S8: =IF(N8="",INDEX('Chart of Accounts'!$A$5:$A$3000,MATCH("accrued_payroll",'Chart of Accounts'!$F$5:$F$3000,0)),N8&"") | T8: =IFERROR(INDEX('Chart of Accounts'!$C$5:$C$3000,MATCH(Q8&"",'Chart of Accounts'!$A$5:$A$3000,0))&"|"&INDEX('Chart of Accounts'!$D$5:$D$3000,MATCH(Q8&"",'Chart of Accounts'!$A$5:$A$3000,0)),"") | U8: =IFERROR(INDEX('Chart of Accounts'!$C$5:$C$3000,MATCH(R8&"",'Chart of Accounts'!$A$5:$A$3000,0))&"|"&INDEX('Chart of Accounts'!$D$5:$D$3000,MATCH(R8&"",'Chart of Accounts'!$A$5:$A$3000,0)),"") | V8: =IFERROR(INDEX('Chart of Accounts'!$C$5:$C$3000,MATCH(S8&"",'Chart of Accounts'!$A$5:$A$3000,0))&"|"&INDEX('Chart of Accounts'!$D$5:$D$3000,MATCH(S8&"",'Chart of Accounts'!$A$5:$A$3000,0)),"") | W8: =IF(LEFT(T8,8)="Revenue|",-N(O8),0)+IF(LEFT(U8,8)="Revenue|",N(K8),0)+IF(LEFT(V8,8)="Revenue|",N(P8),0) | X8: =IF(LEFT(T8,5)="COGS|",N(O8),0)+IF(LEFT(U8,5)="COGS|",-N(K8),0)+IF(LEFT(V8,5)="COGS|",-N(P8),0) | Y8: =IF(LEFT(T8,8)="Expense|",N(O8),0)+IF(LEFT(U8,8)="Expense|",-N(K8),0)+IF(LEFT(V8,8)="Expense|",-N(P8),0) | Z8: =IF(ISNUMBER(MATCH(T8,{"Expense|employee","Expense|general_admin","Expense|marketing","Expense|utilities","Expense|other_operating"},0)),N(O8),0)+IF(ISNUMBER(MATCH(U8,{"Expense|employee","Expense|general_admin","Expense|marketing","Expense|utilities","Expense|other_operating"},0)),-N(K8),0)+IF(ISNUMBER(MATCH(V8,{"Expense|employee","Expense|general_admin","Expense|marketing","Expense|utilities","Expense|other_operating"},0)),-N(P8),0) | AA8: =IF(T8="Liability|payable",-N(O8),0)+IF(U8="Liability|payable",N(K8),0)+IF(V8="Liability|payable",N(P8),0) | AB8: =IF(T8="Liability|accrued",-N(O8),0)+IF(U8="Liability|accrued",N(K8),0)+IF(V8="Liability|accrued",N(P8),0) | AC8: =IF(AND(N(O8)<>0,T8=""),1,0)+IF(AND(N(K8)<>0,U8=""),1,0)+IF(AND(N(P8)<>0,V8=""),1,0)
O9: =ROUND(N(I9)*N(J9),2) | P9: =O9-N(K9) | Q9: =IF(F9<>"",F9&"",IF(LEFT(E9,6)="Indire",INDEX('Chart of Accounts'!$A$5:$A$3000,MATCH("project_overhead",'Chart of Accounts'!$F$5:$F$3000,0)),IF(LEFT(E9,6)="Admini",INDEX('Chart of Accounts'!$A$5:$A$3000,MATCH("admin_salaries",'Chart of Accounts'!$F$5:$F$3000,0)),INDEX('Chart of Accounts'!$A$5:$A$3000,MATCH("direct_labour",'Chart of Accounts'!$F$5:$F$3000,0))))) | R9: =IF(M9="",INDEX('Chart of Accounts'!$A$5:$A$3000,MATCH("bank",'Chart of Accounts'!$F$5:$F$3000,0)),M9&"") | S9: =IF(N9="",INDEX('Chart of Accounts'!$A$5:$A$3000,MATCH("accrued_payroll",'Chart of Accounts'!$F$5:$F$3000,0)),N9&"") | T9: =IFERROR(INDEX('Chart of Accounts'!$C$5:$C$3000,MATCH(Q9&"",'Chart of Accounts'!$A$5:$A$3000,0))&"|"&INDEX('Chart of Accounts'!$D$5:$D$3000,MATCH(Q9&"",'Chart of Accounts'!$A$5:$A$3000,0)),"") | U9: =IFERROR(INDEX('Chart of Accounts'!$C$5:$C$3000,MATCH(R9&"",'Chart of Accounts'!$A$5:$A$3000,0))&"|"&INDEX('Chart of Accounts'!$D$5:$D$3000,MATCH(R9&"",'Chart of Accounts'!$A$5:$A$3000,0)),"") | V9: =IFERROR(INDEX('Chart of Accounts'!$C$5:$C$3000,MATCH(S9&"",'Chart of Accounts'!$A$5:$A$3000,0))&"|"&INDEX('Chart of Accounts'!$D$5:$D$3000,MATCH(S9&"",'Chart of Accounts'!$A$5:$A$3000,0)),"") | W9: =IF(LEFT(T9,8)="Revenue|",-N(O9),0)+IF(LEFT(U9,8)="Revenue|",N(K9),0)+IF(LEFT(V9,8)="Revenue|",N(P9),0) | X9: =IF(LEFT(T9,5)="COGS|",N(O9),0)+IF(LEFT(U9,5)="COGS|",-N(K9),0)+IF(LEFT(V9,5)="COGS|",-N(P9),0) | Y9: =IF(LEFT(T9,8)="Expense|",N(O9),0)+IF(LEFT(U9,8)="Expense|",-N(K9),0)+IF(LEFT(V9,8)="Expense|",-N(P9),0) | Z9: =IF(ISNUMBER(MATCH(T9,{"Expense|employee","Expense|general_admin","Expense|marketing","Expense|utilities","Expense|other_operating"},0)),N(O9),0)+IF(ISNUMBER(MATCH(U9,{"Expense|employee","Expense|general_admin","Expense|marketing","Expense|utilities","Expense|other_operating"},0)),-N(K9),0)+IF(ISNUMBER(MATCH(V9,{"Expense|employee","Expense|general_admin","Expense|marketing","Expense|utilities","Expense|other_operating"},0)),-N(P9),0) | AA9: =IF(T9="Liability|payable",-N(O9),0)+IF(U9="Liability|payable",N(K9),0)+IF(V9="Liability|payable",N(P9),0) | AB9: =IF(T9="Liability|accrued",-N(O9),0)+IF(U9="Liability|accrued",N(K9),0)+IF(V9="Liability|accrued",N(P9),0) | AC9: =IF(AND(N(O9)<>0,T9=""),1,0)+IF(AND(N(K9)<>0,U9=""),1,0)+IF(AND(N(P9)<>0,V9=""),1,0)
O10: =ROUND(N(I10)*N(J10),2) | P10: =O10-N(K10) | Q10: =IF(F10<>"",F10&"",IF(LEFT(E10,6)="Indire",INDEX('Chart of Accounts'!$A$5:$A$3000,MATCH("project_overhead",'Chart of Accounts'!$F$5:$F$3000,0)),IF(LEFT(E10,6)="Admini",INDEX('Chart of Accounts'!$A$5:$A$3000,MATCH("admin_salaries",'Chart of Accounts'!$F$5:$F$3000,0)),INDEX('Chart of Accounts'!$A$5:$A$3000,MATCH("direct_labour",'Chart of Accounts'!$F$5:$F$3000,0))))) | R10: =IF(M10="",INDEX('Chart of Accounts'!$A$5:$A$3000,MATCH("bank",'Chart of Accounts'!$F$5:$F$3000,0)),M10&"") | S10: =IF(N10="",INDEX('Chart of Accounts'!$A$5:$A$3000,MATCH("accrued_payroll",'Chart of Accounts'!$F$5:$F$3000,0)),N10&"") | T10: =IFERROR(INDEX('Chart of Accounts'!$C$5:$C$3000,MATCH(Q10&"",'Chart of Accounts'!$A$5:$A$3000,0))&"|"&INDEX('Chart of Accounts'!$D$5:$D$3000,MATCH(Q10&"",'Chart of Accounts'!$A$5:$A$3000,0)),"") | U10: =IFERROR(INDEX('Chart of Accounts'!$C$5:$C$3000,MATCH(R10&"",'Chart of Accounts'!$A$5:$A$3000,0))&"|"&INDEX('Chart of Accounts'!$D$5:$D$3000,MATCH(R10&"",'Chart of Accounts'!$A$5:$A$3000,0)),"") | V10: =IFERROR(INDEX('Chart of Accounts'!$C$5:$C$3000,MATCH(S10&"",'Chart of Accounts'!$A$5:$A$3000,0))&"|"&INDEX('Chart of Accounts'!$D$5:$D$3000,MATCH(S10&"",'Chart of Accounts'!$A$5:$A$3000,0)),"") | W10: =IF(LEFT(T10,8)="Revenue|",-N(O10),0)+IF(LEFT(U10,8)="Revenue|",N(K10),0)+IF(LEFT(V10,8)="Revenue|",N(P10),0) | X10: =IF(LEFT(T10,5)="COGS|",N(O10),0)+IF(LEFT(U10,5)="COGS|",-N(K10),0)+IF(LEFT(V10,5)="COGS|",-N(P10),0) | Y10: =IF(LEFT(T10,8)="Expense|",N(O10),0)+IF(LEFT(U10,8)="Expense|",-N(K10),0)+IF(LEFT(V10,8)="Expense|",-N(P10),0) | Z10: =IF(ISNUMBER(MATCH(T10,{"Expense|employee","Expense|general_admin","Expense|marketing","Expense|utilities","Expense|other_operating"},0)),N(O10),0)+IF(ISNUMBER(MATCH(U10,{"Expense|employee","Expense|general_admin","Expense|marketing","Expense|utilities","Expense|other_operating"},0)),-N(K10),0)+IF(ISNUMBER(MATCH(V10,{"Expense|employee","Expense|general_admin","Expense|marketing","Expense|utilities","Expense|other_operating"},0)),-N(P10),0) | AA10: =IF(T10="Liability|payable",-N(O10),0)+IF(U10="Liability|payable",N(K10),0)+IF(V10="Liability|payable",N(P10),0) | AB10: =IF(T10="Liability|accrued",-N(O10),0)+IF(U10="Liability|accrued",N(K10),0)+IF(V10="Liability|accrued",N(P10),0) | AC10: =IF(AND(N(O10)<>0,T10=""),1,0)+IF(AND(N(K10)<>0,U10=""),1,0)+IF(AND(N(P10)<>0,V10=""),1,0)
O11: =ROUND(N(I11)*N(J11),2) | P11: =O11-N(K11) | Q11: =IF(F11<>"",F11&"",IF(LEFT(E11,6)="Indire",INDEX('Chart of Accounts'!$A$5:$A$3000,MATCH("project_overhead",'Chart of Accounts'!$F$5:$F$3000,0)),IF(LEFT(E11,6)="Admini",INDEX('Chart of Accounts'!$A$5:$A$3000,MATCH("admin_salaries",'Chart of Accounts'!$F$5:$F$3000,0)),INDEX('Chart of Accounts'!$A$5:$A$3000,MATCH("direct_labour",'Chart of Accounts'!$F$5:$F$3000,0))))) | R11: =IF(M11="",INDEX('Chart of Accounts'!$A$5:$A$3000,MATCH("bank",'Chart of Accounts'!$F$5:$F$3000,0)),M11&"") | S11: =IF(N11="",INDEX('Chart of Accounts'!$A$5:$A$3000,MATCH("accrued_payroll",'Chart of Accounts'!$F$5:$F$3000,0)),N11&"") | T11: =IFERROR(INDEX('Chart of Accounts'!$C$5:$C$3000,MATCH(Q11&"",'Chart of Accounts'!$A$5:$A$3000,0))&"|"&INDEX('Chart of Accounts'!$D$5:$D$3000,MATCH(Q11&"",'Chart of Accounts'!$A$5:$A$3000,0)),"") | U11: =IFERROR(INDEX('Chart of Accounts'!$C$5:$C$3000,MATCH(R11&"",'Chart of Accounts'!$A$5:$A$3000,0))&"|"&INDEX('Chart of Accounts'!$D$5:$D$3000,MATCH(R11&"",'Chart of Accounts'!$A$5:$A$3000,0)),"") | V11: =IFERROR(INDEX('Chart of Accounts'!$C$5:$C$3000,MATCH(S11&"",'Chart of Accounts'!$A$5:$A$3000,0))&"|"&INDEX('Chart of Accounts'!$D$5:$D$3000,MATCH(S11&"",'Chart of Accounts'!$A$5:$A$3000,0)),"") | W11: =IF(LEFT(T11,8)="Revenue|",-N(O11),0)+IF(LEFT(U11,8)="Revenue|",N(K11),0)+IF(LEFT(V11,8)="Revenue|",N(P11),0) | X11: =IF(LEFT(T11,5)="COGS|",N(O11),0)+IF(LEFT(U11,5)="COGS|",-N(K11),0)+IF(LEFT(V11,5)="COGS|",-N(P11),0) | Y11: =IF(LEFT(T11,8)="Expense|",N(O11),0)+IF(LEFT(U11,8)="Expense|",-N(K11),0)+IF(LEFT(V11,8)="Expense|",-N(P11),0) | Z11: =IF(ISNUMBER(MATCH(T11,{"Expense|employee","Expense|general_admin","Expense|marketing","Expense|utilities","Expense|other_operating"},0)),N(O11),0)+IF(ISNUMBER(MATCH(U11,{"Expense|employee","Expense|general_admin","Expense|marketing","Expense|utilities","Expense|other_operating"},0)),-N(K11),0)+IF(ISNUMBER(MATCH(V11,{"Expense|employee","Expense|general_admin","Expense|marketing","Expense|utilities","Expense|other_operating"},0)),-N(P11),0) | AA11: =IF(T11="Liability|payable",-N(O11),0)+IF(U11="Liability|payable",N(K11),0)+IF(V11="Liability|payable",N(P11),0) | AB11: =IF(T11="Liability|accrued",-N(O11),0)+IF(U11="Liability|accrued",N(K11),0)+IF(V11="Liability|accrued",N(P11),0) | AC11: =IF(AND(N(O11)<>0,T11=""),1,0)+IF(AND(N(K11)<>0,U11=""),1,0)+IF(AND(N(P11)<>0,V11=""),1,0)
O12: =ROUND(N(I12)*N(J12),2) | P12: =O12-N(K12) | Q12: =IF(F12<>"",F12&"",IF(LEFT(E12,6)="Indire",INDEX('Chart of Accounts'!$A$5:$A$3000,MATCH("project_overhead",'Chart of Accounts'!$F$5:$F$3000,0)),IF(LEFT(E12,6)="Admini",INDEX('Chart of Accounts'!$A$5:$A$3000,MATCH("admin_salaries",'Chart of Accounts'!$F$5:$F$3000,0)),INDEX('Chart of Accounts'!$A$5:$A$3000,MATCH("direct_labour",'Chart of Accounts'!$F$5:$F$3000,0))))) | R12: =IF(M12="",INDEX('Chart of Accounts'!$A$5:$A$3000,MATCH("bank",'Chart of Accounts'!$F$5:$F$3000,0)),M12&"") | S12: =IF(N12="",INDEX('Chart of Accounts'!$A$5:$A$3000,MATCH("accrued_payroll",'Chart of Accounts'!$F$5:$F$3000,0)),N12&"") | T12: =IFERROR(INDEX('Chart of Accounts'!$C$5:$C$3000,MATCH(Q12&"",'Chart of Accounts'!$A$5:$A$3000,0))&"|"&INDEX('Chart of Accounts'!$D$5:$D$3000,MATCH(Q12&"",'Chart of Accounts'!$A$5:$A$3000,0)),"") | U12: =IFERROR(INDEX('Chart of Accounts'!$C$5:$C$3000,MATCH(R12&"",'Chart of Accounts'!$A$5:$A$3000,0))&"|"&INDEX('Chart of Accounts'!$D$5:$D$3000,MATCH(R12&"",'Chart of Accounts'!$A$5:$A$3000,0)),"") | V12: =IFERROR(INDEX('Chart of Accounts'!$C$5:$C$3000,MATCH(S12&"",'Chart of Accounts'!$A$5:$A$3000,0))&"|"&INDEX('Chart of Accounts'!$D$5:$D$3000,MATCH(S12&"",'Chart of Accounts'!$A$5:$A$3000,0)),"") | W12: =IF(LEFT(T12,8)="Revenue|",-N(O12),0)+IF(LEFT(U12,8)="Revenue|",N(K12),0)+IF(LEFT(V12,8)="Revenue|",N(P12),0) | X12: =IF(LEFT(T12,5)="COGS|",N(O12),0)+IF(LEFT(U12,5)="COGS|",-N(K12),0)+IF(LEFT(V12,5)="COGS|",-N(P12),0) | Y12: =IF(LEFT(T12,8)="Expense|",N(O12),0)+IF(LEFT(U12,8)="Expense|",-N(K12),0)+IF(LEFT(V12,8)="Expense|",-N(P12),0) | Z12: =IF(ISNUMBER(MATCH(T12,{"Expense|employee","Expense|general_admin","Expense|marketing","Expense|utilities","Expense|other_operating"},0)),N(O12),0)+IF(ISNUMBER(MATCH(U12,{"Expense|employee","Expense|general_admin","Expense|marketing","Expense|utilities","Expense|other_operating"},0)),-N(K12),0)+IF(ISNUMBER(MATCH(V12,{"Expense|employee","Expense|general_admin","Expense|marketing","Expense|utilities","Expense|other_operating"},0)),-N(P12),0) | AA12: =IF(T12="Liability|payable",-N(O12),0)+IF(U12="Liability|payable",N(K12),0)+IF(V12="Liability|payable",N(P12),0) | AB12: =IF(T12="Liability|accrued",-N(O12),0)+IF(U12="Liability|accrued",N(K12),0)+IF(V12="Liability|accrued",N(P12),0) | AC12: =IF(AND(N(O12)<>0,T12=""),1,0)+IF(AND(N(K12)<>0,U12=""),1,0)+IF(AND(N(P12)<>0,V12=""),1,0)
O13: =ROUND(N(I13)*N(J13),2) | P13: =O13-N(K13) | Q13: =IF(F13<>"",F13&"",IF(LEFT(E13,6)="Indire",INDEX('Chart of Accounts'!$A$5:$A$3000,MATCH("project_overhead",'Chart of Accounts'!$F$5:$F$3000,0)),IF(LEFT(E13,6)="Admini",INDEX('Chart of Accounts'!$A$5:$A$3000,MATCH("admin_salaries",'Chart of Accounts'!$F$5:$F$3000,0)),INDEX('Chart of Accounts'!$A$5:$A$3000,MATCH("direct_labour",'Chart of Accounts'!$F$5:$F$3000,0))))) | R13: =IF(M13="",INDEX('Chart of Accounts'!$A$5:$A$3000,MATCH("bank",'Chart of Accounts'!$F$5:$F$3000,0)),M13&"") | S13: =IF(N13="",INDEX('Chart of Accounts'!$A$5:$A$3000,MATCH("accrued_payroll",'Chart of Accounts'!$F$5:$F$3000,0)),N13&"") | T13: =IFERROR(INDEX('Chart of Accounts'!$C$5:$C$3000,MATCH(Q13&"",'Chart of Accounts'!$A$5:$A$3000,0))&"|"&INDEX('Chart of Accounts'!$D$5:$D$3000,MATCH(Q13&"",'Chart of Accounts'!$A$5:$A$3000,0)),"") | U13: =IFERROR(INDEX('Chart of Accounts'!$C$5:$C$3000,MATCH(R13&"",'Chart of Accounts'!$A$5:$A$3000,0))&"|"&INDEX('Chart of Accounts'!$D$5:$D$3000,MATCH(R13&"",'Chart of Accounts'!$A$5:$A$3000,0)),"") | V13: =IFERROR(INDEX('Chart of Accounts'!$C$5:$C$3000,MATCH(S13&"",'Chart of Accounts'!$A$5:$A$3000,0))&"|"&INDEX('Chart of Accounts'!$D$5:$D$3000,MATCH(S13&"",'Chart of Accounts'!$A$5:$A$3000,0)),"") | W13: =IF(LEFT(T13,8)="Revenue|",-N(O13),0)+IF(LEFT(U13,8)="Revenue|",N(K13),0)+IF(LEFT(V13,8)="Revenue|",N(P13),0) | X13: =IF(LEFT(T13,5)="COGS|",N(O13),0)+IF(LEFT(U13,5)="COGS|",-N(K13),0)+IF(LEFT(V13,5)="COGS|",-N(P13),0) | Y13: =IF(LEFT(T13,8)="Expense|",N(O13),0)+IF(LEFT(U13,8)="Expense|",-N(K13),0)+IF(LEFT(V13,8)="Expense|",-N(P13),0) | Z13: =IF(ISNUMBER(MATCH(T13,{"Expense|employee","Expense|general_admin","Expense|marketing","Expense|utilities","Expense|other_operating"},0)),N(O13),0)+IF(ISNUMBER(MATCH(U13,{"Expense|employee","Expense|general_admin","Expense|marketing","Expense|utilities","Expense|other_operating"},0)),-N(K13),0)+IF(ISNUMBER(MATCH(V13,{"Expense|employee","Expense|general_admin","Expense|marketing","Expense|utilities","Expense|other_operating"},0)),-N(P13),0) | AA13: =IF(T13="Liability|payable",-N(O13),0)+IF(U13="Liability|payable",N(K13),0)+IF(V13="Liability|payable",N(P13),0) | AB13: =IF(T13="Liability|accrued",-N(O13),0)+IF(U13="Liability|accrued",N(K13),0)+IF(V13="Liability|accrued",N(P13),0) | AC13: =IF(AND(N(O13)<>0,T13=""),1,0)+IF(AND(N(K13)<>0,U13=""),1,0)+IF(AND(N(P13)<>0,V13=""),1,0)
O14: =ROUND(N(I14)*N(J14),2) | P14: =O14-N(K14) | Q14: =IF(F14<>"",F14&"",IF(LEFT(E14,6)="Indire",INDEX('Chart of Accounts'!$A$5:$A$3000,MATCH("project_overhead",'Chart of Accounts'!$F$5:$F$3000,0)),IF(LEFT(E14,6)="Admini",INDEX('Chart of Accounts'!$A$5:$A$3000,MATCH("admin_salaries",'Chart of Accounts'!$F$5:$F$3000,0)),INDEX('Chart of Accounts'!$A$5:$A$3000,MATCH("direct_labour",'Chart of Accounts'!$F$5:$F$3000,0))))) | R14: =IF(M14="",INDEX('Chart of Accounts'!$A$5:$A$3000,MATCH("bank",'Chart of Accounts'!$F$5:$F$3000,0)),M14&"") | S14: =IF(N14="",INDEX('Chart of Accounts'!$A$5:$A$3000,MATCH("accrued_payroll",'Chart of Accounts'!$F$5:$F$3000,0)),N14&"") | T14: =IFERROR(INDEX('Chart of Accounts'!$C$5:$C$3000,MATCH(Q14&"",'Chart of Accounts'!$A$5:$A$3000,0))&"|"&INDEX('Chart of Accounts'!$D$5:$D$3000,MATCH(Q14&"",'Chart of Accounts'!$A$5:$A$3000,0)),"") | U14: =IFERROR(INDEX('Chart of Accounts'!$C$5:$C$3000,MATCH(R14&"",'Chart of Accounts'!$A$5:$A$3000,0))&"|"&INDEX('Chart of Accounts'!$D$5:$D$3000,MATCH(R14&"",'Chart of Accounts'!$A$5:$A$3000,0)),"") | V14: =IFERROR(INDEX('Chart of Accounts'!$C$5:$C$3000,MATCH(S14&"",'Chart of Accounts'!$A$5:$A$3000,0))&"|"&INDEX('Chart of Accounts'!$D$5:$D$3000,MATCH(S14&"",'Chart of Accounts'!$A$5:$A$3000,0)),"") | W14: =IF(LEFT(T14,8)="Revenue|",-N(O14),0)+IF(LEFT(U14,8)="Revenue|",N(K14),0)+IF(LEFT(V14,8)="Revenue|",N(P14),0) | X14: =IF(LEFT(T14,5)="COGS|",N(O14),0)+IF(LEFT(U14,5)="COGS|",-N(K14),0)+IF(LEFT(V14,5)="COGS|",-N(P14),0) | Y14: =IF(LEFT(T14,8)="Expense|",N(O14),0)+IF(LEFT(U14,8)="Expense|",-N(K14),0)+IF(LEFT(V14,8)="Expense|",-N(P14),0) | Z14: =IF(ISNUMBER(MATCH(T14,{"Expense|employee","Expense|general_admin","Expense|marketing","Expense|utilities","Expense|other_operating"},0)),N(O14),0)+IF(ISNUMBER(MATCH(U14,{"Expense|employee","Expense|general_admin","Expense|marketing","Expense|utilities","Expense|other_operating"},0)),-N(K14),0)+IF(ISNUMBER(MATCH(V14,{"Expense|employee","Expense|general_admin","Expense|marketing","Expense|utilities","Expense|other_operating"},0)),-N(P14),0) | AA14: =IF(T14="Liability|payable",-N(O14),0)+IF(U14="Liability|payable",N(K14),0)+IF(V14="Liability|payable",N(P14),0) | AB14: =IF(T14="Liability|accrued",-N(O14),0)+IF(U14="Liability|accrued",N(K14),0)+IF(V14="Liability|accrued",N(P14),0) | AC14: =IF(AND(N(O14)<>0,T14=""),1,0)+IF(AND(N(K14)<>0,U14=""),1,0)+IF(AND(N(P14)<>0,V14=""),1,0)
O15: =ROUND(N(I15)*N(J15),2) | P15: =O15-N(K15) | Q15: =IF(F15<>"",F15&"",IF(LEFT(E15,6)="Indire",INDEX('Chart of Accounts'!$A$5:$A$3000,MATCH("project_overhead",'Chart of Accounts'!$F$5:$F$3000,0)),IF(LEFT(E15,6)="Admini",INDEX('Chart of Accounts'!$A$5:$A$3000,MATCH("admin_salaries",'Chart of Accounts'!$F$5:$F$3000,0)),INDEX('Chart of Accounts'!$A$5:$A$3000,MATCH("direct_labour",'Chart of Accounts'!$F$5:$F$3000,0))))) | R15: =IF(M15="",INDEX('Chart of Accounts'!$A$5:$A$3000,MATCH("bank",'Chart of Accounts'!$F$5:$F$3000,0)),M15&"") | S15: =IF(N15="",INDEX('Chart of Accounts'!$A$5:$A$3000,MATCH("accrued_payroll",'Chart of Accounts'!$F$5:$F$3000,0)),N15&"") | T15: =IFERROR(INDEX('Chart of Accounts'!$C$5:$C$3000,MATCH(Q15&"",'Chart of Accounts'!$A$5:$A$3000,0))&"|"&INDEX('Chart of Accounts'!$D$5:$D$3000,MATCH(Q15&"",'Chart of Accounts'!$A$5:$A$3000,0)),"") | U15: =IFERROR(INDEX('Chart of Accounts'!$C$5:$C$3000,MATCH(R15&"",'Chart of Accounts'!$A$5:$A$3000,0))&"|"&INDEX('Chart of Accounts'!$D$5:$D$3000,MATCH(R15&"",'Chart of Accounts'!$A$5:$A$3000,0)),"") | V15: =IFERROR(INDEX('Chart of Accounts'!$C$5:$C$3000,MATCH(S15&"",'Chart of Accounts'!$A$5:$A$3000,0))&"|"&INDEX('Chart of Accounts'!$D$5:$D$3000,MATCH(S15&"",'Chart of Accounts'!$A$5:$A$3000,0)),"") | W15: =IF(LEFT(T15,8)="Revenue|",-N(O15),0)+IF(LEFT(U15,8)="Revenue|",N(K15),0)+IF(LEFT(V15,8)="Revenue|",N(P15),0) | X15: =IF(LEFT(T15,5)="COGS|",N(O15),0)+IF(LEFT(U15,5)="COGS|",-N(K15),0)+IF(LEFT(V15,5)="COGS|",-N(P15),0) | Y15: =IF(LEFT(T15,8)="Expense|",N(O15),0)+IF(LEFT(U15,8)="Expense|",-N(K15),0)+IF(LEFT(V15,8)="Expense|",-N(P15),0) | Z15: =IF(ISNUMBER(MATCH(T15,{"Expense|employee","Expense|general_admin","Expense|marketing","Expense|utilities","Expense|other_operating"},0)),N(O15),0)+IF(ISNUMBER(MATCH(U15,{"Expense|employee","Expense|general_admin","Expense|marketing","Expense|utilities","Expense|other_operating"},0)),-N(K15),0)+IF(ISNUMBER(MATCH(V15,{"Expense|employee","Expense|general_admin","Expense|marketing","Expense|utilities","Expense|other_operating"},0)),-N(P15),0) | AA15: =IF(T15="Liability|payable",-N(O15),0)+IF(U15="Liability|payable",N(K15),0)+IF(V15="Liability|payable",N(P15),0) | AB15: =IF(T15="Liability|accrued",-N(O15),0)+IF(U15="Liability|accrued",N(K15),0)+IF(V15="Liability|accrued",N(P15),0) | AC15: =IF(AND(N(O15)<>0,T15=""),1,0)+IF(AND(N(K15)<>0,U15=""),1,0)+IF(AND(N(P15)<>0,V15=""),1,0)
O16: =ROUND(N(I16)*N(J16),2) | P16: =O16-N(K16) | Q16: =IF(F16<>"",F16&"",IF(LEFT(E16,6)="Indire",INDEX('Chart of Accounts'!$A$5:$A$3000,MATCH("project_overhead",'Chart of Accounts'!$F$5:$F$3000,0)),IF(LEFT(E16,6)="Admini",INDEX('Chart of Accounts'!$A$5:$A$3000,MATCH("admin_salaries",'Chart of Accounts'!$F$5:$F$3000,0)),INDEX('Chart of Accounts'!$A$5:$A$3000,MATCH("direct_labour",'Chart of Accounts'!$F$5:$F$3000,0))))) | R16: =IF(M16="",INDEX('Chart of Accounts'!$A$5:$A$3000,MATCH("bank",'Chart of Accounts'!$F$5:$F$3000,0)),M16&"") | S16: =IF(N16="",INDEX('Chart of Accounts'!$A$5:$A$3000,MATCH("accrued_payroll",'Chart of Accounts'!$F$5:$F$3000,0)),N16&"") | T16: =IFERROR(INDEX('Chart of Accounts'!$C$5:$C$3000,MATCH(Q16&"",'Chart of Accounts'!$A$5:$A$3000,0))&"|"&INDEX('Chart of Accounts'!$D$5:$D$3000,MATCH(Q16&"",'Chart of Accounts'!$A$5:$A$3000,0)),"") | U16: =IFERROR(INDEX('Chart of Accounts'!$C$5:$C$3000,MATCH(R16&"",'Chart of Accounts'!$A$5:$A$3000,0))&"|"&INDEX('Chart of Accounts'!$D$5:$D$3000,MATCH(R16&"",'Chart of Accounts'!$A$5:$A$3000,0)),"") | V16: =IFERROR(INDEX('Chart of Accounts'!$C$5:$C$3000,MATCH(S16&"",'Chart of Accounts'!$A$5:$A$3000,0))&"|"&INDEX('Chart of Accounts'!$D$5:$D$3000,MATCH(S16&"",'Chart of Accounts'!$A$5:$A$3000,0)),"") | W16: =IF(LEFT(T16,8)="Revenue|",-N(O16),0)+IF(LEFT(U16,8)="Revenue|",N(K16),0)+IF(LEFT(V16,8)="Revenue|",N(P16),0) | X16: =IF(LEFT(T16,5)="COGS|",N(O16),0)+IF(LEFT(U16,5)="COGS|",-N(K16),0)+IF(LEFT(V16,5)="COGS|",-N(P16),0) | Y16: =IF(LEFT(T16,8)="Expense|",N(O16),0)+IF(LEFT(U16,8)="Expense|",-N(K16),0)+IF(LEFT(V16,8)="Expense|",-N(P16),0) | Z16: =IF(ISNUMBER(MATCH(T16,{"Expense|employee","Expense|general_admin","Expense|marketing","Expense|utilities","Expense|other_operating"},0)),N(O16),0)+IF(ISNUMBER(MATCH(U16,{"Expense|employee","Expense|general_admin","Expense|marketing","Expense|utilities","Expense|other_operating"},0)),-N(K16),0)+IF(ISNUMBER(MATCH(V16,{"Expense|employee","Expense|general_admin","Expense|marketing","Expense|utilities","Expense|other_operating"},0)),-N(P16),0) | AA16: =IF(T16="Liability|payable",-N(O16),0)+IF(U16="Liability|payable",N(K16),0)+IF(V16="Liability|payable",N(P16),0) | AB16: =IF(T16="Liability|accrued",-N(O16),0)+IF(U16="Liability|accrued",N(K16),0)+IF(V16="Liability|accrued",N(P16),0) | AC16: =IF(AND(N(O16)<>0,T16=""),1,0)+IF(AND(N(K16)<>0,U16=""),1,0)+IF(AND(N(P16)<>0,V16=""),1,0)
... O204: =ROUND(N(I204)*N(J204),2) | P204: =O204-N(K204) | Q204: =IF(F204<>"",F204&"",IF(LEFT(E204,6)="Indire",INDEX('Chart of Accounts'!$A$5:$A$3000,MATCH("project_overhead",'Chart of Accounts'!$F$5:$F$3000,0)),IF(LEFT(E204,6)="Admini",INDEX('Chart of Accounts'!$A$5:$A$3000,MATCH("admin_salaries",'Chart of Accounts'!$F$5:$F$3000,0)),INDEX('Chart of Accounts'!$A$5:$A$3000,MATCH("direct_labour",'Chart of Accounts'!$F$5:$F$3000,0))))) | R204: =IF(M204="",INDEX('Chart of Accounts'!$A$5:$A$3000,MATCH("bank",'Chart of Accounts'!$F$5:$F$3000,0)),M204&"") | S204: =IF(N204="",INDEX('Chart of Accounts'!$A$5:$A$3000,MATCH("accrued_payroll",'Chart of Accounts'!$F$5:$F$3000,0)),N204&"") | T204: =IFERROR(INDEX('Chart of Accounts'!$C$5:$C$3000,MATCH(Q204&"",'Chart of Accounts'!$A$5:$A$3000,0))&"|"&INDEX('Chart of Accounts'!$D$5:$D$3000,MATCH(Q204&"",'Chart of Accounts'!$A$5:$A$3000,0)),"") | U204: =IFERROR(INDEX('Chart of Accounts'!$C$5:$C$3000,MATCH(R204&"",'Chart of Accounts'!$A$5:$A$3000,0))&"|"&INDEX('Chart of Accounts'!$D$5:$D$3000,MATCH(R204&"",'Chart of Accounts'!$A$5:$A$3000,0)),"") | V204: =IFERROR(INDEX('Chart of Accounts'!$C$5:$C$3000,MATCH(S204&"",'Chart of Accounts'!$A$5:$A$3000,0))&"|"&INDEX('Chart of Accounts'!$D$5:$D$3000,MATCH(S204&"",'Chart of Accounts'!$A$5:$A$3000,0)),"") | W204: =IF(LEFT(T204,8)="Revenue|",-N(O204),0)+IF(LEFT(U204,8)="Revenue|",N(K204),0)+IF(LEFT(V204,8)="Revenue|",N(P204),0) | X204: =IF(LEFT(T204,5)="COGS|",N(O204),0)+IF(LEFT(U204,5)="COGS|",-N(K204),0)+IF(LEFT(V204,5)="COGS|",-N(P204),0) | Y204: =IF(LEFT(T204,8)="Expense|",N(O204),0)+IF(LEFT(U204,8)="Expense|",-N(K204),0)+IF(LEFT(V204,8)="Expense|",-N(P204),0) | Z204: =IF(ISNUMBER(MATCH(T204,{"Expense|employee","Expense|general_admin","Expense|marketing","Expense|utilities","Expense|other_operating"},0)),N(O204),0)+IF(ISNUMBER(MATCH(U204,{"Expense|employee","Expense|general_admin","Expense|marketing","Expense|utilities","Expense|other_operating"},0)),-N(K204),0)+IF(ISNUMBER(MATCH(V204,{"Expense|employee","Expense|general_admin","Expense|marketing","Expense|utilities","Expense|other_operating"},0)),-N(P204),0) | AA204: =IF(T204="Liability|payable",-N(O204),0)+IF(U204="Liability|payable",N(K204),0)+IF(V204="Liability|payable",N(P204),0) | AB204: =IF(T204="Liability|accrued",-N(O204),0)+IF(U204="Liability|accrued",N(K204),0)+IF(V204="Liability|accrued",N(P204),0) | AC204: =IF(AND(N(O204)<>0,T204=""),1,0)+IF(AND(N(K204)<>0,U204=""),1,0)+IF(AND(N(P204)<>0,V204=""),1,0)

Sheet Receipt Vouchers
A1: BEYOND DESIGN | RECEIPT VOUCHERS
A2: Money received from clients. Credit Account: revenue (cash basis), receivables (against an invoice) or client advances
A3: e.g. 2026-10-05 | B3: PRJ-2026-004 | C3: RV-001 | D3: Advance payment | F3: 100000 | G3: Bank Transfer | I3: 2100
A4: Date | B4: Business Unit | C4: Receipt No. | D4: Description | E4: Received From | F4: Amount | G4: Payment Method | H4: Received Into | I4: Credit Account | J4: Tax Withheld by Client | K4: VAT Code (cash revenue) | L4: Gross | M4: Output VAT | N4: Net Credit | O4: received_into (effective) | P4: credit_account (effective) | Q4: wht_receivable account | R4: vat_output account | S4: leg 1 type | T4: leg 2 type | U4: leg 3 type | V4: leg 4 type | W4: revenue | X4: cost of sales | Y4: expenses | Z4: operating expenses | AA4: payables | AB4: accruals | AC4: unknown account
L5: =N(F5)+N(J5) | M5: =IF(K5="",0,L5-ROUND(L5/(1+IFERROR(VLOOKUP(K5,'Tax Codes'!$A$5:$E$300,5,FALSE),0)),2)) | N5: =L5-M5 | O5: =IF(H5="",INDEX('Chart of Accounts'!$A$5:$A$3000,MATCH("bank",'Chart of Accounts'!$F$5:$F$3000,0)),H5&"") | P5: =IF(I5="",INDEX('Chart of Accounts'!$A$5:$A$3000,MATCH("revenue",'Chart of Accounts'!$F$5:$F$3000,0)),I5&"") | Q5: =INDEX('Chart of Accounts'!$A$5:$A$3000,MATCH("wht_receivable",'Chart of Accounts'!$F$5:$F$3000,0)) | R5: =INDEX('Chart of Accounts'!$A$5:$A$3000,MATCH("vat_output",'Chart of Accounts'!$F$5:$F$3000,0)) | S5: =IFERROR(INDEX('Chart of Accounts'!$C$5:$C$3000,MATCH(O5&"",'Chart of Accounts'!$A$5:$A$3000,0))&"|"&INDEX('Chart of Accounts'!$D$5:$D$3000,MATCH(O5&"",'Chart of Accounts'!$A$5:$A$3000,0)),"") | T5: =IFERROR(INDEX('Chart of Accounts'!$C$5:$C$3000,MATCH(Q5&"",'Chart of Accounts'!$A$5:$A$3000,0))&"|"&INDEX('Chart of Accounts'!$D$5:$D$3000,MATCH(Q5&"",'Chart of Accounts'!$A$5:$A$3000,0)),"") | U5: =IFERROR(INDEX('Chart of Accounts'!$C$5:$C$3000,MATCH(P5&"",'Chart of Accounts'!$A$5:$A$3000,0))&"|"&INDEX('Chart of Accounts'!$D$5:$D$3000,MATCH(P5&"",'Chart of Accounts'!$A$5:$A$3000,0)),"") | V5: =IFERROR(INDEX('Chart of Accounts'!$C$5:$C$3000,MATCH(R5&"",'Chart of Accounts'!$A$5:$A$3000,0))&"|"&INDEX('Chart of Accounts'!$D$5:$D$3000,MATCH(R5&"",'Chart of Accounts'!$A$5:$A$3000,0)),"") | W5: =IF(LEFT(S5,8)="Revenue|",-N(F5),0)+IF(LEFT(T5,8)="Revenue|",-N(J5),0)+IF(LEFT(U5,8)="Revenue|",N(N5),0)+IF(LEFT(V5,8)="Revenue|",N(M5),0) | X5: =IF(LEFT(S5,5)="COGS|",N(F5),0)+IF(LEFT(T5,5)="COGS|",N(J5),0)+IF(LEFT(U5,5)="COGS|",-N(N5),0)+IF(LEFT(V5,5)="COGS|",-N(M5),0) | Y5: =IF(LEFT(S5,8)="Expense|",N(F5),0)+IF(LEFT(T5,8)="Expense|",N(J5),0)+IF(LEFT(U5,8)="Expense|",-N(N5),0)+IF(LEFT(V5,8)="Expense|",-N(M5),0) | Z5: =IF(ISNUMBER(MATCH(S5,{"Expense|employee","Expense|general_admin","Expense|marketing","Expense|utilities","Expense|other_operating"},0)),N(F5),0)+IF(ISNUMBER(MATCH(T5,{"Expense|employee","Expense|general_admin","Expense|marketing","Expense|utilities","Expense|other_operating"},0)),N(J5),0)+IF(ISNUMBER(MATCH(U5,{"Expense|employee","Expense|general_admin","Expense|marketing","Expense|utilities","Expense|other_operating"},0)),-N(N5),0)+IF(ISNUMBER(MATCH(V5,{"Expense|employee","Expense|general_admin","Expense|marketing","Expense|utilities","Expense|other_operating"},0)),-N(M5),0) | AA5: =IF(S5="Liability|payable",-N(F5),0)+IF(T5="Liability|payable",-N(J5),0)+IF(U5="Liability|payable",N(N5),0)+IF(V5="Liability|payable",N(M5),0) | AB5: =IF(S5="Liability|accrued",-N(F5),0)+IF(T5="Liability|accrued",-N(J5),0)+IF(U5="Liability|accrued",N(N5),0)+IF(V5="Liability|accrued",N(M5),0) | AC5: =IF(AND(N(F5)<>0,S5=""),1,0)+IF(AND(N(J5)<>0,T5=""),1,0)+IF(AND(N(N5)<>0,U5=""),1,0)+IF(AND(N(M5)<>0,V5=""),1,0)
L6: =N(F6)+N(J6) | M6: =IF(K6="",0,L6-ROUND(L6/(1+IFERROR(VLOOKUP(K6,'Tax Codes'!$A$5:$E$300,5,FALSE),0)),2)) | N6: =L6-M6 | O6: =IF(H6="",INDEX('Chart of Accounts'!$A$5:$A$3000,MATCH("bank",'Chart of Accounts'!$F$5:$F$3000,0)),H6&"") | P6: =IF(I6="",INDEX('Chart of Accounts'!$A$5:$A$3000,MATCH("revenue",'Chart of Accounts'!$F$5:$F$3000,0)),I6&"") | Q6: =INDEX('Chart of Accounts'!$A$5:$A$3000,MATCH("wht_receivable",'Chart of Accounts'!$F$5:$F$3000,0)) | R6: =INDEX('Chart of Accounts'!$A$5:$A$3000,MATCH("vat_output",'Chart of Accounts'!$F$5:$F$3000,0)) | S6: =IFERROR(INDEX('Chart of Accounts'!$C$5:$C$3000,MATCH(O6&"",'Chart of Accounts'!$A$5:$A$3000,0))&"|"&INDEX('Chart of Accounts'!$D$5:$D$3000,MATCH(O6&"",'Chart of Accounts'!$A$5:$A$3000,0)),"") | T6: =IFERROR(INDEX('Chart of Accounts'!$C$5:$C$3000,MATCH(Q6&"",'Chart of Accounts'!$A$5:$A$3000,0))&"|"&INDEX('Chart of Accounts'!$D$5:$D$3000,MATCH(Q6&"",'Chart of Accounts'!$A$5:$A$3000,0)),"") | U6: =IFERROR(INDEX('Chart of Accounts'!$C$5:$C$3000,MATCH(P6&"",'Chart of Accounts'!$A$5:$A$3000,0))&"|"&INDEX('Chart of Accounts'!$D$5:$D$3000,MATCH(P6&"",'Chart of Accounts'!$A$5:$A$3000,0)),"") | V6: =IFERROR(INDEX('Chart of Accounts'!$C$5:$C$3000,MATCH(R6&"",'Chart of Accounts'!$A$5:$A$3000,0))&"|"&INDEX('Chart of Accounts'!$D$5:$D$3000,MATCH(R6&"",'Chart of Accounts'!$A$5:$A$3000,0)),"") | W6: =IF(LEFT(S6,8)="Revenue|",-N(F6),0)+IF(LEFT(T6,8)="Revenue|",-N(J6),0)+IF(LEFT(U6,8)="Revenue|",N(N6),0)+IF(LEFT(V6,8)="Revenue|",N(M6),0) | X6: =IF(LEFT(S6,5)="COGS|",N(F6),0)+IF(LEFT(T6,5)="COGS|",N(J6),0)+IF(LEFT(U6,5)="COGS|",-N(N6),0)+IF(LEFT(V6,5)="COGS|",-N(M6),0) | Y6: =IF(LEFT(S6,8)="Expense|",N(F6),0)+IF(LEFT(T6,8)="Expense|",N(J6),0)+IF(LEFT(U6,8)="Expense|",-N(N6),0)+IF(LEFT(V6,8)="Expense|",-N(M6),0) | Z6: =IF(ISNUMBER(MATCH(S6,{"Expense|employee","Expense|general_admin","Expense|marketing","Expense|utilities","Expense|other_operating"},0)),N(F6),0)+IF(ISNUMBER(MATCH(T6,{"Expense|employee","Expense|general_admin","Expense|marketing","Expense|utilities","Expense|other_operating"},0)),N(J6),0)+IF(ISNUMBER(MATCH(U6,{"Expense|employee","Expense|general_admin","Expense|marketing","Expense|utilities","Expense|other_operating"},0)),-N(N6),0)+IF(ISNUMBER(MATCH(V6,{"Expense|employee","Expense|general_admin","Expense|marketing","Expense|utilities","Expense|other_operating"},0)),-N(M6),0) | AA6: =IF(S6="Liability|payable",-N(F6),0)+IF(T6="Liability|payable",-N(J6),0)+IF(U6="Liability|payable",N(N6),0)+IF(V6="Liability|payable",N(M6),0) | AB6: =IF(S6="Liability|accrued",-N(F6),0)+IF(T6="Liability|accrued",-N(J6),0)+IF(U6="Liability|accrued",N(N6),0)+IF(V6="Liability|accrued",N(M6),0) | AC6: =IF(AND(N(F6)<>0,S6=""),1,0)+IF(AND(N(J6)<>0,T6=""),1,0)+IF(AND(N(N6)<>0,U6=""),1,0)+IF(AND(N(M6)<>0,V6=""),1,0)
L7: =N(F7)+N(J7) | M7: =IF(K7="",0,L7-ROUND(L7/(1+IFERROR(VLOOKUP(K7,'Tax Codes'!$A$5:$E$300,5,FALSE),0)),2)) | N7: =L7-M7 | O7: =IF(H7="",INDEX('Chart of Accounts'!$A$5:$A$3000,MATCH("bank",'Chart of Accounts'!$F$5:$F$3000,0)),H7&"") | P7: =IF(I7="",INDEX('Chart of Accounts'!$A$5:$A$3000,MATCH("revenue",'Chart of Accounts'!$F$5:$F$3000,0)),I7&"") | Q7: =INDEX('Chart of Accounts'!$A$5:$A$3000,MATCH("wht_receivable",'Chart of Accounts'!$F$5:$F$3000,0)) | R7: =INDEX('Chart of Accounts'!$A$5:$A$3000,MATCH("vat_output",'Chart of Accounts'!$F$5:$F$3000,0)) | S7: =IFERROR(INDEX('Chart of Accounts'!$C$5:$C$3000,MATCH(O7&"",'Chart of Accounts'!$A$5:$A$3000,0))&"|"&INDEX('Chart of Accounts'!$D$5:$D$3000,MATCH(O7&"",'Chart of Accounts'!$A$5:$A$3000,0)),"") | T7: =IFERROR(INDEX('Chart of Accounts'!$C$5:$C$3000,MATCH(Q7&"",'Chart of Accounts'!$A$5:$A$3000,0))&"|"&INDEX('Chart of Accounts'!$D$5:$D$3000,MATCH(Q7&"",'Chart of Accounts'!$A$5:$A$3000,0)),"") | U7: =IFERROR(INDEX('Chart of Accounts'!$C$5:$C$3000,MATCH(P7&"",'Chart of Accounts'!$A$5:$A$3000,0))&"|"&INDEX('Chart of Accounts'!$D$5:$D$3000,MATCH(P7&"",'Chart of Accounts'!$A$5:$A$3000,0)),"") | V7: =IFERROR(INDEX('Chart of Accounts'!$C$5:$C$3000,MATCH(R7&"",'Chart of Accounts'!$A$5:$A$3000,0))&"|"&INDEX('Chart of Accounts'!$D$5:$D$3000,MATCH(R7&"",'Chart of Accounts'!$A$5:$A$3000,0)),"") | W7: =IF(LEFT(S7,8)="Revenue|",-N(F7),0)+IF(LEFT(T7,8)="Revenue|",-N(J7),0)+IF(LEFT(U7,8)="Revenue|",N(N7),0)+IF(LEFT(V7,8)="Revenue|",N(M7),0) | X7: =IF(LEFT(S7,5)="COGS|",N(F7),0)+IF(LEFT(T7,5)="COGS|",N(J7),0)+IF(LEFT(U7,5)="COGS|",-N(N7),0)+IF(LEFT(V7,5)="COGS|",-N(M7),0) | Y7: =IF(LEFT(S7,8)="Expense|",N(F7),0)+IF(LEFT(T7,8)="Expense|",N(J7),0)+IF(LEFT(U7,8)="Expense|",-N(N7),0)+IF(LEFT(V7,8)="Expense|",-N(M7),0) | Z7: =IF(ISNUMBER(MATCH(S7,{"Expense|employee","Expense|general_admin","Expense|marketing","Expense|utilities","Expense|other_operating"},0)),N(F7),0)+IF(ISNUMBER(MATCH(T7,{"Expense|employee","Expense|general_admin","Expense|marketing","Expense|utilities","Expense|other_operating"},0)),N(J7),0)+IF(ISNUMBER(MATCH(U7,{"Expense|employee","Expense|general_admin","Expense|marketing","Expense|utilities","Expense|other_operating"},0)),-N(N7),0)+IF(ISNUMBER(MATCH(V7,{"Expense|employee","Expense|general_admin","Expense|marketing","Expense|utilities","Expense|other_operating"},0)),-N(M7),0) | AA7: =IF(S7="Liability|payable",-N(F7),0)+IF(T7="Liability|payable",-N(J7),0)+IF(U7="Liability|payable",N(N7),0)+IF(V7="Liability|payable",N(M7),0) | AB7: =IF(S7="Liability|accrued",-N(F7),0)+IF(T7="Liability|accrued",-N(J7),0)+IF(U7="Liability|accrued",N(N7),0)+IF(V7="Liability|accrued",N(M7),0) | AC7: =IF(AND(N(F7)<>0,S7=""),1,0)+IF(AND(N(J7)<>0,T7=""),1,0)+IF(AND(N(N7)<>0,U7=""),1,0)+IF(AND(N(M7)<>0,V7=""),1,0)
L8: =N(F8)+N(J8) | M8: =IF(K8="",0,L8-ROUND(L8/(1+IFERROR(VLOOKUP(K8,'Tax Codes'!$A$5:$E$300,5,FALSE),0)),2)) | N8: =L8-M8 | O8: =IF(H8="",INDEX('Chart of Accounts'!$A$5:$A$3000,MATCH("bank",'Chart of Accounts'!$F$5:$F$3000,0)),H8&"") | P8: =IF(I8="",INDEX('Chart of Accounts'!$A$5:$A$3000,MATCH("revenue",'Chart of Accounts'!$F$5:$F$3000,0)),I8&"") | Q8: =INDEX('Chart of Accounts'!$A$5:$A$3000,MATCH("wht_receivable",'Chart of Accounts'!$F$5:$F$3000,0)) | R8: =INDEX('Chart of Accounts'!$A$5:$A$3000,MATCH("vat_output",'Chart of Accounts'!$F$5:$F$3000,0)) | S8: =IFERROR(INDEX('Chart of Accounts'!$C$5:$C$3000,MATCH(O8&"",'Chart of Accounts'!$A$5:$A$3000,0))&"|"&INDEX('Chart of Accounts'!$D$5:$D$3000,MATCH(O8&"",'Chart of Accounts'!$A$5:$A$3000,0)),"") | T8: =IFERROR(INDEX('Chart of Accounts'!$C$5:$C$3000,MATCH(Q8&"",'Chart of Accounts'!$A$5:$A$3000,0))&"|"&INDEX('Chart of Accounts'!$D$5:$D$3000,MATCH(Q8&"",'Chart of Accounts'!$A$5:$A$3000,0)),"") | U8: =IFERROR(INDEX('Chart of Accounts'!$C$5:$C$3000,MATCH(P8&"",'Chart of Accounts'!$A$5:$A$3000,0))&"|"&INDEX('Chart of Accounts'!$D$5:$D$3000,MATCH(P8&"",'Chart of Accounts'!$A$5:$A$3000,0)),"") | V8: =IFERROR(INDEX('Chart of Accounts'!$C$5:$C$3000,MATCH(R8&"",'Chart of Accounts'!$A$5:$A$3000,0))&"|"&INDEX('Chart of Accounts'!$D$5:$D$3000,MATCH(R8&"",'Chart of Accounts'!$A$5:$A$3000,0)),"") | W8: =IF(LEFT(S8,8)="Revenue|",-N(F8),0)+IF(LEFT(T8,8)="Revenue|",-N(J8),0)+IF(LEFT(U8,8)="Revenue|",N(N8),0)+IF(LEFT(V8,8)="Revenue|",N(M8),0) | X8: =IF(LEFT(S8,5)="COGS|",N(F8),0)+IF(LEFT(T8,5)="COGS|",N(J8),0)+IF(LEFT(U8,5)="COGS|",-N(N8),0)+IF(LEFT(V8,5)="COGS|",-N(M8),0) | Y8: =IF(LEFT(S8,8)="Expense|",N(F8),0)+IF(LEFT(T8,8)="Expense|",N(J8),0)+IF(LEFT(U8,8)="Expense|",-N(N8),0)+IF(LEFT(V8,8)="Expense|",-N(M8),0) | Z8: =IF(ISNUMBER(MATCH(S8,{"Expense|employee","Expense|general_admin","Expense|marketing","Expense|utilities","Expense|other_operating"},0)),N(F8),0)+IF(ISNUMBER(MATCH(T8,{"Expense|employee","Expense|general_admin","Expense|marketing","Expense|utilities","Expense|other_operating"},0)),N(J8),0)+IF(ISNUMBER(MATCH(U8,{"Expense|employee","Expense|general_admin","Expense|marketing","Expense|utilities","Expense|other_operating"},0)),-N(N8),0)+IF(ISNUMBER(MATCH(V8,{"Expense|employee","Expense|general_admin","Expense|marketing","Expense|utilities","Expense|other_operating"},0)),-N(M8),0) | AA8: =IF(S8="Liability|payable",-N(F8),0)+IF(T8="Liability|payable",-N(J8),0)+IF(U8="Liability|payable",N(N8),0)+IF(V8="Liability|payable",N(M8),0) | AB8: =IF(S8="Liability|accrued",-N(F8),0)+IF(T8="Liability|accrued",-N(J8),0)+IF(U8="Liability|accrued",N(N8),0)+IF(V8="Liability|accrued",N(M8),0) | AC8: =IF(AND(N(F8)<>0,S8=""),1,0)+IF(AND(N(J8)<>0,T8=""),1,0)+IF(AND(N(N8)<>0,U8=""),1,0)+IF(AND(N(M8)<>0,V8=""),1,0)
L9: =N(F9)+N(J9) | M9: =IF(K9="",0,L9-ROUND(L9/(1+IFERROR(VLOOKUP(K9,'Tax Codes'!$A$5:$E$300,5,FALSE),0)),2)) | N9: =L9-M9 | O9: =IF(H9="",INDEX('Chart of Accounts'!$A$5:$A$3000,MATCH("bank",'Chart of Accounts'!$F$5:$F$3000,0)),H9&"") | P9: =IF(I9="",INDEX('Chart of Accounts'!$A$5:$A$3000,MATCH("revenue",'Chart of Accounts'!$F$5:$F$3000,0)),I9&"") | Q9: =INDEX('Chart of Accounts'!$A$5:$A$3000,MATCH("wht_receivable",'Chart of Accounts'!$F$5:$F$3000,0)) | R9: =INDEX('Chart of Accounts'!$A$5:$A$3000,MATCH("vat_output",'Chart of Accounts'!$F$5:$F$3000,0)) | S9: =IFERROR(INDEX('Chart of Accounts'!$C$5:$C$3000,MATCH(O9&"",'Chart of Accounts'!$A$5:$A$3000,0))&"|"&INDEX('Chart of Accounts'!$D$5:$D$3000,MATCH(O9&"",'Chart of Accounts'!$A$5:$A$3000,0)),"") | T9: =IFERROR(INDEX('Chart of Accounts'!$C$5:$C$3000,MATCH(Q9&"",'Chart of Accounts'!$A$5:$A$3000,0))&"|"&INDEX('Chart of Accounts'!$D$5:$D$3000,MATCH(Q9&"",'Chart of Accounts'!$A$5:$A$3000,0)),"") | U9: =IFERROR(INDEX('Chart of Accounts'!$C$5:$C$3000,MATCH(P9&"",'Chart of Accounts'!$A$5:$A$3000,0))&"|"&INDEX('Chart of Accounts'!$D$5:$D$3000,MATCH(P9&"",'Chart of Accounts'!$A$5:$A$3000,0)),"") | V9: =IFERROR(INDEX('Chart of Accounts'!$C$5:$C$3000,MATCH(R9&"",'Chart of Accounts'!$A$5:$A$3000,0))&"|"&INDEX('Chart of Accounts'!$D$5:$D$3000,MATCH(R9&"",'Chart of Accounts'!$A$5:$A$3000,0)),"") | W9: =IF(LEFT(S9,8)="Revenue|",-N(F9),0)+IF(LEFT(T9,8)="Revenue|",-N(J9),0)+IF(LEFT(U9,8)="Revenue|",N(N9),0)+IF(LEFT(V9,8)="Revenue|",N(M9),0) | X9: =IF(LEFT(S9,5)="COGS|",N(F9),0)+IF(LEFT(T9,5)="COGS|",N(J9),0)+IF(LEFT(U9,5)="COGS|",-N(N9),0)+IF(LEFT(V9,5)="COGS|",-N(M9),0) | Y9: =IF(LEFT(S9,8)="Expense|",N(F9),0)+IF(LEFT(T9,8)="Expense|",N(J9),0)+IF(LEFT(U9,8)="Expense|",-N(N9),0)+IF(LEFT(V9,8)="Expense|",-N(M9),0) | Z9: =IF(ISNUMBER(MATCH(S9,{"Expense|employee","Expense|general_admin","Expense|marketing","Expense|utilities","Expense|other_operating"},0)),N(F9),0)+IF(ISNUMBER(MATCH(T9,{"Expense|employee","Expense|general_admin","Expense|marketing","Expense|utilities","Expense|other_operating"},0)),N(J9),0)+IF(ISNUMBER(MATCH(U9,{"Expense|employee","Expense|general_admin","Expense|marketing","Expense|utilities","Expense|other_operating"},0)),-N(N9),0)+IF(ISNUMBER(MATCH(V9,{"Expense|employee","Expense|general_admin","Expense|marketing","Expense|utilities","Expense|other_operating"},0)),-N(M9),0) | AA9: =IF(S9="Liability|payable",-N(F9),0)+IF(T9="Liability|payable",-N(J9),0)+IF(U9="Liability|payable",N(N9),0)+IF(V9="Liability|payable",N(M9),0) | AB9: =IF(S9="Liability|accrued",-N(F9),0)+IF(T9="Liability|accrued",-N(J9),0)+IF(U9="Liability|accrued",N(N9),0)+IF(V9="Liability|accrued",N(M9),0) | AC9: =IF(AND(N(F9)<>0,S9=""),1,0)+IF(AND(N(J9)<>0,T9=""),1,0)+IF(AND(N(N9)<>0,U9=""),1,0)+IF(AND(N(M9)<>0,V9=""),1,0)
L10: =N(F10)+N(J10) | M10: =IF(K10="",0,L10-ROUND(L10/(1+IFERROR(VLOOKUP(K10,'Tax Codes'!$A$5:$E$300,5,FALSE),0)),2)) | N10: =L10-M10 | O10: =IF(H10="",INDEX('Chart of Accounts'!$A$5:$A$3000,MATCH("bank",'Chart of Accounts'!$F$5:$F$3000,0)),H10&"") | P10: =IF(I10="",INDEX('Chart of Accounts'!$A$5:$A$3000,MATCH("revenue",'Chart of Accounts'!$F$5:$F$3000,0)),I10&"") | Q10: =INDEX('Chart of Accounts'!$A$5:$A$3000,MATCH("wht_receivable",'Chart of Accounts'!$F$5:$F$3000,0)) | R10: =INDEX('Chart of Accounts'!$A$5:$A$3000,MATCH("vat_output",'Chart of Accounts'!$F$5:$F$3000,0)) | S10: =IFERROR(INDEX('Chart of Accounts'!$C$5:$C$3000,MATCH(O10&"",'Chart of Accounts'!$A$5:$A$3000,0))&"|"&INDEX('Chart of Accounts'!$D$5:$D$3000,MATCH(O10&"",'Chart of Accounts'!$A$5:$A$3000,0)),"") | T10: =IFERROR(INDEX('Chart of Accounts'!$C$5:$C$3000,MATCH(Q10&"",'Chart of Accounts'!$A$5:$A$3000,0))&"|"&INDEX('Chart of Accounts'!$D$5:$D$3000,MATCH(Q10&"",'Chart of Accounts'!$A$5:$A$3000,0)),"") | U10: =IFERROR(INDEX('Chart of Accounts'!$C$5:$C$3000,MATCH(P10&"",'Chart of Accounts'!$A$5:$A$3000,0))&"|"&INDEX('Chart of Accounts'!$D$5:$D$3000,MATCH(P10&"",'Chart of Accounts'!$A$5:$A$3000,0)),"") | V10: =IFERROR(INDEX('Chart of Accounts'!$C$5:$C$3000,MATCH(R10&"",'Chart of Accounts'!$A$5:$A$3000,0))&"|"&INDEX('Chart of Accounts'!$D$5:$D$3000,MATCH(R10&"",'Chart of Accounts'!$A$5:$A$3000,0)),"") | W10: =IF(LEFT(S10,8)="Revenue|",-N(F10),0)+IF(LEFT(T10,8)="Revenue|",-N(J10),0)+IF(LEFT(U10,8)="Revenue|",N(N10),0)+IF(LEFT(V10,8)="Revenue|",N(M10),0) | X10: =IF(LEFT(S10,5)="COGS|",N(F10),0)+IF(LEFT(T10,5)="COGS|",N(J10),0)+IF(LEFT(U10,5)="COGS|",-N(N10),0)+IF(LEFT(V10,5)="COGS|",-N(M10),0) | Y10: =IF(LEFT(S10,8)="Expense|",N(F10),0)+IF(LEFT(T10,8)="Expense|",N(J10),0)+IF(LEFT(U10,8)="Expense|",-N(N10),0)+IF(LEFT(V10,8)="Expense|",-N(M10),0) | Z10: =IF(ISNUMBER(MATCH(S10,{"Expense|employee","Expense|general_admin","Expense|marketing","Expense|utilities","Expense|other_operating"},0)),N(F10),0)+IF(ISNUMBER(MATCH(T10,{"Expense|employee","Expense|general_admin","Expense|marketing","Expense|utilities","Expense|other_operating"},0)),N(J10),0)+IF(ISNUMBER(MATCH(U10,{"Expense|employee","Expense|general_admin","Expense|marketing","Expense|utilities","Expense|other_operating"},0)),-N(N10),0)+IF(ISNUMBER(MATCH(V10,{"Expense|employee","Expense|general_admin","Expense|marketing","Expense|utilities","Expense|other_operating"},0)),-N(M10),0) | AA10: =IF(S10="Liability|payable",-N(F10),0)+IF(T10="Liability|payable",-N(J10),0)+IF(U10="Liability|payable",N(N10),0)+IF(V10="Liability|payable",N(M10),0) | AB10: =IF(S10="Liability|accrued",-N(F10),0)+IF(T10="Liability|accrued",-N(J10),0)+IF(U10="Liability|accrued",N(N10),0)+IF(V10="Liability|accrued",N(M10),0) | AC10: =IF(AND(N(F10)<>0,S10=""),1,0)+IF(AND(N(J10)<>0,T10=""),1,0)+IF(AND(N(N10)<>0,U10=""),1,0)+IF(AND(N(M10)<>0,V10=""),1,0)
L11: =N(F11)+N(J11) | M11: =IF(K11="",0,L11-ROUND(L11/(1+IFERROR(VLOOKUP(K11,'Tax Codes'!$A$5:$E$300,5,FALSE),0)),2)) | N11: =L11-M11 | O11: =IF(H11="",INDEX('Chart of Accounts'!$A$5:$A$3000,MATCH("bank",'Chart of Accounts'!$F$5:$F$3000,0)),H11&"") | P11: =IF(I11="",INDEX('Chart of Accounts'!$A$5:$A$3000,MATCH("revenue",'Chart of Accounts'!$F$5:$F$3000,0)),I11&"") | Q11: =INDEX('Chart of Accounts'!$A$5:$A$3000,MATCH("wht_receivable",'Chart of Accounts'!$F$5:$F$3000,0)) | R11: =INDEX('Chart of Accounts'!$A$5:$A$3000,MATCH("vat_output",'Chart of Accounts'!$F$5:$F$3000,0)) | S11: =IFERROR(INDEX('Chart of Accounts'!$C$5:$C$3000,MATCH(O11&"",'Chart of Accounts'!$A$5:$A$3000,0))&"|"&INDEX('Chart of Accounts'!$D$5:$D$3000,MATCH(O11&"",'Chart of Accounts'!$A$5:$A$3000,0)),"") | T11: =IFERROR(INDEX('Chart of Accounts'!$C$5:$C$3000,MATCH(Q11&"",'Chart of Accounts'!$A$5:$A$3000,0))&"|"&INDEX('Chart of Accounts'!$D$5:$D$3000,MATCH(Q11&"",'Chart of Accounts'!$A$5:$A$3000,0)),"") | U11: =IFERROR(INDEX('Chart of Accounts'!$C$5:$C$3000,MATCH(P11&"",'Chart of Accounts'!$A$5:$A$3000,0))&"|"&INDEX('Chart of Accounts'!$D$5:$D$3000,MATCH(P11&"",'Chart of Accounts'!$A$5:$A$3000,0)),"") | V11: =IFERROR(INDEX('Chart of Accounts'!$C$5:$C$3000,MATCH(R11&"",'Chart of Accounts'!$A$5:$A$3000,0))&"|"&INDEX('Chart of Accounts'!$D$5:$D$3000,MATCH(R11&"",'Chart of Accounts'!$A$5:$A$3000,0)),"") | W11: =IF(LEFT(S11,8)="Revenue|",-N(F11),0)+IF(LEFT(T11,8)="Revenue|",-N(J11),0)+IF(LEFT(U11,8)="Revenue|",N(N11),0)+IF(LEFT(V11,8)="Revenue|",N(M11),0) | X11: =IF(LEFT(S11,5)="COGS|",N(F11),0)+IF(LEFT(T11,5)="COGS|",N(J11),0)+IF(LEFT(U11,5)="COGS|",-N(N11),0)+IF(LEFT(V11,5)="COGS|",-N(M11),0) | Y11: =IF(LEFT(S11,8)="Expense|",N(F11),0)+IF(LEFT(T11,8)="Expense|",N(J11),0)+IF(LEFT(U11,8)="Expense|",-N(N11),0)+IF(LEFT(V11,8)="Expense|",-N(M11),0) | Z11: =IF(ISNUMBER(MATCH(S11,{"Expense|employee","Expense|general_admin","Expense|marketing","Expense|utilities","Expense|other_operating"},0)),N(F11),0)+IF(ISNUMBER(MATCH(T11,{"Expense|employee","Expense|general_admin","Expense|marketing","Expense|utilities","Expense|other_operating"},0)),N(J11),0)+IF(ISNUMBER(MATCH(U11,{"Expense|employee","Expense|general_admin","Expense|marketing","Expense|utilities","Expense|other_operating"},0)),-N(N11),0)+IF(ISNUMBER(MATCH(V11,{"Expense|employee","Expense|general_admin","Expense|marketing","Expense|utilities","Expense|other_operating"},0)),-N(M11),0) | AA11: =IF(S11="Liability|payable",-N(F11),0)+IF(T11="Liability|payable",-N(J11),0)+IF(U11="Liability|payable",N(N11),0)+IF(V11="Liability|payable",N(M11),0) | AB11: =IF(S11="Liability|accrued",-N(F11),0)+IF(T11="Liability|accrued",-N(J11),0)+IF(U11="Liability|accrued",N(N11),0)+IF(V11="Liability|accrued",N(M11),0) | AC11: =IF(AND(N(F11)<>0,S11=""),1,0)+IF(AND(N(J11)<>0,T11=""),1,0)+IF(AND(N(N11)<>0,U11=""),1,0)+IF(AND(N(M11)<>0,V11=""),1,0)
L12: =N(F12)+N(J12) | M12: =IF(K12="",0,L12-ROUND(L12/(1+IFERROR(VLOOKUP(K12,'Tax Codes'!$A$5:$E$300,5,FALSE),0)),2)) | N12: =L12-M12 | O12: =IF(H12="",INDEX('Chart of Accounts'!$A$5:$A$3000,MATCH("bank",'Chart of Accounts'!$F$5:$F$3000,0)),H12&"") | P12: =IF(I12="",INDEX('Chart of Accounts'!$A$5:$A$3000,MATCH("revenue",'Chart of Accounts'!$F$5:$F$3000,0)),I12&"") | Q12: =INDEX('Chart of Accounts'!$A$5:$A$3000,MATCH("wht_receivable",'Chart of Accounts'!$F$5:$F$3000,0)) | R12: =INDEX('Chart of Accounts'!$A$5:$A$3000,MATCH("vat_output",'Chart of Accounts'!$F$5:$F$3000,0)) | S12: =IFERROR(INDEX('Chart of Accounts'!$C$5:$C$3000,MATCH(O12&"",'Chart of Accounts'!$A$5:$A$3000,0))&"|"&INDEX('Chart of Accounts'!$D$5:$D$3000,MATCH(O12&"",'Chart of Accounts'!$A$5:$A$3000,0)),"") | T12: =IFERROR(INDEX('Chart of Accounts'!$C$5:$C$3000,MATCH(Q12&"",'Chart of Accounts'!$A$5:$A$3000,0))&"|"&INDEX('Chart of Accounts'!$D$5:$D$3000,MATCH(Q12&"",'Chart of Accounts'!$A$5:$A$3000,0)),"") | U12: =IFERROR(INDEX('Chart of Accounts'!$C$5:$C$3000,MATCH(P12&"",'Chart of Accounts'!$A$5:$A$3000,0))&"|"&INDEX('Chart of Accounts'!$D$5:$D$3000,MATCH(P12&"",'Chart of Accounts'!$A$5:$A$3000,0)),"") | V12: =IFERROR(INDEX('Chart of Accounts'!$C$5:$C$3000,MATCH(R12&"",'Chart of Accounts'!$A$5:$A$3000,0))&"|"&INDEX('Chart of Accounts'!$D$5:$D$3000,MATCH(R12&"",'Chart of Accounts'!$A$5:$A$3000,0)),"") | W12: =IF(LEFT(S12,8)="Revenue|",-N(F12),0)+IF(LEFT(T12,8)="Revenue|",-N(J12),0)+IF(LEFT(U12,8)="Revenue|",N(N12),0)+IF(LEFT(V12,8)="Revenue|",N(M12),0) | X12: =IF(LEFT(S12,5)="COGS|",N(F12),0)+IF(LEFT(T12,5)="COGS|",N(J12),0)+IF(LEFT(U12,5)="COGS|",-N(N12),0)+IF(LEFT(V12,5)="COGS|",-N(M12),0) | Y12: =IF(LEFT(S12,8)="Expense|",N(F12),0)+IF(LEFT(T12,8)="Expense|",N(J12),0)+IF(LEFT(U12,8)="Expense|",-N(N12),0)+IF(LEFT(V12,8)="Expense|",-N(M12),0) | Z12: =IF(ISNUMBER(MATCH(S12,{"Expense|employee","Expense|general_admin","Expense|marketing","Expense|utilities","Expense|other_operating"},0)),N(F12),0)+IF(ISNUMBER(MATCH(T12,{"Expense|employee","Expense|general_admin","Expense|marketing","Expense|utilities","Expense|other_operating"},0)),N(J12),0)+IF(ISNUMBER(MATCH(U12,{"Expense|employee","Expense|general_admin","Expense|marketing","Expense|utilities","Expense|other_operating"},0)),-N(N12),0)+IF(ISNUMBER(MATCH(V12,{"Expense|employee","Expense|general_admin","Expense|marketing","Expense|utilities","Expense|other_operating"},0)),-N(M12),0) | AA12: =IF(S12="Liability|payable",-N(F12),0)+IF(T12="Liability|payable",-N(J12),0)+IF(U12="Liability|payable",N(N12),0)+IF(V12="Liability|payable",N(M12),0) | AB12: =IF(S12="Liability|accrued",-N(F12),0)+IF(T12="Liability|accrued",-N(J12),0)+IF(U12="Liability|accrued",N(N12),0)+IF(V12="Liability|accrued",N(M12),0) | AC12: =IF(AND(N(F12)<>0,S12=""),1,0)+IF(AND(N(J12)<>0,T12=""),1,0)+IF(AND(N(N12)<>0,U12=""),1,0)+IF(AND(N(M12)<>0,V12=""),1,0)
